Workbook

Sheet Start_Here
A1: Demand & Inventory Planning Model (Excel V1: learning and validation prototype)
A2: Methodological source of truth for the later Python / Streamlit application. All data synthetic. No macros.
A4: Business question: Given what we expect customers to buy, the inventory we currently have, inventory already on order, supplier lead times and basic replenishment economics, which products need attention, when should we reorder them, and approximately how much should we order?
A6: PLANNING CHAIN
A7: Historical Sales -> Simple Forecast -> WAPE / Bias -> Historical Forecast Error -> Safety Stock -> Lead-Time Demand -> Reorder Point -> Inventory Position -> Reorder Decision -> Economic Order Quantity -> Recommended Order -> 12-Week Inventory Projection -> Stockout / Reorder / Excess / Healthy Status -> Simple Historical Backtest
A9: SHEET MAP (in study order)
A10: Study step | B10: Sheet | C10: What it does | D10: What to focus on
A11: 1 | B11: Formula_Guide | C11: Definitions, formulas, examples and limitations for every concept. | D11: Read once before touching numbers.
A12: 2 | B12: Inputs | C12: Global parameters, suppliers (lead time, ordering cost), SKU master and current inventory. | D12: Which cells are inputs (blue on yellow); the fixed snapshot date.
A13: 3 | B13: Demand_History | C13: Tidy table: Week, date, SKU, actual demand (48 SKUs x 104 weeks). | D13: Scroll one SKU; spot stable, variable, growing, declining patterns.
A14: 4 | B14: Forecast_Walkforward | C14: Row per SKU-week: the four walk-forward forecasts, errors (F-A) and absolute errors. | D14: Click a MA4 or SES cell: it only references earlier rows.
A15: 5 | B15: Forecast | C15: Per SKU: WAPE, Bias, Error SD and next-week forecast of each method; selection rule. | D15: Selected method, current forecast, the tolerance logic (MATCH TRUE).
A16: 6 | B16: Replenishment_Plan | C16: Core table: SS, LTD, ROP, IP, weeks of cover, EOQ, trigger, recommended order, status, reason. | D16: Read one row left to right; ROP = when, EOQ = how much.
A17: 7 | B17: Projection | C17: 12-week closing inventory per SKU with existing PO and new order receipts. | D17: Timing of receipts; the zero-within-lead-time flag.
A18: 8 | B18: SKU_Deep_Dive | C18: HERO SHEET: pick a SKU and follow every step with formula, numbers, result and interpretation. | D18: Explain one SKU out loud from history to projected inventory.
A19: 9 | B19: Planner_Overview | C19: KPIs, status summary, two charts and the ranked attention list. | D19: How a planner would start the week.
A20: 10 | B20: Backtest | C20: 16-week replay: 4-week baseline vs forecast + SS + ROP + EOQ, lost sales, no look-ahead. | D20: The trade-off between fill rate, orders and inventory value.
A21: 11 | B21: Validation | C21: Textbook examples plus four SKUs and the backtest recomputed independently in Python: PASS/FAIL. | D21: Confirms the Excel logic before porting it to Python.
A23: CELL LEGEND
A24: Input | B24: Blue text on light yellow: values you may change (Inputs sheet, SKU selectors).
A25: Formula | B25: Black text: calculated. Do not overwrite.
A26: Link | B26: Green text: value pulled from another sheet.
A27: Status shading | B27: Dark grey = STOCKOUT RISK, mid grey = REORDER REQUIRED, light grey = EXCESS STOCK. Status is always written as text too (grayscale-printable).
A29: KEY SIMPLIFICATIONS (V1)
A30: - Fixed supplier lead times; lead-time variability out of scope.
A31: - Flat forecasts (no trend or seasonality); growing items tend to be under-forecast and declining items over-forecast.
A32: - Safety stock = z x Error SD x SQRT(LT): errors assumed roughly normal and independent week to week; the weekly review period is not added to the lead time.
A33: - EOQ ignores quantity discounts, supplier minimums and capacity; one EOQ per weekly review.
A34: - One open PO per SKU at the snapshot; projection is deterministic and includes only today's recommended order.
A35: - Backtest: lost sales, parameters calibrated before the replay, one synthetic scenario; results show trade-offs, not proof.

Sheet Inputs
A1: Inputs: global parameters, suppliers, SKU master and current inventory
A2: Fictitious company: Hearthline Home Online GmbH (home & living e-commerce). One central warehouse. All data synthetic.
A4: Legend: | B4: Blue text on yellow = input you may change | C4: Black text = formula (do not overwrite) | D4: Green text = link pulled from another sheet
A6: GLOBAL PLANNING PARAMETERS
A7: Parameter | B7: Value | C7: Unit | D7: Note
A8: Company | B8: Hearthline Home Online GmbH | C8: text | D8: Fictitious retailer used for the scenario.
A9: Warehouse | B9: DC-01 Central Warehouse | C9: text | D9: Single stocking location (multi-echelon is out of scope).
A10: Model snapshot date | B10: 46202 | C10: date | D10: Fixed planning date = start of planning week 105. TODAY() is deliberately NOT used.
A11: Target service level | B11: 0.95 | C11: % | D11: Probability of not stocking out during lead time (cycle service level). Default 95%.
A12: z-value | B12: =_xlfn.NORM.S.INV(TSL) -> 1.6448536 | C12: number | D12: Formula NORM.S.INV(Target service level). 95% gives about 1.645.
A13: Annual holding rate | B13: 0.2 | C13: % of unit cost / year | D13: Cost of holding one unit for a year as % of its cost (capital, storage, obsolescence).
A14: Weeks per year | B14: 52 | C14: weeks | D14: Used to annualise weekly forecast for EOQ.
A15: Excess-stock threshold | B15: 12 | C15: weeks of cover | D15: Inventory position above this many weeks of forecast demand is flagged EXCESS STOCK.
A16: SES smoothing alpha | B16: 0.3 | C16: 0-1 | D16: Weight on the most recent actual in Simple Exponential Smoothing.
A17: WAPE tie tolerance | B17: 0.01 | C17: WAPE points | D17: If a simpler method is within this WAPE of the best one, the simpler method is selected. 0.01 = 1.0 percentage point.
A18: Forecast evaluation window | B18: 52 | C18: weeks | D18: Number of most recent weeks used for WAPE, Bias and Error SD (allowed 13-52).
A19: History length | B19: 104 | C19: weeks | D19: Structural: 104 weeks per SKU in Demand_History. Do not change without rebuilding.
A20: Evaluation start week | B20: =Weeks_History-Eval_Weeks+1 -> 53 | C20: week # | D20: First week of the evaluation window for live planning.
A21: Backtest length | B21: 16 | C21: weeks | D21: Structural: the Backtest sheet replays the final 16 weeks. Do not change without rebuilding.
A22: Backtest start week | B22: =Weeks_History-BT_Weeks+1 -> 89 | C22: week # | D22: First replayed week.
A23: Backtest calibration start week | B23: =BT_Start_Week-Eval_Weeks -> 37 | C23: week # | D23: Method choice and Error SD for the backtest are estimated only on weeks BEFORE the backtest (no look-ahead).
A24: Backtest calibration end week | B24: =BT_Start_Week-1 -> 88 | C24: week # | D24: Last week of the calibration window.
A25: Baseline policy: weeks of stock | B25: 4 | C25: weeks | D25: Policy A orders up to this many weeks of the trailing 4-week average demand.
A26: Backtest opening stock | B26: 6 | C26: weeks | D26: Both policies start the replay with this many weeks of the trailing 8-week average demand on hand, nothing on order.
A27: Projection horizon | B27: 12 | C27: weeks | D27: Structural: forward projection length on the Projection sheet.
A29: SUPPLIERS (fixed lead times; lead-time variability is out of scope)
A30: Supplier ID | B30: Supplier Name | C30: Lead Time (weeks) | D30: Ordering Cost per Order (€)
A31: SUP-01 | B31: Rhein-Main Kitchenware GmbH | C31: 2 | D31: 40
A32: SUP-02 | B32: Alpina Bath & Textile AG | C32: 3 | D32: 45
A33: SUP-03 | B33: Baltic Linen Works UAB | C33: 4 | D33: 55
A34: SUP-04 | B34: Pearl River Electrics Ltd | C34: 6 | D34: 90
A35: SUP-05 | B35: CleanCare Distribution BV | C35: 1 | D35: 35
A38: SKU MASTER AND CURRENT INVENTORY AT SNAPSHOT DATE
A39: SKU # | B39: SKU | C39: Product Name | D39: Category | E39: Supplier ID | F39: Supplier Lead Time (weeks) | G39: Ordering Cost per Order (€) | H39: Unit Cost (€) | I39: Case Pack (units) | J39: Current On Hand (units) | K39: On Order (open PO units) | L39: Open PO Due Week (1 = week starting snapshot) | M39: Backorders (units) | N39: Synthetic Demand Pattern (info only)
A40: 1 | B40: KIT-001 | C40: Chef's Knife 20cm | D40: Kitchen | E40: SUP-01 | F40: =INDEX(Inputs!$C$31:$C$35,MATCH(E40,Inputs!$A$31:$A$35,0)) -> 2 | G40: =INDEX(Inputs!$D$31:$D$35,MATCH(E40,Inputs!$A$31:$A$35,0)) -> 40 | H40: 18 | I40: 6 | J40: 236 | K40: 0 | M40: 0 | N40: stable
A41: 2 | B41: KIT-002 | C41: Non-Stick Frying Pan 28cm | D41: Kitchen | E41: SUP-01 | F41: =INDEX(Inputs!$C$31:$C$35,MATCH(E41,Inputs!$A$31:$A$35,0)) -> 2 | G41: =INDEX(Inputs!$D$31:$D$35,MATCH(E41,Inputs!$A$31:$A$35,0)) -> 40 | H41: 22 | I41: 4 | J41: 6 | K41: 92 | L41: 1 | M41: 0 | N41: variable
A42: 3 | B42: KIT-003 | C42: Glass Food Storage Set 5pc | D42: Kitchen | E42: SUP-01 | F42: =INDEX(Inputs!$C$31:$C$35,MATCH(E42,Inputs!$A$31:$A$35,0)) -> 2 | G42: =INDEX(Inputs!$D$31:$D$35,MATCH(E42,Inputs!$A$31:$A$35,0)) -> 40 | H42: 15 | I42: 6 | J42: 0 | K42: 0 | M42: 36 | N42: growing
A43: 4 | B43: KIT-004 | C43: Bamboo Cutting Board | D43: Kitchen | E43: SUP-01 | F43: =INDEX(Inputs!$C$31:$C$35,MATCH(E43,Inputs!$A$31:$A$35,0)) -> 2 | G43: =INDEX(Inputs!$D$31:$D$35,MATCH(E43,Inputs!$A$31:$A$35,0)) -> 40 | H43: 9 | I43: 12 | J43: 270 | K43: 0 | M43: 0 | N43: stable
A44: 5 | B44: KIT-005 | C44: Stainless Saucepan 2L | D44: Kitchen | E44: SUP-01 | F44: =INDEX(Inputs!$C$31:$C$35,MATCH(E44,Inputs!$A$31:$A$35,0)) -> 2 | G44: =INDEX(Inputs!$D$31:$D$35,MATCH(E44,Inputs!$A$31:$A$35,0)) -> 40 | H44: 28 | I44: 4 | J44: 334 | K44: 0 | M44: 0 | N44: declining
A45: 6 | B45: KIT-006 | C45: Silicone Utensil Set | D45: Kitchen | E45: SUP-01 | F45: =INDEX(Inputs!$C$31:$C$35,MATCH(E45,Inputs!$A$31:$A$35,0)) -> 2 | G45: =INDEX(Inputs!$D$31:$D$35,MATCH(E45,Inputs!$A$31:$A$35,0)) -> 40 | H45: 12 | I45: 10 | J45: 378 | K45: 0 | M45: 0 | N45: variable
A46: 7 | B46: KIT-007 | C46: Cast Iron Casserole 5L | D46: Kitchen | E46: SUP-01 | F46: =INDEX(Inputs!$C$31:$C$35,MATCH(E46,Inputs!$A$31:$A$35,0)) -> 2 | G46: =INDEX(Inputs!$D$31:$D$35,MATCH(E46,Inputs!$A$31:$A$35,0)) -> 40 | H46: 85 | I46: 1 | J46: 21 | K46: 0 | M46: 0 | N46: low
A47: 8 | B47: KIT-008 | C47: Espresso Cup Set 6pc | D47: Kitchen | E47: SUP-01 | F47: =INDEX(Inputs!$C$31:$C$35,MATCH(E47,Inputs!$A$31:$A$35,0)) -> 2 | G47: =INDEX(Inputs!$D$31:$D$35,MATCH(E47,Inputs!$A$31:$A$35,0)) -> 40 | H47: 19 | I47: 6 | J47: 766 | K47: 0 | M47: 0 | N47: stable
A48: 9 | B48: KIT-009 | C48: Digital Kitchen Scale | D48: Kitchen | E48: SUP-01 | F48: =INDEX(Inputs!$C$31:$C$35,MATCH(E48,Inputs!$A$31:$A$35,0)) -> 2 | G48: =INDEX(Inputs!$D$31:$D$35,MATCH(E48,Inputs!$A$31:$A$35,0)) -> 40 | H48: 24 | I48: 5 | J48: 80 | K48: 0 | M48: 0 | N48: growing
A49: 10 | B49: KIT-010 | C49: Measuring Jug 1L | D49: Kitchen | E49: SUP-01 | F49: =INDEX(Inputs!$C$31:$C$35,MATCH(E49,Inputs!$A$31:$A$35,0)) -> 2 | G49: =INDEX(Inputs!$D$31:$D$35,MATCH(E49,Inputs!$A$31:$A$35,0)) -> 40 | H49: 6 | I49: 24 | J49: 304 | K49: 0 | M49: 0 | N49: stable
A50: 11 | B50: BTH-001 | C50: Bath Towel 70x140 Grey | D50: Bathroom | E50: SUP-02 | F50: =INDEX(Inputs!$C$31:$C$35,MATCH(E50,Inputs!$A$31:$A$35,0)) -> 3 | G50: =INDEX(Inputs!$D$31:$D$35,MATCH(E50,Inputs!$A$31:$A$35,0)) -> 45 | H50: 11 | I50: 10 | J50: 486 | K50: 0 | M50: 0 | N50: stable
A51: 12 | B51: BTH-002 | C51: Hand Towel 50x100 White | D51: Bathroom | E51: SUP-02 | F51: =INDEX(Inputs!$C$31:$C$35,MATCH(E51,Inputs!$A$31:$A$35,0)) -> 3 | G51: =INDEX(Inputs!$D$31:$D$35,MATCH(E51,Inputs!$A$31:$A$35,0)) -> 45 | H51: 6 | I51: 20 | J51: 75 | K51: 380 | L51: 1 | M51: 0 | N51: stable
A52: 13 | B52: BTH-003 | C52: Cotton Bath Mat | D52: Bathroom | E52: SUP-02 | F52: =INDEX(Inputs!$C$31:$C$35,MATCH(E52,Inputs!$A$31:$A$35,0)) -> 3 | G52: =INDEX(Inputs!$D$31:$D$35,MATCH(E52,Inputs!$A$31:$A$35,0)) -> 45 | H52: 14 | I52: 8 | J52: 250 | K52: 0 | M52: 0 | N52: variable
A53: 14 | B53: BTH-004 | C53: Waterproof Shower Curtain | D53: Bathroom | E53: SUP-02 | F53: =INDEX(Inputs!$C$31:$C$35,MATCH(E53,Inputs!$A$31:$A$35,0)) -> 3 | G53: =INDEX(Inputs!$D$31:$D$35,MATCH(E53,Inputs!$A$31:$A$35,0)) -> 45 | H53: 16 | I53: 10 | J53: 443 | K53: 0 | M53: 0 | N53: declining
A54: 15 | B54: BTH-005 | C54: Waffle Bathrobe M | D54: Bathroom | E54: SUP-02 | F54: =INDEX(Inputs!$C$31:$C$35,MATCH(E54,Inputs!$A$31:$A$35,0)) -> 3 | G54: =INDEX(Inputs!$D$31:$D$35,MATCH(E54,Inputs!$A$31:$A$35,0)) -> 45 | H54: 32 | I54: 5 | J54: 19 | K54: 25 | L54: 2 | M54: 0 | N54: variable
A55: 16 | B55: BTH-006 | C55: Ceramic Toothbrush Holder | D55: Bathroom | E55: SUP-02 | F55: =INDEX(Inputs!$C$31:$C$35,MATCH(E55,Inputs!$A$31:$A$35,0)) -> 3 | G55: =INDEX(Inputs!$D$31:$D$35,MATCH(E55,Inputs!$A$31:$A$35,0)) -> 45 | H55: 16 | I55: 12 | J55: 164 | K55: 0 | M55: 0 | N55: stable
A56: 17 | B56: BTH-007 | C56: Glass Soap Dispenser | D56: Bathroom | E56: SUP-02 | F56: =INDEX(Inputs!$C$31:$C$35,MATCH(E56,Inputs!$A$31:$A$35,0)) -> 3 | G56: =INDEX(Inputs!$D$31:$D$35,MATCH(E56,Inputs!$A$31:$A$35,0)) -> 45 | H56: 12 | I56: 12 | J56: 416 | K56: 0 | M56: 0 | N56: growing
A57: 18 | B57: BTH-008 | C57: Chrome Towel Rail | D57: Bathroom | E57: SUP-02 | F57: =INDEX(Inputs!$C$31:$C$35,MATCH(E57,Inputs!$A$31:$A$35,0)) -> 3 | G57: =INDEX(Inputs!$D$31:$D$35,MATCH(E57,Inputs!$A$31:$A$35,0)) -> 45 | H57: 95 | I57: 1 | J57: 126 | K57: 0 | M57: 0 | N57: low
A58: 19 | B58: BTH-009 | C58: Woven Laundry Basket | D58: Bathroom | E58: SUP-02 | F58: =INDEX(Inputs!$C$31:$C$35,MATCH(E58,Inputs!$A$31:$A$35,0)) -> 3 | G58: =INDEX(Inputs!$D$31:$D$35,MATCH(E58,Inputs!$A$31:$A$35,0)) -> 45 | H58: 21 | I58: 4 | J58: 100 | K58: 0 | M58: 0 | N58: variable
A59: 20 | B59: BTH-010 | C59: Microfibre Hair Towel | D59: Bathroom | E59: SUP-02 | F59: =INDEX(Inputs!$C$31:$C$35,MATCH(E59,Inputs!$A$31:$A$35,0)) -> 3 | G59: =INDEX(Inputs!$D$31:$D$35,MATCH(E59,Inputs!$A$31:$A$35,0)) -> 45 | H59: 9 | I59: 20 | J59: 81 | K59: 100 | L59: 3 | M59: 0 | N59: growing
A60: 21 | B60: BED-001 | C60: All-Season Duvet 135x200 | D60: Bedding | E60: SUP-03 | F60: =INDEX(Inputs!$C$31:$C$35,MATCH(E60,Inputs!$A$31:$A$35,0)) -> 4 | G60: =INDEX(Inputs!$D$31:$D$35,MATCH(E60,Inputs!$A$31:$A$35,0)) -> 55 | H60: 45 | I60: 4 | J60: 116 | K60: 156 | L60: 1 | M60: 0 | N60: stable
A61: 22 | B61: BED-002 | C61: Pillow 80x80 Medium | D61: Bedding | E61: SUP-03 | F61: =INDEX(Inputs!$C$31:$C$35,MATCH(E61,Inputs!$A$31:$A$35,0)) -> 4 | G61: =INDEX(Inputs!$D$31:$D$35,MATCH(E61,Inputs!$A$31:$A$35,0)) -> 55 | H61: 14 | I61: 8 | J61: 350 | K61: 408 | L61: 1 | M61: 0 | N61: stable
A62: 23 | B62: BED-003 | C62: Cotton Bed Linen Set Grey | D62: Bedding | E62: SUP-03 | F62: =INDEX(Inputs!$C$31:$C$35,MATCH(E62,Inputs!$A$31:$A$35,0)) -> 4 | G62: =INDEX(Inputs!$D$31:$D$35,MATCH(E62,Inputs!$A$31:$A$35,0)) -> 55 | H62: 38 | I62: 5 | J62: 138 | K62: 105 | L62: 1 | M62: 0 | N62: variable
A63: 24 | B63: BED-004 | C63: Fitted Sheet 180x200 | D63: Bedding | E63: SUP-03 | F63: =INDEX(Inputs!$C$31:$C$35,MATCH(E63,Inputs!$A$31:$A$35,0)) -> 4 | G63: =INDEX(Inputs!$D$31:$D$35,MATCH(E63,Inputs!$A$31:$A$35,0)) -> 55 | H63: 19 | I63: 10 | J63: 0 | K63: 0 | M63: 35 | N63: growing
A64: 25 | B64: BED-005 | C64: Weighted Blanket 7kg | D64: Bedding | E64: SUP-03 | F64: =INDEX(Inputs!$C$31:$C$35,MATCH(E64,Inputs!$A$31:$A$35,0)) -> 4 | G64: =INDEX(Inputs!$D$31:$D$35,MATCH(E64,Inputs!$A$31:$A$35,0)) -> 55 | H64: 65 | I64: 2 | J64: 253 | K64: 0 | M64: 0 | N64: declining
A65: 26 | B65: BED-006 | C65: Mattress Protector 160x200 | D65: Bedding | E65: SUP-03 | F65: =INDEX(Inputs!$C$31:$C$35,MATCH(E65,Inputs!$A$31:$A$35,0)) -> 4 | G65: =INDEX(Inputs!$D$31:$D$35,MATCH(E65,Inputs!$A$31:$A$35,0)) -> 55 | H65: 29 | I65: 6 | J65: 74 | K65: 180 | L65: 2 | M65: 0 | N65: stable
A66: 27 | B66: BED-007 | C66: Linen Throw Blanket | D66: Bedding | E66: SUP-03 | F66: =INDEX(Inputs!$C$31:$C$35,MATCH(E66,Inputs!$A$31:$A$35,0)) -> 4 | G66: =INDEX(Inputs!$D$31:$D$35,MATCH(E66,Inputs!$A$31:$A$35,0)) -> 55 | H66: 34 | I66: 5 | J66: 84 | K66: 160 | L66: 3 | M66: 0 | N66: variable
A67: 28 | B67: BED-008 | C67: Silk Pillowcase | D67: Bedding | E67: SUP-03 | F67: =INDEX(Inputs!$C$31:$C$35,MATCH(E67,Inputs!$A$31:$A$35,0)) -> 4 | G67: =INDEX(Inputs!$D$31:$D$35,MATCH(E67,Inputs!$A$31:$A$35,0)) -> 55 | H67: 72 | I67: 2 | J67: 35 | K67: 0 | M67: 0 | N67: low
A68: 29 | B68: BED-009 | C68: Kids Bedding Set Stars | D68: Bedding | E68: SUP-03 | F68: =INDEX(Inputs!$C$31:$C$35,MATCH(E68,Inputs!$A$31:$A$35,0)) -> 4 | G68: =INDEX(Inputs!$D$31:$D$35,MATCH(E68,Inputs!$A$31:$A$35,0)) -> 55 | H68: 30 | I68: 4 | J68: 119 | K68: 0 | M68: 0 | N68: declining
A69: 30 | B69: ELE-001 | C69: Dimmable LED Desk Lamp | D69: Small Electrics | E69: SUP-04 | F69: =INDEX(Inputs!$C$31:$C$35,MATCH(E69,Inputs!$A$31:$A$35,0)) -> 6 | G69: =INDEX(Inputs!$D$31:$D$35,MATCH(E69,Inputs!$A$31:$A$35,0)) -> 90 | H69: 27 | I69: 6 | J69: 375 | K69: 0 | M69: 0 | N69: stable
A70: 31 | B70: ELE-002 | C70: Electric Kettle 1.7L | D70: Small Electrics | E70: SUP-04 | F70: =INDEX(Inputs!$C$31:$C$35,MATCH(E70,Inputs!$A$31:$A$35,0)) -> 6 | G70: =INDEX(Inputs!$D$31:$D$35,MATCH(E70,Inputs!$A$31:$A$35,0)) -> 90 | H70: 31 | I70: 4 | J70: 106 | K70: 120 | L70: 2 | M70: 0 | N70: variable
A71: 32 | B71: ELE-003 | C71: Hand Blender 800W | D71: Small Electrics | E71: SUP-04 | F71: =INDEX(Inputs!$C$31:$C$35,MATCH(E71,Inputs!$A$31:$A$35,0)) -> 6 | G71: =INDEX(Inputs!$D$31:$D$35,MATCH(E71,Inputs!$A$31:$A$35,0)) -> 90 | H71: 36 | I71: 4 | J71: 58 | K71: 276 | L71: 6 | M71: 0 | N71: growing
A72: 33 | B72: ELE-004 | C72: Smart Plug 2-Pack | D72: Small Electrics | E72: SUP-04 | F72: =INDEX(Inputs!$C$31:$C$35,MATCH(E72,Inputs!$A$31:$A$35,0)) -> 6 | G72: =INDEX(Inputs!$D$31:$D$35,MATCH(E72,Inputs!$A$31:$A$35,0)) -> 90 | H72: 14 | I72: 10 | J72: 1060 | K72: 0 | M72: 0 | N72: growing
A73: 34 | B73: ELE-005 | C73: Mini Bluetooth Speaker | D73: Small Electrics | E73: SUP-04 | F73: =INDEX(Inputs!$C$31:$C$35,MATCH(E73,Inputs!$A$31:$A$35,0)) -> 6 | G73: =INDEX(Inputs!$D$31:$D$35,MATCH(E73,Inputs!$A$31:$A$35,0)) -> 90 | H73: 23 | I73: 6 | J73: 569 | K73: 0 | M73: 0 | N73: declining
A74: 35 | B74: ELE-006 | C74: USB-C Charging Hub | D74: Small Electrics | E74: SUP-04 | F74: =INDEX(Inputs!$C$31:$C$35,MATCH(E74,Inputs!$A$31:$A$35,0)) -> 6 | G74: =INDEX(Inputs!$D$31:$D$35,MATCH(E74,Inputs!$A$31:$A$35,0)) -> 90 | H74: 17 | I74: 10 | J74: 687 | K74: 0 | M74: 0 | N74: stable
A75: 36 | B75: ELE-007 | C75: Compact Air Purifier | D75: Small Electrics | E75: SUP-04 | F75: =INDEX(Inputs!$C$31:$C$35,MATCH(E75,Inputs!$A$31:$A$35,0)) -> 6 | G75: =INDEX(Inputs!$D$31:$D$35,MATCH(E75,Inputs!$A$31:$A$35,0)) -> 90 | H75: 120 | I75: 1 | J75: 120 | K75: 0 | M75: 0 | N75: low
A76: 37 | B76: ELE-008 | C76: Burr Coffee Grinder | D76: Small Electrics | E76: SUP-04 | F76: =INDEX(Inputs!$C$31:$C$35,MATCH(E76,Inputs!$A$31:$A$35,0)) -> 6 | G76: =INDEX(Inputs!$D$31:$D$35,MATCH(E76,Inputs!$A$31:$A$35,0)) -> 90 | H76: 48 | I76: 2 | J76: 29 | K76: 126 | L76: 2 | M76: 0 | N76: variable
A77: 38 | B77: CLN-001 | C77: Dishwasher Tabs 60pc | D77: Cleaning & Care | E77: SUP-05 | F77: =INDEX(Inputs!$C$31:$C$35,MATCH(E77,Inputs!$A$31:$A$35,0)) -> 1 | G77: =INDEX(Inputs!$D$31:$D$35,MATCH(E77,Inputs!$A$31:$A$35,0)) -> 35 | H77: 7 | I77: 12 | J77: 666 | K77: 0 | M77: 0 | N77: stable
A78: 39 | B78: CLN-002 | C78: Microfibre Cloths 10-Pack | D78: Cleaning & Care | E78: SUP-05 | F78: =INDEX(Inputs!$C$31:$C$35,MATCH(E78,Inputs!$A$31:$A$35,0)) -> 1 | G78: =INDEX(Inputs!$D$31:$D$35,MATCH(E78,Inputs!$A$31:$A$35,0)) -> 35 | H78: 5 | I78: 20 | J78: 180 | K78: 0 | M78: 0 | N78: stable
A79: 40 | B79: CLN-003 | C79: Eco Laundry Detergent 2L | D79: Cleaning & Care | E79: SUP-05 | F79: =INDEX(Inputs!$C$31:$C$35,MATCH(E79,Inputs!$A$31:$A$35,0)) -> 1 | G79: =INDEX(Inputs!$D$31:$D$35,MATCH(E79,Inputs!$A$31:$A$35,0)) -> 35 | H79: 9 | I79: 6 | J79: 0 | K79: 0 | M79: 99 | N79: growing
A80: 41 | B80: CLN-004 | C80: Glass Cleaner Spray | D80: Cleaning & Care | E80: SUP-05 | F80: =INDEX(Inputs!$C$31:$C$35,MATCH(E80,Inputs!$A$31:$A$35,0)) -> 1 | G80: =INDEX(Inputs!$D$31:$D$35,MATCH(E80,Inputs!$A$31:$A$35,0)) -> 35 | H80: 6 | I80: 12 | J80: 556 | K80: 0 | M80: 0 | N80: variable
A81: 42 | B81: CLN-005 | C81: Bamboo Toilet Brush | D81: Cleaning & Care | E81: SUP-05 | F81: =INDEX(Inputs!$C$31:$C$35,MATCH(E81,Inputs!$A$31:$A$35,0)) -> 1 | G81: =INDEX(Inputs!$D$31:$D$35,MATCH(E81,Inputs!$A$31:$A$35,0)) -> 35 | H81: 11 | I81: 12 | J81: 307 | K81: 0 | M81: 0 | N81: stable
A82: 43 | B82: CLN-006 | C82: Reusable Mop Pads 3-Pack | D82: Cleaning & Care | E82: SUP-05 | F82: =INDEX(Inputs!$C$31:$C$35,MATCH(E82,Inputs!$A$31:$A$35,0)) -> 1 | G82: =INDEX(Inputs!$D$31:$D$35,MATCH(E82,Inputs!$A$31:$A$35,0)) -> 35 | H82: 10 | I82: 12 | J82: 930 | K82: 0 | M82: 0 | N82: declining
A83: 44 | B83: CLN-007 | C83: Kettle Descaler 500ml | D83: Cleaning & Care | E83: SUP-05 | F83: =INDEX(Inputs!$C$31:$C$35,MATCH(E83,Inputs!$A$31:$A$35,0)) -> 1 | G83: =INDEX(Inputs!$D$31:$D$35,MATCH(E83,Inputs!$A$31:$A$35,0)) -> 35 | H83: 8 | I83: 12 | J83: 72 | K83: 0 | M83: 0 | N83: variable
A84: 45 | B84: CLN-008 | C84: Lint Roller 3-Pack | D84: Cleaning & Care | E84: SUP-05 | F84: =INDEX(Inputs!$C$31:$C$35,MATCH(E84,Inputs!$A$31:$A$35,0)) -> 1 | G84: =INDEX(Inputs!$D$31:$D$35,MATCH(E84,Inputs!$A$31:$A$35,0)) -> 35 | H84: 7 | I84: 24 | J84: 351 | K84: 0 | M84: 0 | N84: stable
A85: 46 | B85: CLN-009 | C85: Stain Remover Pen | D85: Cleaning & Care | E85: SUP-05 | F85: =INDEX(Inputs!$C$31:$C$35,MATCH(E85,Inputs!$A$31:$A$35,0)) -> 1 | G85: =INDEX(Inputs!$D$31:$D$35,MATCH(E85,Inputs!$A$31:$A$35,0)) -> 35 | H85: 13 | I85: 24 | J85: 416 | K85: 0 | M85: 0 | N85: growing
A86: 47 | B86: CLN-010 | C86: Scrub Brush Set | D86: Cleaning & Care | E86: SUP-05 | F86: =INDEX(Inputs!$C$31:$C$35,MATCH(E86,Inputs!$A$31:$A$35,0)) -> 1 | G86: =INDEX(Inputs!$D$31:$D$35,MATCH(E86,Inputs!$A$31:$A$35,0)) -> 35 | H86: 16 | I86: 12 | J86: 50 | K86: 0 | M86: 0 | N86: variable
A87: 48 | B87: CLN-011 | C87: Oven Cleaner Gel | D87: Cleaning & Care | E87: SUP-05 | F87: =INDEX(Inputs!$C$31:$C$35,MATCH(E87,Inputs!$A$31:$A$35,0)) -> 1 | G87: =INDEX(Inputs!$D$31:$D$35,MATCH(E87,Inputs!$A$31:$A$35,0)) -> 35 | H87: 14 | I87: 12 | J87: 102 | K87: 0 | M87: 0 | N87: stable

Sheet Demand_History
A1: Week | B1: Week Start Date | C1: SKU | D1: Actual Demand (units)
A2: 1 | B2: 45474 | C2: KIT-001 | D2: 62
A3: 2 | B3: 45481 | C3: KIT-001 | D3: 58
A4: 3 | B4: 45488 | C4: KIT-001 | D4: 53
A5: 4 | B5: 45495 | C5: KIT-001 | D5: 56
A6: 5 | B6: 45502 | C6: KIT-001 | D6: 52
A7: 6 | B7: 45509 | C7: KIT-001 | D7: 60
A8: 7 | B8: 45516 | C8: KIT-001 | D8: 71
A9: 8 | B9: 45523 | C9: KIT-001 | D9: 56
A10: 9 | B10: 45530 | C10: KIT-001 | D10: 55
A11: 10 | B11: 45537 | C11: KIT-001 | D11: 64
A12: 11 | B12: 45544 | C12: KIT-001 | D12: 63
A13: 12 | B13: 45551 | C13: KIT-001 | D13: 61
... A4993: 104 | B4993: 46195 | C4993: CLN-011 | D4993: 45

Sheet Forecast
A1: Forecast: walk-forward method comparison and selection per SKU
A2: WAPE = SUM|F-A| / SUM(A). Bias = SUM(F-A) / SUM(A). Error SD = STDEV.S of out-of-sample errors (F-A). Selection: lowest WAPE; a simpler method wins if within the WAPE tolerance. Simplicity order: Naive < MA4 < MA8 < SES.
A3: Portfolio WAPE (selected methods, volume-weighted): | E3: =SUM(AJ7:AJ54)/SUM(H7:H54) -> 0.14220804
A5: ROW LOOKUPS | H5: LIVE PLANNING: evaluation window = weeks Eval_Start_Week to 104 (default 53-104) | AK5: BACKTEST CALIBRATION: weeks Cal_Start_Week to Cal_End_Week (default 37-88), uses no data from the backtest weeks
A6: SKU | B6: Product | C6: First Row in history | D6: Last Row | E6: Eval First Row | F6: Calib First Row | G6: Calib Last Row | H6: Eval Actual Sum | I6: WAPE Naive | J6: WAPE MA4 | K6: WAPE MA8 | L6: WAPE SES | M6: Bias Naive | N6: Bias MA4 | O6: Bias MA8 | P6: Bias SES | Q6: Err SD Naive | R6: Err SD MA4 | S6: Err SD MA8 | T6: Err SD SES | U6: Next-Wk Fcst Naive | V6: Next-Wk Fcst MA4 | W6: Next-Wk Fcst MA8 | X6: Next-Wk Fcst SES | Y6: Best WAPE | Z6: Naive within tol? | AA6: MA4 within tol? | AB6: MA8 within tol? | AC6: SES within tol? | AD6: Selected Method # | AE6: Selected Forecast Method | AF6: Current Weekly Forecast | AG6: Selected WAPE | AH6: Selected Bias | AI6: Selected Error SD | AJ6: Selected Abs Error Sum | AK6: Calib Actual Sum | AL6: Calib WAPE Naive | AM6: Calib WAPE MA4 | AN6: Calib WAPE MA8 | AO6: Calib WAPE SES | AP6: Calib Err SD Naive | AQ6: Calib Err SD MA4 | AR6: Calib Err SD MA8 | AS6: Calib Err SD SES | AT6: Calib Best WAPE | AU6: Calib Naive within tol? | AV6: Calib MA4 within tol? | AW6: Calib MA8 within tol? | AX6: Calib SES within tol? | AY6: Calib Selected # | AZ6: Calib Selected Method | BA6: Calib Error SD (selected)
A7: =Inputs!B40 -> KIT-001 | B7: =Inputs!C40 -> Chef's Knife 20cm | C7: =MATCH(A7,Demand_History!$C:$C,0) -> 2 | D7: =C7+Weeks_History-1 -> 105 | E7: =C7+Eval_Start_Week-1 -> 54 | F7: =C7+Cal_Start_Week-1 -> 38 | G7: =C7+Cal_End_Week-1 -> 89 | H7: =SUM(INDEX(Forecast_Walkforward!$C:$C,$E7):INDEX(Forecast_Walkforward!$C:$C,$D7)) -> 3104 | I7: =SUM(INDEX(Forecast_Walkforward!$L:$L,$E7):INDEX(Forecast_Walkforward!$L:$L,$D7))/$H7 -> 0.13659794 | J7: =SUM(INDEX(Forecast_Walkforward!$M:$M,$E7):INDEX(Forecast_Walkforward!$M:$M,$D7))/$H7 -> 0.10647552 | K7: =SUM(INDEX(Forecast_Walkforward!$N:$N,$E7):INDEX(Forecast_Walkforward!$N:$N,$D7))/$H7 -> 0.096488402 | L7: =SUM(INDEX(Forecast_Walkforward!$O:$O,$E7):INDEX(Forecast_Walkforward!$O:$O,$D7))/$H7 -> 0.1024709 | M7: =SUM(INDEX(Forecast_Walkforward!$H:$H,$E7):INDEX(Forecast_Walkforward!$H:$H,$D7))/$H7 -> 0.0025773196 | N7: =SUM(INDEX(Forecast_Walkforward!$I:$I,$E7):INDEX(Forecast_Walkforward!$I:$I,$D7))/$H7 -> -0.0012886598 | O7: =SUM(INDEX(Forecast_Walkforward!$J:$J,$E7):INDEX(Forecast_Walkforward!$J:$J,$D7))/$H7 -> 0.003382732 | P7: =SUM(INDEX(Forecast_Walkforward!$K:$K,$E7):INDEX(Forecast_Walkforward!$K:$K,$D7))/$H7 -> 0.001049945 | Q7: =_xlfn.STDEV.S(INDEX(Forecast_Walkforward!$H:$H,$E7):INDEX(Forecast_Walkforward!$H:$H,$D7)) -> 9.9200423 | R7: =_xlfn.STDEV.S(INDEX(Forecast_Walkforward!$I:$I,$E7):INDEX(Forecast_Walkforward!$I:$I,$D7)) -> 8.0702398 | S7: =_xlfn.STDEV.S(INDEX(Forecast_Walkforward!$J:$J,$E7):INDEX(Forecast_Walkforward!$J:$J,$D7)) -> 7.6105075 | T7: =_xlfn.STDEV.S(INDEX(Forecast_Walkforward!$K:$K,$E7):INDEX(Forecast_Walkforward!$K:$K,$D7)) -> 7.7251244 | U7: =INDEX(Forecast_Walkforward!$C:$C,$D7) -> 53 | V7: =AVERAGE(INDEX(Forecast_Walkforward!$C:$C,$D7-3):INDEX(Forecast_Walkforward!$C:$C,$D7)) -> 61.25 | W7: =AVERAGE(INDEX(Forecast_Walkforward!$C:$C,$D7-7):INDEX(Forecast_Walkforward!$C:$C,$D7)) -> 57.125 | X7: =SES_Alpha*INDEX(Forecast_Walkforward!$C:$C,$D7)+(1-SES_Alpha)*INDEX(Forecast_Walkforward!$G:$G,$D7) -> 59.718987 | Y7: =MIN(I7:L7) -> 0.096488402 | Z7: =I7<=$Y7+WAPE_Tol -> FALSE | AA7: =J7<=$Y7+WAPE_Tol -> TRUE | AB7: =K7<=$Y7+WAPE_Tol -> TRUE | AC7: =L7<=$Y7+WAPE_Tol -> TRUE | AD7: =MATCH(TRUE(),Z7:AC7,0) -> 2 | AE7: =CHOOSE(AD7,"Naive","MA4","MA8","SES") -> MA4 | AF7: =INDEX(U7:X7,AD7) -> 61.25 | AG7: =INDEX(I7:L7,AD7) -> 0.10647552 | AH7: =INDEX(M7:P7,AD7) -> -0.0012886598 | AI7: =INDEX(Q7:T7,AD7) -> 8.0702398 | AJ7: =AG7*H7 -> 330.5 | AK7: =SUM(INDEX(Forecast_Walkforward!$C:$C,$F7):INDEX(Forecast_Walkforward!$C:$C,$G7)) -> 3127 | AL7: =SUM(INDEX(Forecast_Walkforward!$L:$L,$F7):INDEX(Forecast_Walkforward!$L:$L,$G7))/$AK7 -> 0.1371922 | AM7: =SUM(INDEX(Forecast_Walkforward!$M:$M,$F7):INDEX(Forecast_Walkforward!$M:$M,$G7))/$AK7 -> 0.10089543 | AN7: =SUM(INDEX(Forecast_Walkforward!$N:$N,$F7):INDEX(Forecast_Walkforward!$N:$N,$G7))/$AK7 -> 0.094099776 | AO7: =SUM(INDEX(Forecast_Walkforward!$O:$O,$F7):INDEX(Forecast_Walkforward!$O:$O,$G7))/$AK7 -> 0.098986363 | AP7: =_xlfn.STDEV.S(INDEX(Forecast_Walkforward!$H:$H,$F7):INDEX(Forecast_Walkforward!$H:$H,$G7)) -> 10.100905 | AQ7: =_xlfn.STDEV.S(INDEX(Forecast_Walkforward!$I:$I,$F7):INDEX(Forecast_Walkforward!$I:$I,$G7)) -> 7.7446218 | AR7: =_xlfn.STDEV.S(INDEX(Forecast_Walkforward!$J:$J,$F7):INDEX(Forecast_Walkforward!$J:$J,$G7)) -> 7.2709769 | AS7: =_xlfn.STDEV.S(INDEX(Forecast_Walkforward!$K:$K,$F7):INDEX(Forecast_Walkforward!$K:$K,$G7)) -> 7.5877795 | AT7: =MIN(AL7:AO7) -> 0.094099776 | AU7: =AL7<=$AT7+WAPE_Tol -> FALSE | AV7: =AM7<=$AT7+WAPE_Tol -> TRUE | AW7: =AN7<=$AT7+WAPE_Tol -> TRUE | AX7: =AO7<=$AT7+WAPE_Tol -> TRUE | AY7: =MATCH(TRUE(),AU7:AX7,0) -> 2 | AZ7: =CHOOSE(AY7,"Naive","MA4","MA8","SES") -> MA4 | BA7: =INDEX(AP7:AS7,AY7) -> 7.7446218
A8: =Inputs!B41 -> KIT-002 | B8: =Inputs!C41 -> Non-Stick Frying Pan 28cm | C8: =MATCH(A8,Demand_History!$C:$C,0) -> 106 | D8: =C8+Weeks_History-1 -> 209 | E8: =C8+Eval_Start_Week-1 -> 158 | F8: =C8+Cal_Start_Week-1 -> 142 | G8: =C8+Cal_End_Week-1 -> 193 | H8: =SUM(INDEX(Forecast_Walkforward!$C:$C,$E8):INDEX(Forecast_Walkforward!$C:$C,$D8)) -> 2383 | I8: =SUM(INDEX(Forecast_Walkforward!$L:$L,$E8):INDEX(Forecast_Walkforward!$L:$L,$D8))/$H8 -> 0.35459505 | J8: =SUM(INDEX(Forecast_Walkforward!$M:$M,$E8):INDEX(Forecast_Walkforward!$M:$M,$D8))/$H8 -> 0.27276542 | K8: =SUM(INDEX(Forecast_Walkforward!$N:$N,$E8):INDEX(Forecast_Walkforward!$N:$N,$D8))/$H8 -> 0.26778221 | L8: =SUM(INDEX(Forecast_Walkforward!$O:$O,$E8):INDEX(Forecast_Walkforward!$O:$O,$D8))/$H8 -> 0.27505341 | M8: =SUM(INDEX(Forecast_Walkforward!$H:$H,$E8):INDEX(Forecast_Walkforward!$H:$H,$D8))/$H8 -> 0.0012589173 | N8: =SUM(INDEX(Forecast_Walkforward!$I:$I,$E8):INDEX(Forecast_Walkforward!$I:$I,$D8))/$H8 -> -0.0035669324 | O8: =SUM(INDEX(Forecast_Walkforward!$J:$J,$E8):INDEX(Forecast_Walkforward!$J:$J,$D8))/$H8 -> -0.015054553 | P8: =SUM(INDEX(Forecast_Walkforward!$K:$K,$E8):INDEX(Forecast_Walkforward!$K:$K,$D8))/$H8 -> -0.0092835341 | Q8: =_xlfn.STDEV.S(INDEX(Forecast_Walkforward!$H:$H,$E8):INDEX(Forecast_Walkforward!$H:$H,$D8)) -> 20.865032 | R8: =_xlfn.STDEV.S(INDEX(Forecast_Walkforward!$I:$I,$E8):INDEX(Forecast_Walkforward!$I:$I,$D8)) -> 16.126331 | S8: =_xlfn.STDEV.S(INDEX(Forecast_Walkforward!$J:$J,$E8):INDEX(Forecast_Walkforward!$J:$J,$D8)) -> 15.250371 | T8: =_xlfn.STDEV.S(INDEX(Forecast_Walkforward!$K:$K,$E8):INDEX(Forecast_Walkforward!$K:$K,$D8)) -> 15.813458 | U8: =INDEX(Forecast_Walkforward!$C:$C,$D8) -> 30 | V8: =AVERAGE(INDEX(Forecast_Walkforward!$C:$C,$D8-3):INDEX(Forecast_Walkforward!$C:$C,$D8)) -> 33.5 | W8: =AVERAGE(INDEX(Forecast_Walkforward!$C:$C,$D8-7):INDEX(Forecast_Walkforward!$C:$C,$D8)) -> 48.375 | X8: =SES_Alpha*INDEX(Forecast_Walkforward!$C:$C,$D8)+(1-SES_Alpha)*INDEX(Forecast_Walkforward!$G:$G,$D8) -> 41.513413 | Y8: =MIN(I8:L8) -> 0.26778221 | Z8: =I8<=$Y8+WAPE_Tol -> FALSE | AA8: =J8<=$Y8+WAPE_Tol -> TRUE | AB8: =K8<=$Y8+WAPE_Tol -> TRUE | AC8: =L8<=$Y8+WAPE_Tol -> TRUE | AD8: =MATCH(TRUE(),Z8:AC8,0) -> 2 | AE8: =CHOOSE(AD8,"Naive","MA4","MA8","SES") -> MA4 | AF8: =INDEX(U8:X8,AD8) -> 33.5 | AG8: =INDEX(I8:L8,AD8) -> 0.27276542 | AH8: =INDEX(M8:P8,AD8) -> -0.0035669324 | AI8: =INDEX(Q8:T8,AD8) -> 16.126331 | AJ8: =AG8*H8 -> 650 | AK8: =SUM(INDEX(Forecast_Walkforward!$C:$C,$F8):INDEX(Forecast_Walkforward!$C:$C,$G8)) -> 2220 | AL8: =SUM(INDEX(Forecast_Walkforward!$L:$L,$F8):INDEX(Forecast_Walkforward!$L:$L,$G8))/$AK8 -> 0.33333333 | AM8: =SUM(INDEX(Forecast_Walkforward!$M:$M,$F8):INDEX(Forecast_Walkforward!$M:$M,$G8))/$AK8 -> 0.25236486 | AN8: =SUM(INDEX(Forecast_Walkforward!$N:$N,$F8):INDEX(Forecast_Walkforward!$N:$N,$G8))/$AK8 -> 0.2446509 | AO8: =SUM(INDEX(Forecast_Walkforward!$O:$O,$F8):INDEX(Forecast_Walkforward!$O:$O,$G8))/$AK8 -> 0.2467857 | AP8: =_xlfn.STDEV.S(INDEX(Forecast_Walkforward!$H:$H,$F8):INDEX(Forecast_Walkforward!$H:$H,$G8)) -> 18.279587 | AQ8: =_xlfn.STDEV.S(INDEX(Forecast_Walkforward!$I:$I,$F8):INDEX(Forecast_Walkforward!$I:$I,$G8)) -> 14.122994 | AR8: =_xlfn.STDEV.S(INDEX(Forecast_Walkforward!$J:$J,$F8):INDEX(Forecast_Walkforward!$J:$J,$G8)) -> 13.29631 | AS8: =_xlfn.STDEV.S(INDEX(Forecast_Walkforward!$K:$K,$F8):INDEX(Forecast_Walkforward!$K:$K,$G8)) -> 13.783621 | AT8: =MIN(AL8:AO8) -> 0.2446509 | AU8: =AL8<=$AT8+WAPE_Tol -> FALSE | AV8: =AM8<=$AT8+WAPE_Tol -> TRUE | AW8: =AN8<=$AT8+WAPE_Tol -> TRUE | AX8: =AO8<=$AT8+WAPE_Tol -> TRUE | AY8: =MATCH(TRUE(),AU8:AX8,0) -> 2 | AZ8: =CHOOSE(AY8,"Naive","MA4","MA8","SES") -> MA4 | BA8: =INDEX(AP8:AS8,AY8) -> 14.122994
A9: =Inputs!B42 -> KIT-003 | B9: =Inputs!C42 -> Glass Food Storage Set 5pc | C9: =MATCH(A9,Demand_History!$C:$C,0) -> 210 | D9: =C9+Weeks_History-1 -> 313 | E9: =C9+Eval_Start_Week-1 -> 262 | F9: =C9+Cal_Start_Week-1 -> 246 | G9: =C9+Cal_End_Week-1 -> 297 | H9: =SUM(INDEX(Forecast_Walkforward!$C:$C,$E9):INDEX(Forecast_Walkforward!$C:$C,$D9)) -> 4472 | I9: =SUM(INDEX(Forecast_Walkforward!$L:$L,$E9):INDEX(Forecast_Walkforward!$L:$L,$D9))/$H9 -> 0.13528623 | J9: =SUM(INDEX(Forecast_Walkforward!$M:$M,$E9):INDEX(Forecast_Walkforward!$M:$M,$D9))/$H9 -> 0.1151051 | K9: =SUM(INDEX(Forecast_Walkforward!$N:$N,$E9):INDEX(Forecast_Walkforward!$N:$N,$D9))/$H9 -> 0.10336538 | L9: =SUM(INDEX(Forecast_Walkforward!$O:$O,$E9):INDEX(Forecast_Walkforward!$O:$O,$D9))/$H9 -> 0.10735683 | M9: =SUM(INDEX(Forecast_Walkforward!$H:$H,$E9):INDEX(Forecast_Walkforward!$H:$H,$D9))/$H9 -> -0.0033542039 | N9: =SUM(INDEX(Forecast_Walkforward!$I:$I,$E9):INDEX(Forecast_Walkforward!$I:$I,$D9))/$H9 -> -0.012690072 | O9: =SUM(INDEX(Forecast_Walkforward!$J:$J,$E9):INDEX(Forecast_Walkforward!$J:$J,$D9))/$H9 -> -0.022976297 | P9: =SUM(INDEX(Forecast_Walkforward!$K:$K,$E9):INDEX(Forecast_Walkforward!$K:$K,$D9))/$H9 -> -0.017137407 | Q9: =_xlfn.STDEV.S(INDEX(Forecast_Walkforward!$H:$H,$E9):INDEX(Forecast_Walkforward!$H:$H,$D9)) -> 15.363997 | R9: =_xlfn.STDEV.S(INDEX(Forecast_Walkforward!$I:$I,$E9):INDEX(Forecast_Walkforward!$I:$I,$D9)) -> 12.625452 | S9: =_xlfn.STDEV.S(INDEX(Forecast_Walkforward!$J:$J,$E9):INDEX(Forecast_Walkforward!$J:$J,$D9)) -> 11.354526 | T9: =_xlfn.STDEV.S(INDEX(Forecast_Walkforward!$K:$K,$E9):INDEX(Forecast_Walkforward!$K:$K,$D9)) -> 11.893202 | U9: =INDEX(Forecast_Walkforward!$C:$C,$D9) -> 95 | V9: =AVERAGE(INDEX(Forecast_Walkforward!$C:$C,$D9-3):INDEX(Forecast_Walkforward!$C:$C,$D9)) -> 98 | W9: =AVERAGE(INDEX(Forecast_Walkforward!$C:$C,$D9-7):INDEX(Forecast_Walkforward!$C:$C,$D9)) -> 95.125 | X9: =SES_Alpha*INDEX(Forecast_Walkforward!$C:$C,$D9)+(1-SES_Alpha)*INDEX(Forecast_Walkforward!$G:$G,$D9) -> 95.660303 | Y9: =MIN(I9:L9) -> 0.10336538 | Z9: =I9<=$Y9+WAPE_Tol -> FALSE | AA9: =J9<=$Y9+WAPE_Tol -> FALSE | AB9: =K9<=$Y9+WAPE_Tol -> TRUE | AC9: =L9<=$Y9+WAPE_Tol -> TRUE | AD9: =MATCH(TRUE(),Z9:AC9,0) -> 3 | AE9: =CHOOSE(AD9,"Naive","MA4","MA8","SES") -> MA8 | AF9: =INDEX(U9:X9,AD9) -> 95.125 | AG9: =INDEX(I9:L9,AD9) -> 0.10336538 | AH9: =INDEX(M9:P9,AD9) -> -0.022976297 | AI9: =INDEX(Q9:T9,AD9) -> 11.354526 | AJ9: =AG9*H9 -> 462.25 | AK9: =SUM(INDEX(Forecast_Walkforward!$C:$C,$F9):INDEX(Forecast_Walkforward!$C:$C,$G9)) -> 3961 | AL9: =SUM(INDEX(Forecast_Walkforward!$L:$L,$F9):INDEX(Forecast_Walkforward!$L:$L,$G9))/$AK9 -> 0.15576875 | AM9: =SUM(INDEX(Forecast_Walkforward!$M:$M,$F9):INDEX(Forecast_Walkforward!$M:$M,$G9))/$AK9 -> 0.13153244 | AN9: =SUM(INDEX(Forecast_Walkforward!$N:$N,$F9):INDEX(Forecast_Walkforward!$N:$N,$G9))/$AK9 -> 0.12414794 | AO9: =SUM(INDEX(Forecast_Walkforward!$O:$O,$F9):INDEX(Forecast_Walkforward!$O:$O,$G9))/$AK9 -> 0.12472271 | AP9: =_xlfn.STDEV.S(INDEX(Forecast_Walkforward!$H:$H,$F9):INDEX(Forecast_Walkforward!$H:$H,$G9)) -> 15.468976 | AQ9: =_xlfn.STDEV.S(INDEX(Forecast_Walkforward!$I:$I,$F9):INDEX(Forecast_Walkforward!$I:$I,$G9)) -> 12.744602 | AR9: =_xlfn.STDEV.S(INDEX(Forecast_Walkforward!$J:$J,$F9):INDEX(Forecast_Walkforward!$J:$J,$G9)) -> 11.998749 | AS9: =_xlfn.STDEV.S(INDEX(Forecast_Walkforward!$K:$K,$F9):INDEX(Forecast_Walkforward!$K:$K,$G9)) -> 12.246729 | AT9: =MIN(AL9:AO9) -> 0.12414794 | AU9: =AL9<=$AT9+WAPE_Tol -> FALSE | AV9: =AM9<=$AT9+WAPE_Tol -> TRUE | AW9: =AN9<=$AT9+WAPE_Tol -> TRUE | AX9: =AO9<=$AT9+WAPE_Tol -> TRUE | AY9: =MATCH(TRUE(),AU9:AX9,0) -> 2 | AZ9: =CHOOSE(AY9,"Naive","MA4","MA8","SES") -> MA4 | BA9: =INDEX(AP9:AS9,AY9) -> 12.744602
A10: =Inputs!B43 -> KIT-004 | B10: =Inputs!C43 -> Bamboo Cutting Board | C10: =MATCH(A10,Demand_History!$C:$C,0) -> 314 | D10: =C10+Weeks_History-1 -> 417 | E10: =C10+Eval_Start_Week-1 -> 366 | F10: =C10+Cal_Start_Week-1 -> 350 | G10: =C10+Cal_End_Week-1 -> 401 | H10: =SUM(INDEX(Forecast_Walkforward!$C:$C,$E10):INDEX(Forecast_Walkforward!$C:$C,$D10)) -> 4668 | I10: =SUM(INDEX(Forecast_Walkforward!$L:$L,$E10):INDEX(Forecast_Walkforward!$L:$L,$D10))/$H10 -> 0.12253642 | J10: =SUM(INDEX(Forecast_Walkforward!$M:$M,$E10):INDEX(Forecast_Walkforward!$M:$M,$D10))/$H10 -> 0.10689803 | K10: =SUM(INDEX(Forecast_Walkforward!$N:$N,$E10):INDEX(Forecast_Walkforward!$N:$N,$D10))/$H10 -> 0.09733826 | L10: =SUM(INDEX(Forecast_Walkforward!$O:$O,$E10):INDEX(Forecast_Walkforward!$O:$O,$D10))/$H10 -> 0.10060173 | M10: =SUM(INDEX(Forecast_Walkforward!$H:$H,$E10):INDEX(Forecast_Walkforward!$H:$H,$D10))/$H10 -> -0.0072836332 | N10: =SUM(INDEX(Forecast_Walkforward!$I:$I,$E10):INDEX(Forecast_Walkforward!$I:$I,$D10))/$H10 -> -0.0099614396 | O10: =SUM(INDEX(Forecast_Walkforward!$J:$J,$E10):INDEX(Forecast_Walkforward!$J:$J,$D10))/$H10 -> -0.008863539 | P10: =SUM(INDEX(Forecast_Walkforward!$K:$K,$E10):INDEX(Forecast_Walkforward!$K:$K,$D10))/$H10 -> -0.0087757022 | Q10: =_xlfn.STDEV.S(INDEX(Forecast_Walkforward!$H:$H,$E10):INDEX(Forecast_Walkforward!$H:$H,$D10)) -> 13.846334 | R10: =_xlfn.STDEV.S(INDEX(Forecast_Walkforward!$I:$I,$E10):INDEX(Forecast_Walkforward!$I:$I,$D10)) -> 11.467916 | S10: =_xlfn.STDEV.S(INDEX(Forecast_Walkforward!$J:$J,$E10):INDEX(Forecast_Walkforward!$J:$J,$D10)) -> 10.507672 | T10: =_xlfn.STDEV.S(INDEX(Forecast_Walkforward!$K:$K,$E10):INDEX(Forecast_Walkforward!$K:$K,$D10)) -> 10.897646 | U10: =INDEX(Forecast_Walkforward!$C:$C,$D10) -> 105 | V10: =AVERAGE(INDEX(Forecast_Walkforward!$C:$C,$D10-3):INDEX(Forecast_Walkforward!$C:$C,$D10)) -> 96.5 | W10: =AVERAGE(INDEX(Forecast_Walkforward!$C:$C,$D10-7):INDEX(Forecast_Walkforward!$C:$C,$D10)) -> 94.75 | X10: =SES_Alpha*INDEX(Forecast_Walkforward!$C:$C,$D10)+(1-SES_Alpha)*INDEX(Forecast_Walkforward!$G:$G,$D10) -> 96.693918 | Y10: =MIN(I10:L10) -> 0.09733826 | Z10: =I10<=$Y10+WAPE_Tol -> FALSE | AA10: =J10<=$Y10+WAPE_Tol -> TRUE | AB10: =K10<=$Y10+WAPE_Tol -> TRUE | AC10: =L10<=$Y10+WAPE_Tol -> TRUE | AD10: =MATCH(TRUE(),Z10:AC10,0) -> 2 | AE10: =CHOOSE(AD10,"Naive","MA4","MA8","SES") -> MA4 | AF10: =INDEX(U10:X10,AD10) -> 96.5 | AG10: =INDEX(I10:L10,AD10) -> 0.10689803 | AH10: =INDEX(M10:P10,AD10) -> -0.0099614396 | AI10: =INDEX(Q10:T10,AD10) -> 11.467916 | AJ10: =AG10*H10 -> 499 | AK10: =SUM(INDEX(Forecast_Walkforward!$C:$C,$F10):INDEX(Forecast_Walkforward!$C:$C,$G10)) -> 4630 | AL10: =SUM(INDEX(Forecast_Walkforward!$L:$L,$F10):INDEX(Forecast_Walkforward!$L:$L,$G10))/$AK10 -> 0.10194384 | AM10: =SUM(INDEX(Forecast_Walkforward!$M:$M,$F10):INDEX(Forecast_Walkforward!$M:$M,$G10))/$AK10 -> 0.092278618 | AN10: =SUM(INDEX(Forecast_Walkforward!$N:$N,$F10):INDEX(Forecast_Walkforward!$N:$N,$G10))/$AK10 -> 0.08336933 | AO10: =SUM(INDEX(Forecast_Walkforward!$O:$O,$F10):INDEX(Forecast_Walkforward!$O:$O,$G10))/$AK10 -> 0.084538399 | AP10: =_xlfn.STDEV.S(INDEX(Forecast_Walkforward!$H:$H,$F10):INDEX(Forecast_Walkforward!$H:$H,$G10)) -> 11.468364 | AQ10: =_xlfn.STDEV.S(INDEX(Forecast_Walkforward!$I:$I,$F10):INDEX(Forecast_Walkforward!$I:$I,$G10)) -> 10.552742 | AR10: =_xlfn.STDEV.S(INDEX(Forecast_Walkforward!$J:$J,$F10):INDEX(Forecast_Walkforward!$J:$J,$G10)) -> 9.6472278 | AS10: =_xlfn.STDEV.S(INDEX(Forecast_Walkforward!$K:$K,$F10):INDEX(Forecast_Walkforward!$K:$K,$G10)) -> 9.6969871 | AT10: =MIN(AL10:AO10) -> 0.08336933 | AU10: =AL10<=$AT10+WAPE_Tol -> FALSE | AV10: =AM10<=$AT10+WAPE_Tol -> TRUE | AW10: =AN10<=$AT10+WAPE_Tol -> TRUE | AX10: =AO10<=$AT10+WAPE_Tol -> TRUE | AY10: =MATCH(TRUE(),AU10:AX10,0) -> 2 | AZ10: =CHOOSE(AY10,"Naive","MA4","MA8","SES") -> MA4 | BA10: =INDEX(AP10:AS10,AY10) -> 10.552742
A11: =Inputs!B44 -> KIT-005 | B11: =Inputs!C44 -> Stainless Saucepan 2L | C11: =MATCH(A11,Demand_History!$C:$C,0) -> 418 | D11: =C11+Weeks_History-1 -> 521 | E11: =C11+Eval_Start_Week-1 -> 470 | F11: =C11+Cal_Start_Week-1 -> 454 | G11: =C11+Cal_End_Week-1 -> 505 | H11: =SUM(INDEX(Forecast_Walkforward!$C:$C,$E11):INDEX(Forecast_Walkforward!$C:$C,$D11)) -> 1441 | I11: =SUM(INDEX(Forecast_Walkforward!$L:$L,$E11):INDEX(Forecast_Walkforward!$L:$L,$D11))/$H11 -> 0.17071478 | J11: =SUM(INDEX(Forecast_Walkforward!$M:$M,$E11):INDEX(Forecast_Walkforward!$M:$M,$D11))/$H11 -> 0.15076336 | K11: =SUM(INDEX(Forecast_Walkforward!$N:$N,$E11):INDEX(Forecast_Walkforward!$N:$N,$D11))/$H11 -> 0.13861901 | L11: =SUM(INDEX(Forecast_Walkforward!$O:$O,$E11):INDEX(Forecast_Walkforward!$O:$O,$D11))/$H11 -> 0.1401491 | M11: =SUM(INDEX(Forecast_Walkforward!$H:$H,$E11):INDEX(Forecast_Walkforward!$H:$H,$D11))/$H11 -> 0.0055517002 | N11: =SUM(INDEX(Forecast_Walkforward!$I:$I,$E11):INDEX(Forecast_Walkforward!$I:$I,$D11))/$H11 -> 0.018563498 | O11: =SUM(INDEX(Forecast_Walkforward!$J:$J,$E11):INDEX(Forecast_Walkforward!$J:$J,$D11))/$H11 -> 0.031575295 | P11: =SUM(INDEX(Forecast_Walkforward!$K:$K,$E11):INDEX(Forecast_Walkforward!$K:$K,$D11))/$H11 -> 0.023456009 | Q11: =_xlfn.STDEV.S(INDEX(Forecast_Walkforward!$H:$H,$E11):INDEX(Forecast_Walkforward!$H:$H,$D11)) -> 6.3288465 | R11: =_xlfn.STDEV.S(INDEX(Forecast_Walkforward!$I:$I,$E11):INDEX(Forecast_Walkforward!$I:$I,$D11)) -> 5.0218672 | S11: =_xlfn.STDEV.S(INDEX(Forecast_Walkforward!$J:$J,$E11):INDEX(Forecast_Walkforward!$J:$J,$D11)) -> 4.6755649 | T11: =_xlfn.STDEV.S(INDEX(Forecast_Walkforward!$K:$K,$E11):INDEX(Forecast_Walkforward!$K:$K,$D11)) -> 4.8040358 | U11: =INDEX(Forecast_Walkforward!$C:$C,$D11) -> 23 | V11: =AVERAGE(INDEX(Forecast_Walkforward!$C:$C,$D11-3):INDEX(Forecast_Walkforward!$C:$C,$D11)) -> 22 | W11: =AVERAGE(INDEX(Forecast_Walkforward!$C:$C,$D11-7):INDEX(Forecast_Walkforward!$C:$C,$D11)) -> 23.875 | X11: =SES_Alpha*INDEX(Forecast_Walkforward!$C:$C,$D11)+(1-SES_Alpha)*INDEX(Forecast_Walkforward!$G:$G,$D11) -> 22.616277 | Y11: =MIN(I11:L11) -> 0.13861901 | Z11: =I11<=$Y11+WAPE_Tol -> FALSE | AA11: =J11<=$Y11+WAPE_Tol -> FALSE | AB11: =K11<=$Y11+WAPE_Tol -> TRUE | AC11: =L11<=$Y11+WAPE_Tol -> TRUE | AD11: =MATCH(TRUE(),Z11:AC11,0) -> 3 | AE11: =CHOOSE(AD11,"Naive","MA4","MA8","SES") -> MA8 | AF11: =INDEX(U11:X11,AD11) -> 23.875 | AG11: =INDEX(I11:L11,AD11) -> 0.13861901 | AH11: =INDEX(M11:P11,AD11) -> 0.031575295 | AI11: =INDEX(Q11:T11,AD11) -> 4.6755649 | AJ11: =AG11*H11 -> 199.75 | AK11: =SUM(INDEX(Forecast_Walkforward!$C:$C,$F11):INDEX(Forecast_Walkforward!$C:$C,$G11)) -> 1611 | AL11: =SUM(INDEX(Forecast_Walkforward!$L:$L,$F11):INDEX(Forecast_Walkforward!$L:$L,$G11))/$AK11 -> 0.19056487 | AM11: =SUM(INDEX(Forecast_Walkforward!$M:$M,$F11):INDEX(Forecast_Walkforward!$M:$M,$G11))/$AK11 -> 0.14835506 | AN11: =SUM(INDEX(Forecast_Walkforward!$N:$N,$F11):INDEX(Forecast_Walkforward!$N:$N,$G11))/$AK11 -> 0.1396648 | AO11: =SUM(INDEX(Forecast_Walkforward!$O:$O,$F11):INDEX(Forecast_Walkforward!$O:$O,$G11))/$AK11 -> 0.14567808 | AP11: =_xlfn.STDEV.S(INDEX(Forecast_Walkforward!$H:$H,$F11):INDEX(Forecast_Walkforward!$H:$H,$G11)) -> 7.3146014 | AQ11: =_xlfn.STDEV.S(INDEX(Forecast_Walkforward!$I:$I,$F11):INDEX(Forecast_Walkforward!$I:$I,$G11)) -> 5.3806991 | AR11: =_xlfn.STDEV.S(INDEX(Forecast_Walkforward!$J:$J,$F11):INDEX(Forecast_Walkforward!$J:$J,$G11)) -> 5.120793 | AS11: =_xlfn.STDEV.S(INDEX(Forecast_Walkforward!$K:$K,$F11):INDEX(Forecast_Walkforward!$K:$K,$G11)) -> 5.3437487 | AT11: =MIN(AL11:AO11) -> 0.1396648 | AU11: =AL11<=$AT11+WAPE_Tol -> FALSE | AV11: =AM11<=$AT11+WAPE_Tol -> TRUE | AW11: =AN11<=$AT11+WAPE_Tol -> TRUE | AX11: =AO11<=$AT11+WAPE_Tol -> TRUE | AY11: =MATCH(TRUE(),AU11:AX11,0) -> 2 | AZ11: =CHOOSE(AY11,"Naive","MA4","MA8","SES") -> MA4 | BA11: =INDEX(AP11:AS11,AY11) -> 5.3806991
A12: =Inputs!B45 -> KIT-006 | B12: =Inputs!C45 -> Silicone Utensil Set | C12: =MATCH(A12,Demand_History!$C:$C,0) -> 522 | D12: =C12+Weeks_History-1 -> 625 | E12: =C12+Eval_Start_Week-1 -> 574 | F12: =C12+Cal_Start_Week-1 -> 558 | G12: =C12+Cal_End_Week-1 -> 609 | H12: =SUM(INDEX(Forecast_Walkforward!$C:$C,$E12):INDEX(Forecast_Walkforward!$C:$C,$D12)) -> 2910 | I12: =SUM(INDEX(Forecast_Walkforward!$L:$L,$E12):INDEX(Forecast_Walkforward!$L:$L,$D12))/$H12 -> 0.32268041 | J12: =SUM(INDEX(Forecast_Walkforward!$M:$M,$E12):INDEX(Forecast_Walkforward!$M:$M,$D12))/$H12 -> 0.30249141 | K12: =SUM(INDEX(Forecast_Walkforward!$N:$N,$E12):INDEX(Forecast_Walkforward!$N:$N,$D12))/$H12 -> 0.27079038 | L12: =SUM(INDEX(Forecast_Walkforward!$O:$O,$E12):INDEX(Forecast_Walkforward!$O:$O,$D12))/$H12 -> 0.28376677 | M12: =SUM(INDEX(Forecast_Walkforward!$H:$H,$E12):INDEX(Forecast_Walkforward!$H:$H,$D12))/$H12 -> -0.023024055 | N12: =SUM(INDEX(Forecast_Walkforward!$I:$I,$E12):INDEX(Forecast_Walkforward!$I:$I,$D12))/$H12 -> -0.033247423 | O12: =SUM(INDEX(Forecast_Walkforward!$J:$J,$E12):INDEX(Forecast_Walkforward!$J:$J,$D12))/$H12 -> -0.041237113 | P12: =SUM(INDEX(Forecast_Walkforward!$K:$K,$E12):INDEX(Forecast_Walkforward!$K:$K,$D12))/$H12 -> -0.034934952 | Q12: =_xlfn.STDEV.S(INDEX(Forecast_Walkforward!$H:$H,$E12):INDEX(Forecast_Walkforward!$H:$H,$D12)) -> 22.762488 | R12: =_xlfn.STDEV.S(INDEX(Forecast_Walkforward!$I:$I,$E12):INDEX(Forecast_Walkforward!$I:$I,$D12)) -> 20.779858 | S12: =_xlfn.STDEV.S(INDEX(Forecast_Walkforward!$J:$J,$E12):INDEX(Forecast_Walkforward!$J:$J,$D12)) -> 19.838 | T12: =_xlfn.STDEV.S(INDEX(Forecast_Walkforward!$K:$K,$E12):INDEX(Forecast_Walkforward!$K:$K,$D12)) -> 19.768279 | U12: =INDEX(Forecast_Walkforward!$C:$C,$D12) -> 93 | V12: =AVERAGE(INDEX(Forecast_Walkforward!$C:$C,$D12-3):INDEX(Forecast_Walkforward!$C:$C,$D12)) -> 66 | W12: =AVERAGE(INDEX(Forecast_Walkforward!$C:$C,$D12-7):INDEX(Forecast_Walkforward!$C:$C,$D12)) -> 66.625 | X12: =SES_Alpha*INDEX(Forecast_Walkforward!$C:$C,$D12)+(1-SES_Alpha)*INDEX(Forecast_Walkforward!$G:$G,$D12) -> 71.530846 | Y12: =MIN(I12:L12) -> 0.27079038 | Z12: =I12<=$Y12+WAPE_Tol -> FALSE | AA12: =J12<=$Y12+WAPE_Tol -> FALSE | AB12: =K12<=$Y12+WAPE_Tol -> TRUE | AC12: =L12<=$Y12+WAPE_Tol -> FALSE | AD12: =MATCH(TRUE(),Z12:AC12,0) -> 3 | AE12: =CHOOSE(AD12,"Naive","MA4","MA8","SES") -> MA8 | AF12: =INDEX(U12:X12,AD12) -> 66.625 | AG12: =INDEX(I12:L12,AD12) -> 0.27079038 | AH12: =INDEX(M12:P12,AD12) -> -0.041237113 | AI12: =INDEX(Q12:T12,AD12) -> 19.838 | AJ12: =AG12*H12 -> 788 | AK12: =SUM(INDEX(Forecast_Walkforward!$C:$C,$F12):INDEX(Forecast_Walkforward!$C:$C,$G12)) -> 2761 | AL12: =SUM(INDEX(Forecast_Walkforward!$L:$L,$F12):INDEX(Forecast_Walkforward!$L:$L,$G12))/$AK12 -> 0.37232887 | AM12: =SUM(INDEX(Forecast_Walkforward!$M:$M,$F12):INDEX(Forecast_Walkforward!$M:$M,$G12))/$AK12 -> 0.32461065 | AN12: =SUM(INDEX(Forecast_Walkforward!$N:$N,$F12):INDEX(Forecast_Walkforward!$N:$N,$G12))/$AK12 -> 0.28984064 | AO12: =SUM(INDEX(Forecast_Walkforward!$O:$O,$F12):INDEX(Forecast_Walkforward!$O:$O,$G12))/$AK12 -> 0.30485769 | AP12: =_xlfn.STDEV.S(INDEX(Forecast_Walkforward!$H:$H,$F12):INDEX(Forecast_Walkforward!$H:$H,$G12)) -> 24.401864 | AQ12: =_xlfn.STDEV.S(INDEX(Forecast_Walkforward!$I:$I,$F12):INDEX(Forecast_Walkforward!$I:$I,$G12)) -> 20.920301 | AR12: =_xlfn.STDEV.S(INDEX(Forecast_Walkforward!$J:$J,$F12):INDEX(Forecast_Walkforward!$J:$J,$G12)) -> 20.329749 | AS12: =_xlfn.STDEV.S(INDEX(Forecast_Walkforward!$K:$K,$F12):INDEX(Forecast_Walkforward!$K:$K,$G12)) -> 20.211907 | AT12: =MIN(AL12:AO12) -> 0.28984064 | AU12: =AL12<=$AT12+WAPE_Tol -> FALSE | AV12: =AM12<=$AT12+WAPE_Tol -> FALSE | AW12: =AN12<=$AT12+WAPE_Tol -> TRUE | AX12: =AO12<=$AT12+WAPE_Tol -> FALSE | AY12: =MATCH(TRUE(),AU12:AX12,0) -> 3 | AZ12: =CHOOSE(AY12,"Naive","MA4","MA8","SES") -> MA8 | BA12: =INDEX(AP12:AS12,AY12) -> 20.329749
A13: =Inputs!B46 -> KIT-007 | B13: =Inputs!C46 -> Cast Iron Casserole 5L | C13: =MATCH(A13,Demand_History!$C:$C,0) -> 626 | D13: =C13+Weeks_History-1 -> 729 | E13: =C13+Eval_Start_Week-1 -> 678 | F13: =C13+Cal_Start_Week-1 -> 662 | G13: =C13+Cal_End_Week-1 -> 713 | H13: =SUM(INDEX(Forecast_Walkforward!$C:$C,$E13):INDEX(Forecast_Walkforward!$C:$C,$D13)) -> 386 | I13: =SUM(INDEX(Forecast_Walkforward!$L:$L,$E13):INDEX(Forecast_Walkforward!$L:$L,$D13))/$H13 -> 0.41709845 | J13: =SUM(INDEX(Forecast_Walkforward!$M:$M,$E13):INDEX(Forecast_Walkforward!$M:$M,$D13))/$H13 -> 0.31282383 | K13: =SUM(INDEX(Forecast_Walkforward!$N:$N,$E13):INDEX(Forecast_Walkforward!$N:$N,$D13))/$H13 -> 0.29371762 | L13: =SUM(INDEX(Forecast_Walkforward!$O:$O,$E13):INDEX(Forecast_Walkforward!$O:$O,$D13))/$H13 -> 0.30741071 | M13: =SUM(INDEX(Forecast_Walkforward!$H:$H,$E13):INDEX(Forecast_Walkforward!$H:$H,$D13))/$H13 -> -0.012953368 | N13: =SUM(INDEX(Forecast_Walkforward!$I:$I,$E13):INDEX(Forecast_Walkforward!$I:$I,$D13))/$H13 -> -0.018782383 | O13: =SUM(INDEX(Forecast_Walkforward!$J:$J,$E13):INDEX(Forecast_Walkforward!$J:$J,$D13))/$H13 -> -0.028173575 | P13: =SUM(INDEX(Forecast_Walkforward!$K:$K,$E13):INDEX(Forecast_Walkforward!$K:$K,$D13))/$H13 -> -0.023308287 | Q13: =_xlfn.STDEV.S(INDEX(Forecast_Walkforward!$H:$H,$E13):INDEX(Forecast_Walkforward!$H:$H,$D13)) -> 3.9717612 | R13: =_xlfn.STDEV.S(INDEX(Forecast_Walkforward!$I:$I,$E13):INDEX(Forecast_Walkforward!$I:$I,$D13)) -> 2.9825528 | S13: =_xlfn.STDEV.S(INDEX(Forecast_Walkforward!$J:$J,$E13):INDEX(Forecast_Walkforward!$J:$J,$D13)) -> 2.8252539 | T13: =_xlfn.STDEV.S(INDEX(Forecast_Walkforward!$K:$K,$E13):INDEX(Forecast_Walkforward!$K:$K,$D13)) -> 2.9396325 | U13: =INDEX(Forecast_Walkforward!$C:$C,$D13) -> 9 | V13: =AVERAGE(INDEX(Forecast_Walkforward!$C:$C,$D13-3):INDEX(Forecast_Walkforward!$C:$C,$D13)) -> 8.5 | W13: =AVERAGE(INDEX(Forecast_Walkforward!$C:$C,$D13-7):INDEX(Forecast_Walkforward!$C:$C,$D13)) -> 8.875 | X13: =SES_Alpha*INDEX(Forecast_Walkforward!$C:$C,$D13)+(1-SES_Alpha)*INDEX(Forecast_Walkforward!$G:$G,$D13) -> 8.7888096 | Y13: =MIN(I13:L13) -> 0.29371762 | Z13: =I13<=$Y13+WAPE_Tol -> FALSE | AA13: =J13<=$Y13+WAPE_Tol -> FALSE | AB13: =K13<=$Y13+WAPE_Tol -> TRUE | AC13: =L13<=$Y13+WAPE_Tol -> FALSE | AD13: =MATCH(TRUE(),Z13:AC13,0) -> 3 | AE13: =CHOOSE(AD13,"Naive","MA4","MA8","SES") -> MA8 | AF13: =INDEX(U13:X13,AD13) -> 8.875 | AG13: =INDEX(I13:L13,AD13) -> 0.29371762 | AH13: =INDEX(M13:P13,AD13) -> -0.028173575 | AI13: =INDEX(Q13:T13,AD13) -> 2.8252539 | AJ13: =AG13*H13 -> 113.375 | AK13: =SUM(INDEX(Forecast_Walkforward!$C:$C,$F13):INDEX(Forecast_Walkforward!$C:$C,$G13)) -> 360 | AL13: =SUM(INDEX(Forecast_Walkforward!$L:$L,$F13):INDEX(Forecast_Walkforward!$L:$L,$G13))/$AK13 -> 0.48055556 | AM13: =SUM(INDEX(Forecast_Walkforward!$M:$M,$F13):INDEX(Forecast_Walkforward!$M:$M,$G13))/$AK13 -> 0.36944444 | AN13: =SUM(INDEX(Forecast_Walkforward!$N:$N,$F13):INDEX(Forecast_Walkforward!$N:$N,$G13))/$AK13 -> 0.34756944 | AO13: =SUM(INDEX(Forecast_Walkforward!$O:$O,$F13):INDEX(Forecast_Walkforward!$O:$O,$G13))/$AK13 -> 0.36592269 | AP13: =_xlfn.STDEV.S(INDEX(Forecast_Walkforward!$H:$H,$F13):INDEX(Forecast_Walkforward!$H:$H,$G13)) -> 4.14677 | AQ13: =_xlfn.STDEV.S(INDEX(Forecast_Walkforward!$I:$I,$F13):INDEX(Forecast_Walkforward!$I:$I,$G13)) -> 3.1090809 | AR13: =_xlfn.STDEV.S(INDEX(Forecast_Walkforward!$J:$J,$F13):INDEX(Forecast_Walkforward!$J:$J,$G13)) -> 2.9568715 | AS13: =_xlfn.STDEV.S(INDEX(Forecast_Walkforward!$K:$K,$F13):INDEX(Forecast_Walkforward!$K:$K,$G13)) -> 3.093027 | AT13: =MIN(AL13:AO13) -> 0.34756944 | AU13: =AL13<=$AT13+WAPE_Tol -> FALSE | AV13: =AM13<=$AT13+WAPE_Tol -> FALSE | AW13: =AN13<=$AT13+WAPE_Tol -> TRUE | AX13: =AO13<=$AT13+WAPE_Tol -> FALSE | AY13: =MATCH(TRUE(),AU13:AX13,0) -> 3 | AZ13: =CHOOSE(AY13,"Naive","MA4","MA8","SES") -> MA8 | BA13: =INDEX(AP13:AS13,AY13) -> 2.9568715
A14: =Inputs!B47 -> KIT-008 | B14: =Inputs!C47 -> Espresso Cup Set 6pc | C14: =MATCH(A14,Demand_History!$C:$C,0) -> 730 | D14: =C14+Weeks_History-1 -> 833 | E14: =C14+Eval_Start_Week-1 -> 782 | F14: =C14+Cal_Start_Week-1 -> 766 | G14: =C14+Cal_End_Week-1 -> 817 | H14: =SUM(INDEX(Forecast_Walkforward!$C:$C,$E14):INDEX(Forecast_Walkforward!$C:$C,$D14)) -> 2125 | I14: =SUM(INDEX(Forecast_Walkforward!$L:$L,$E14):INDEX(Forecast_Walkforward!$L:$L,$D14))/$H14 -> 0.10164706 | J14: =SUM(INDEX(Forecast_Walkforward!$M:$M,$E14):INDEX(Forecast_Walkforward!$M:$M,$D14))/$H14 -> 0.087411765 | K14: =SUM(INDEX(Forecast_Walkforward!$N:$N,$E14):INDEX(Forecast_Walkforward!$N:$N,$D14))/$H14 -> 0.087235294 | L14: =SUM(INDEX(Forecast_Walkforward!$O:$O,$E14):INDEX(Forecast_Walkforward!$O:$O,$D14))/$H14 -> 0.082091486 | M14: =SUM(INDEX(Forecast_Walkforward!$H:$H,$E14):INDEX(Forecast_Walkforward!$H:$H,$D14))/$H14 -> 0 | N14: =SUM(INDEX(Forecast_Walkforward!$I:$I,$E14):INDEX(Forecast_Walkforward!$I:$I,$D14))/$H14 -> -0.00011764706 | O14: =SUM(INDEX(Forecast_Walkforward!$J:$J,$E14):INDEX(Forecast_Walkforward!$J:$J,$D14))/$H14 -> -0.0045294118 | P14: =SUM(INDEX(Forecast_Walkforward!$K:$K,$E14):INDEX(Forecast_Walkforward!$K:$K,$D14))/$H14 -> -0.0016359657 | Q14: =_xlfn.STDEV.S(INDEX(Forecast_Walkforward!$H:$H,$E14):INDEX(Forecast_Walkforward!$H:$H,$D14)) -> 5.5093503 | R14: =_xlfn.STDEV.S(INDEX(Forecast_Walkforward!$I:$I,$E14):INDEX(Forecast_Walkforward!$I:$I,$D14)) -> 4.6122945 | S14: =_xlfn.STDEV.S(INDEX(Forecast_Walkforward!$J:$J,$E14):INDEX(Forecast_Walkforward!$J:$J,$D14)) -> 4.5042525 | T14: =_xlfn.STDEV.S(INDEX(Forecast_Walkforward!$K:$K,$E14):INDEX(Forecast_Walkforward!$K:$K,$D14)) -> 4.4191618 | U14: =INDEX(Forecast_Walkforward!$C:$C,$D14) -> 40 | V14: =AVERAGE(INDEX(Forecast_Walkforward!$C:$C,$D14-3):INDEX(Forecast_Walkforward!$C:$C,$D14)) -> 41.5 | W14: =AVERAGE(INDEX(Forecast_Walkforward!$C:$C,$D14-7):INDEX(Forecast_Walkforward!$C:$C,$D14)) -> 41.5 | X14: =SES_Alpha*INDEX(Forecast_Walkforward!$C:$C,$D14)+(1-SES_Alpha)*INDEX(Forecast_Walkforward!$G:$G,$D14) -> 40.899519 | Y14: =MIN(I14:L14) -> 0.082091486 | Z14: =I14<=$Y14+WAPE_Tol -> FALSE | AA14: =J14<=$Y14+WAPE_Tol -> TRUE | AB14: =K14<=$Y14+WAPE_Tol -> TRUE | AC14: =L14<=$Y14+WAPE_Tol -> TRUE | AD14: =MATCH(TRUE(),Z14:AC14,0) -> 2 | AE14: =CHOOSE(AD14,"Naive","MA4","MA8","SES") -> MA4 | AF14: =INDEX(U14:X14,AD14) -> 41.5 | AG14: =INDEX(I14:L14,AD14) -> 0.087411765 | AH14: =INDEX(M14:P14,AD14) -> -0.00011764706 | AI14: =INDEX(Q14:T14,AD14) -> 4.6122945 | AJ14: =AG14*H14 -> 185.75 | AK14: =SUM(INDEX(Forecast_Walkforward!$C:$C,$F14):INDEX(Forecast_Walkforward!$C:$C,$G14)) -> 2115 | AL14: =SUM(INDEX(Forecast_Walkforward!$L:$L,$F14):INDEX(Forecast_Walkforward!$L:$L,$G14))/$AK14 -> 0.11583924 | AM14: =SUM(INDEX(Forecast_Walkforward!$M:$M,$F14):INDEX(Forecast_Walkforward!$M:$M,$G14))/$AK14 -> 0.095508274 | AN14: =SUM(INDEX(Forecast_Walkforward!$N:$N,$F14):INDEX(Forecast_Walkforward!$N:$N,$G14))/$AK14 -> 0.088947991 | AO14: =SUM(INDEX(Forecast_Walkforward!$O:$O,$F14):INDEX(Forecast_Walkforward!$O:$O,$G14))/$AK14 -> 0.088667661 | AP14: =_xlfn.STDEV.S(INDEX(Forecast_Walkforward!$H:$H,$F14):INDEX(Forecast_Walkforward!$H:$H,$G14)) -> 5.9718735 | AQ14: =_xlfn.STDEV.S(INDEX(Forecast_Walkforward!$I:$I,$F14):INDEX(Forecast_Walkforward!$I:$I,$G14)) -> 4.9357486 | AR14: =_xlfn.STDEV.S(INDEX(Forecast_Walkforward!$J:$J,$F14):INDEX(Forecast_Walkforward!$J:$J,$G14)) -> 4.6532497 | AS14: =_xlfn.STDEV.S(INDEX(Forecast_Walkforward!$K:$K,$F14):INDEX(Forecast_Walkforward!$K:$K,$G14)) -> 4.6695842 | AT14: =MIN(AL14:AO14) -> 0.088667661 | AU14: =AL14<=$AT14+WAPE_Tol -> FALSE | AV14: =AM14<=$AT14+WAPE_Tol -> TRUE | AW14: =AN14<=$AT14+WAPE_Tol -> TRUE | AX14: =AO14<=$AT14+WAPE_Tol -> TRUE | AY14: =MATCH(TRUE(),AU14:AX14,0) -> 2 | AZ14: =CHOOSE(AY14,"Naive","MA4","MA8","SES") -> MA4 | BA14: =INDEX(AP14:AS14,AY14) -> 4.9357486
A15: =Inputs!B48 -> KIT-009 | B15: =Inputs!C48 -> Digital Kitchen Scale | C15: =MATCH(A15,Demand_History!$C:$C,0) -> 834 | D15: =C15+Weeks_History-1 -> 937 | E15: =C15+Eval_Start_Week-1 -> 886 | F15: =C15+Cal_Start_Week-1 -> 870 | G15: =C15+Cal_End_Week-1 -> 921 | H15: =SUM(INDEX(Forecast_Walkforward!$C:$C,$E15):INDEX(Forecast_Walkforward!$C:$C,$D15)) -> 1845 | I15: =SUM(INDEX(Forecast_Walkforward!$L:$L,$E15):INDEX(Forecast_Walkforward!$L:$L,$D15))/$H15 -> 0.14905149 | J15: =SUM(INDEX(Forecast_Walkforward!$M:$M,$E15):INDEX(Forecast_Walkforward!$M:$M,$D15))/$H15 -> 0.10921409 | K15: =SUM(INDEX(Forecast_Walkforward!$N:$N,$E15):INDEX(Forecast_Walkforward!$N:$N,$D15))/$H15 -> 0.11124661 | L15: =SUM(INDEX(Forecast_Walkforward!$O:$O,$E15):INDEX(Forecast_Walkforward!$O:$O,$D15))/$H15 -> 0.10824638 | M15: =SUM(INDEX(Forecast_Walkforward!$H:$H,$E15):INDEX(Forecast_Walkforward!$H:$H,$D15))/$H15 -> -0.0070460705 | N15: =SUM(INDEX(Forecast_Walkforward!$I:$I,$E15):INDEX(Forecast_Walkforward!$I:$I,$D15))/$H15 -> -0.01598916 | O15: =SUM(INDEX(Forecast_Walkforward!$J:$J,$E15):INDEX(Forecast_Walkforward!$J:$J,$D15))/$H15 -> -0.030216802 | P15: =SUM(INDEX(Forecast_Walkforward!$K:$K,$E15):INDEX(Forecast_Walkforward!$K:$K,$D15))/$H15 -> -0.021742456 | Q15: =_xlfn.STDEV.S(INDEX(Forecast_Walkforward!$H:$H,$E15):INDEX(Forecast_Walkforward!$H:$H,$D15)) -> 6.4378629 | R15: =_xlfn.STDEV.S(INDEX(Forecast_Walkforward!$I:$I,$E15):INDEX(Forecast_Walkforward!$I:$I,$D15)) -> 4.8535199 | S15: =_xlfn.STDEV.S(INDEX(Forecast_Walkforward!$J:$J,$E15):INDEX(Forecast_Walkforward!$J:$J,$D15)) -> 5.1089446 | T15: =_xlfn.STDEV.S(INDEX(Forecast_Walkforward!$K:$K,$E15):INDEX(Forecast_Walkforward!$K:$K,$D15)) -> 4.9473142 | U15: =INDEX(Forecast_Walkforward!$C:$C,$D15) -> 36 | V15: =AVERAGE(INDEX(Forecast_Walkforward!$C:$C,$D15-3):INDEX(Forecast_Walkforward!$C:$C,$D15)) -> 39.5 | W15: =AVERAGE(INDEX(Forecast_Walkforward!$C:$C,$D15-7):INDEX(Forecast_Walkforward!$C:$C,$D15)) -> 41.25 | X15: =SES_Alpha*INDEX(Forecast_Walkforward!$C:$C,$D15)+(1-SES_Alpha)*INDEX(Forecast_Walkforward!$G:$G,$D15) -> 39.715593 | Y15: =MIN(I15:L15) -> 0.10824638 | Z15: =I15<=$Y15+WAPE_Tol -> FALSE | AA15: =J15<=$Y15+WAPE_Tol -> TRUE | AB15: =K15<=$Y15+WAPE_Tol -> TRUE | AC15: =L15<=$Y15+WAPE_Tol -> TRUE | AD15: =MATCH(TRUE(),Z15:AC15,0) -> 2 | AE15: =CHOOSE(AD15,"Naive","MA4","MA8","SES") -> MA4 | AF15: =INDEX(U15:X15,AD15) -> 39.5 | AG15: =INDEX(I15:L15,AD15) -> 0.10921409 | AH15: =INDEX(M15:P15,AD15) -> -0.01598916 | AI15: =INDEX(Q15:T15,AD15) -> 4.8535199 | AJ15: =AG15*H15 -> 201.5 | AK15: =SUM(INDEX(Forecast_Walkforward!$C:$C,$F15):INDEX(Forecast_Walkforward!$C:$C,$G15)) -> 1693 | AL15: =SUM(INDEX(Forecast_Walkforward!$L:$L,$F15):INDEX(Forecast_Walkforward!$L:$L,$G15))/$AK15 -> 0.15416421 | AM15: =SUM(INDEX(Forecast_Walkforward!$M:$M,$F15):INDEX(Forecast_Walkforward!$M:$M,$G15))/$AK15 -> 0.11311282 | AN15: =SUM(INDEX(Forecast_Walkforward!$N:$N,$F15):INDEX(Forecast_Walkforward!$N:$N,$G15))/$AK15 -> 0.11488482 | AO15: =SUM(INDEX(Forecast_Walkforward!$O:$O,$F15):INDEX(Forecast_Walkforward!$O:$O,$G15))/$AK15 -> 0.11643772 | AP15: =_xlfn.STDEV.S(INDEX(Forecast_Walkforward!$H:$H,$F15):INDEX(Forecast_Walkforward!$H:$H,$G15)) -> 6.2856525 | AQ15: =_xlfn.STDEV.S(INDEX(Forecast_Walkforward!$I:$I,$F15):INDEX(Forecast_Walkforward!$I:$I,$G15)) -> 4.6944236 | AR15: =_xlfn.STDEV.S(INDEX(Forecast_Walkforward!$J:$J,$F15):INDEX(Forecast_Walkforward!$J:$J,$G15)) -> 4.8612561 | AS15: =_xlfn.STDEV.S(INDEX(Forecast_Walkforward!$K:$K,$F15):INDEX(Forecast_Walkforward!$K:$K,$G15)) -> 4.850543 | AT15: =MIN(AL15:AO15) -> 0.11311282 | AU15: =AL15<=$AT15+WAPE_Tol -> FALSE | AV15: =AM15<=$AT15+WAPE_Tol -> TRUE | AW15: =AN15<=$AT15+WAPE_Tol -> TRUE | AX15: =AO15<=$AT15+WAPE_Tol -> TRUE | AY15: =MATCH(TRUE(),AU15:AX15,0) -> 2 | AZ15: =CHOOSE(AY15,"Naive","MA4","MA8","SES") -> MA4 | BA15: =INDEX(AP15:AS15,AY15) -> 4.6944236
A16: =Inputs!B49 -> KIT-010 | B16: =Inputs!C49 -> Measuring Jug 1L | C16: =MATCH(A16,Demand_History!$C:$C,0) -> 938 | D16: =C16+Weeks_History-1 -> 1041 | E16: =C16+Eval_Start_Week-1 -> 990 | F16: =C16+Cal_Start_Week-1 -> 974 | G16: =C16+Cal_End_Week-1 -> 1025 | H16: =SUM(INDEX(Forecast_Walkforward!$C:$C,$E16):INDEX(Forecast_Walkforward!$C:$C,$D16)) -> 5105 | I16: =SUM(INDEX(Forecast_Walkforward!$L:$L,$E16):INDEX(Forecast_Walkforward!$L:$L,$D16))/$H16 -> 0.12693438 | J16: =SUM(INDEX(Forecast_Walkforward!$M:$M,$E16):INDEX(Forecast_Walkforward!$M:$M,$D16))/$H16 -> 0.08956905 | K16: =SUM(INDEX(Forecast_Walkforward!$N:$N,$E16):INDEX(Forecast_Walkforward!$N:$N,$D16))/$H16 -> 0.087047013 | L16: =SUM(INDEX(Forecast_Walkforward!$O:$O,$E16):INDEX(Forecast_Walkforward!$O:$O,$D16))/$H16 -> 0.090343713 | M16: =SUM(INDEX(Forecast_Walkforward!$H:$H,$E16):INDEX(Forecast_Walkforward!$H:$H,$D16))/$H16 -> 0.00078354554 | N16: =SUM(INDEX(Forecast_Walkforward!$I:$I,$E16):INDEX(Forecast_Walkforward!$I:$I,$D16))/$H16 -> -0.0020078355 | O16: =SUM(INDEX(Forecast_Walkforward!$J:$J,$E16):INDEX(Forecast_Walkforward!$J:$J,$D16))/$H16 -> -0.004970617 | P16: =SUM(INDEX(Forecast_Walkforward!$K:$K,$E16):INDEX(Forecast_Walkforward!$K:$K,$D16))/$H16 -> -0.0023274887 | Q16: =_xlfn.STDEV.S(INDEX(Forecast_Walkforward!$H:$H,$E16):INDEX(Forecast_Walkforward!$H:$H,$D16)) -> 15.299425 | R16: =_xlfn.STDEV.S(INDEX(Forecast_Walkforward!$I:$I,$E16):INDEX(Forecast_Walkforward!$I:$I,$D16)) -> 10.37535 | S16: =_xlfn.STDEV.S(INDEX(Forecast_Walkforward!$J:$J,$E16):INDEX(Forecast_Walkforward!$J:$J,$D16)) -> 10.22415 | T16: =_xlfn.STDEV.S(INDEX(Forecast_Walkforward!$K:$K,$E16):INDEX(Forecast_Walkforward!$K:$K,$D16)) -> 10.616225 | U16: =INDEX(Forecast_Walkforward!$C:$C,$D16) -> 91 | V16: =AVERAGE(INDEX(Forecast_Walkforward!$C:$C,$D16-3):INDEX(Forecast_Walkforward!$C:$C,$D16)) -> 101 | W16: =AVERAGE(INDEX(Forecast_Walkforward!$C:$C,$D16-7):INDEX(Forecast_Walkforward!$C:$C,$D16)) -> 99.25 | X16: =SES_Alpha*INDEX(Forecast_Walkforward!$C:$C,$D16)+(1-SES_Alpha)*INDEX(Forecast_Walkforward!$G:$G,$D16) -> 97.933094 | Y16: =MIN(I16:L16) -> 0.087047013 | Z16: =I16<=$Y16+WAPE_Tol -> FALSE | AA16: =J16<=$Y16+WAPE_Tol -> TRUE | AB16: =K16<=$Y16+WAPE_Tol -> TRUE | AC16: =L16<=$Y16+WAPE_Tol -> TRUE | AD16: =MATCH(TRUE(),Z16:AC16,0) -> 2 | AE16: =CHOOSE(AD16,"Naive","MA4","MA8","SES") -> MA4 | AF16: =INDEX(U16:X16,AD16) -> 101 | AG16: =INDEX(I16:L16,AD16) -> 0.08956905 | AH16: =INDEX(M16:P16,AD16) -> -0.0020078355 | AI16: =INDEX(Q16:T16,AD16) -> 10.37535 | AJ16: =AG16*H16 -> 457.25 | AK16: =SUM(INDEX(Forecast_Walkforward!$C:$C,$F16):INDEX(Forecast_Walkforward!$C:$C,$G16)) -> 5102 | AL16: =SUM(INDEX(Forecast_Walkforward!$L:$L,$F16):INDEX(Forecast_Walkforward!$L:$L,$G16))/$AK16 -> 0.10623285 | AM16: =SUM(INDEX(Forecast_Walkforward!$M:$M,$F16):INDEX(Forecast_Walkforward!$M:$M,$G16))/$AK16 -> 0.08869071 | AN16: =SUM(INDEX(Forecast_Walkforward!$N:$N,$F16):INDEX(Forecast_Walkforward!$N:$N,$G16))/$AK16 -> 0.081953156 | AO16: =SUM(INDEX(Forecast_Walkforward!$O:$O,$F16):INDEX(Forecast_Walkforward!$O:$O,$G16))/$AK16 -> 0.084069645 | AP16: =_xlfn.STDEV.S(INDEX(Forecast_Walkforward!$H:$H,$F16):INDEX(Forecast_Walkforward!$H:$H,$G16)) -> 13.285188 | AQ16: =_xlfn.STDEV.S(INDEX(Forecast_Walkforward!$I:$I,$F16):INDEX(Forecast_Walkforward!$I:$I,$G16)) -> 10.066952 | AR16: =_xlfn.STDEV.S(INDEX(Forecast_Walkforward!$J:$J,$F16):INDEX(Forecast_Walkforward!$J:$J,$G16)) -> 9.7424638 | AS16: =_xlfn.STDEV.S(INDEX(Forecast_Walkforward!$K:$K,$F16):INDEX(Forecast_Walkforward!$K:$K,$G16)) -> 9.7633968 | AT16: =MIN(AL16:AO16) -> 0.081953156 | AU16: =AL16<=$AT16+WAPE_Tol -> FALSE | AV16: =AM16<=$AT16+WAPE_Tol -> TRUE | AW16: =AN16<=$AT16+WAPE_Tol -> TRUE | AX16: =AO16<=$AT16+WAPE_Tol -> TRUE | AY16: =MATCH(TRUE(),AU16:AX16,0) -> 2 | AZ16: =CHOOSE(AY16,"Naive","MA4","MA8","SES") -> MA4 | BA16: =INDEX(AP16:AS16,AY16) -> 10.066952
A17: =Inputs!B50 -> BTH-001 | B17: =Inputs!C50 -> Bath Towel 70x140 Grey | C17: =MATCH(A17,Demand_History!$C:$C,0) -> 1042 | D17: =C17+Weeks_History-1 -> 1145 | E17: =C17+Eval_Start_Week-1 -> 1094 | F17: =C17+Cal_Start_Week-1 -> 1078 | G17: =C17+Cal_End_Week-1 -> 1129 | H17: =SUM(INDEX(Forecast_Walkforward!$C:$C,$E17):INDEX(Forecast_Walkforward!$C:$C,$D17)) -> 6085 | I17: =SUM(INDEX(Forecast_Walkforward!$L:$L,$E17):INDEX(Forecast_Walkforward!$L:$L,$D17))/$H17 -> 0.18997535 | J17: =SUM(INDEX(Forecast_Walkforward!$M:$M,$E17):INDEX(Forecast_Walkforward!$M:$M,$D17))/$H17 -> 0.13323747 | K17: =SUM(INDEX(Forecast_Walkforward!$N:$N,$E17):INDEX(Forecast_Walkforward!$N:$N,$D17))/$H17 -> 0.12481512 | L17: =SUM(INDEX(Forecast_Walkforward!$O:$O,$E17):INDEX(Forecast_Walkforward!$O:$O,$D17))/$H17 -> 0.13400852 | M17: =SUM(INDEX(Forecast_Walkforward!$H:$H,$E17):INDEX(Forecast_Walkforward!$H:$H,$D17))/$H17 -> 0.0019720624 | N17: =SUM(INDEX(Forecast_Walkforward!$I:$I,$E17):INDEX(Forecast_Walkforward!$I:$I,$D17))/$H17 -> 0.0022596549 | O17: =SUM(INDEX(Forecast_Walkforward!$J:$J,$E17):INDEX(Forecast_Walkforward!$J:$J,$D17))/$H17 -> 0.0022596549 | P17: =SUM(INDEX(Forecast_Walkforward!$K:$K,$E17):INDEX(Forecast_Walkforward!$K:$K,$D17))/$H17 -> 0.0024115462 | Q17: =_xlfn.STDEV.S(INDEX(Forecast_Walkforward!$H:$H,$E17):INDEX(Forecast_Walkforward!$H:$H,$D17)) -> 27.118921 | R17: =_xlfn.STDEV.S(INDEX(Forecast_Walkforward!$I:$I,$E17):INDEX(Forecast_Walkforward!$I:$I,$D17)) -> 18.698158 | S17: =_xlfn.STDEV.S(INDEX(Forecast_Walkforward!$J:$J,$E17):INDEX(Forecast_Walkforward!$J:$J,$D17)) -> 17.848948 | T17: =_xlfn.STDEV.S(INDEX(Forecast_Walkforward!$K:$K,$E17):INDEX(Forecast_Walkforward!$K:$K,$D17)) -> 18.752751 | U17: =INDEX(Forecast_Walkforward!$C:$C,$D17) -> 103 | V17: =AVERAGE(INDEX(Forecast_Walkforward!$C:$C,$D17-3):INDEX(Forecast_Walkforward!$C:$C,$D17)) -> 106 | W17: =AVERAGE(INDEX(Forecast_Walkforward!$C:$C,$D17-7):INDEX(Forecast_Walkforward!$C:$C,$D17)) -> 109.75 | X17: =SES_Alpha*INDEX(Forecast_Walkforward!$C:$C,$D17)+(1-SES_Alpha)*INDEX(Forecast_Walkforward!$G:$G,$D17) -> 109.23514 | Y17: =MIN(I17:L17) -> 0.12481512 | Z17: =I17<=$Y17+WAPE_Tol -> FALSE | AA17: =J17<=$Y17+WAPE_Tol -> TRUE | AB17: =K17<=$Y17+WAPE_Tol -> TRUE | AC17: =L17<=$Y17+WAPE_Tol -> TRUE | AD17: =MATCH(TRUE(),Z17:AC17,0) -> 2 | AE17: =CHOOSE(AD17,"Naive","MA4","MA8","SES") -> MA4 | AF17: =INDEX(U17:X17,AD17) -> 106 | AG17: =INDEX(I17:L17,AD17) -> 0.13323747 | AH17: =INDEX(M17:P17,AD17) -> 0.0022596549 | AI17: =INDEX(Q17:T17,AD17) -> 18.698158 | AJ17: =AG17*H17 -> 810.75 | AK17: =SUM(INDEX(Forecast_Walkforward!$C:$C,$F17):INDEX(Forecast_Walkforward!$C:$C,$G17)) -> 6213 | AL17: =SUM(INDEX(Forecast_Walkforward!$L:$L,$F17):INDEX(Forecast_Walkforward!$L:$L,$G17))/$AK17 -> 0.19668437 | AM17: =SUM(INDEX(Forecast_Walkforward!$M:$M,$F17):INDEX(Forecast_Walkforward!$M:$M,$G17))/$AK17 -> 0.14413327 | AN17: =SUM(INDEX(Forecast_Walkforward!$N:$N,$F17):INDEX(Forecast_Walkforward!$N:$N,$G17))/$AK17 -> 0.13387253 | AO17: =SUM(INDEX(Forecast_Walkforward!$O:$O,$F17):INDEX(Forecast_Walkforward!$O:$O,$G17))/$AK17 -> 0.14303468 | AP17: =_xlfn.STDEV.S(INDEX(Forecast_Walkforward!$H:$H,$F17):INDEX(Forecast_Walkforward!$H:$H,$G17)) -> 28.368694 | AQ17: =_xlfn.STDEV.S(INDEX(Forecast_Walkforward!$I:$I,$F17):INDEX(Forecast_Walkforward!$I:$I,$G17)) -> 20.105125 | AR17: =_xlfn.STDEV.S(INDEX(Forecast_Walkforward!$J:$J,$F17):INDEX(Forecast_Walkforward!$J:$J,$G17)) -> 18.915114 | AS17: =_xlfn.STDEV.S(INDEX(Forecast_Walkforward!$K:$K,$F17):INDEX(Forecast_Walkforward!$K:$K,$G17)) -> 20.004516 | AT17: =MIN(AL17:AO17) -> 0.13387253 | AU17: =AL17<=$AT17+WAPE_Tol -> FALSE | AV17: =AM17<=$AT17+WAPE_Tol -> FALSE | AW17: =AN17<=$AT17+WAPE_Tol -> TRUE | AX17: =AO17<=$AT17+WAPE_Tol -> TRUE | AY17: =MATCH(TRUE(),AU17:AX17,0) -> 3 | AZ17: =CHOOSE(AY17,"Naive","MA4","MA8","SES") -> MA8 | BA17: =INDEX(AP17:AS17,AY17) -> 18.915114
A18: =Inputs!B51 -> BTH-002 | B18: =Inputs!C51 -> Hand Towel 50x100 White | C18: =MATCH(A18,Demand_History!$C:$C,0) -> 1146 | D18: =C18+Weeks_History-1 -> 1249 | E18: =C18+Eval_Start_Week-1 -> 1198 | F18: =C18+Cal_Start_Week-1 -> 1182 | G18: =C18+Cal_End_Week-1 -> 1233 | H18: =SUM(INDEX(Forecast_Walkforward!$C:$C,$E18):INDEX(Forecast_Walkforward!$C:$C,$D18)) -> 7872 | I18: =SUM(INDEX(Forecast_Walkforward!$L:$L,$E18):INDEX(Forecast_Walkforward!$L:$L,$D18))/$H18 -> 0.10086382 | J18: =SUM(INDEX(Forecast_Walkforward!$M:$M,$E18):INDEX(Forecast_Walkforward!$M:$M,$D18))/$H18 -> 0.070915904 | K18: =SUM(INDEX(Forecast_Walkforward!$N:$N,$E18):INDEX(Forecast_Walkforward!$N:$N,$D18))/$H18 -> 0.070296621 | L18: =SUM(INDEX(Forecast_Walkforward!$O:$O,$E18):INDEX(Forecast_Walkforward!$O:$O,$D18))/$H18 -> 0.072404702 | M18: =SUM(INDEX(Forecast_Walkforward!$H:$H,$E18):INDEX(Forecast_Walkforward!$H:$H,$D18))/$H18 -> 0.0017784553 | N18: =SUM(INDEX(Forecast_Walkforward!$I:$I,$E18):INDEX(Forecast_Walkforward!$I:$I,$D18))/$H18 -> 0.00390625 | O18: =SUM(INDEX(Forecast_Walkforward!$J:$J,$E18):INDEX(Forecast_Walkforward!$J:$J,$D18))/$H18 -> 0.0066533283 | P18: =SUM(INDEX(Forecast_Walkforward!$K:$K,$E18):INDEX(Forecast_Walkforward!$K:$K,$D18))/$H18 -> 0.004717227 | Q18: =_xlfn.STDEV.S(INDEX(Forecast_Walkforward!$H:$H,$E18):INDEX(Forecast_Walkforward!$H:$H,$D18)) -> 19.981477 | R18: =_xlfn.STDEV.S(INDEX(Forecast_Walkforward!$I:$I,$E18):INDEX(Forecast_Walkforward!$I:$I,$D18)) -> 14.063496 | S18: =_xlfn.STDEV.S(INDEX(Forecast_Walkforward!$J:$J,$E18):INDEX(Forecast_Walkforward!$J:$J,$D18)) -> 13.872613 | T18: =_xlfn.STDEV.S(INDEX(Forecast_Walkforward!$K:$K,$E18):INDEX(Forecast_Walkforward!$K:$K,$D18)) -> 14.388641 | U18: =INDEX(Forecast_Walkforward!$C:$C,$D18) -> 148 | V18: =AVERAGE(INDEX(Forecast_Walkforward!$C:$C,$D18-3):INDEX(Forecast_Walkforward!$C:$C,$D18)) -> 146.25 | W18: =AVERAGE(INDEX(Forecast_Walkforward!$C:$C,$D18-7):INDEX(Forecast_Walkforward!$C:$C,$D18)) -> 148.125 | X18: =SES_Alpha*INDEX(Forecast_Walkforward!$C:$C,$D18)+(1-SES_Alpha)*INDEX(Forecast_Walkforward!$G:$G,$D18) -> 145.85158 | Y18: =MIN(I18:L18) -> 0.070296621 | Z18: =I18<=$Y18+WAPE_Tol -> FALSE | AA18: =J18<=$Y18+WAPE_Tol -> TRUE | AB18: =K18<=$Y18+WAPE_Tol -> TRUE | AC18: =L18<=$Y18+WAPE_Tol -> TRUE | AD18: =MATCH(TRUE(),Z18:AC18,0) -> 2 | AE18: =CHOOSE(AD18,"Naive","MA4","MA8","SES") -> MA4 | AF18: =INDEX(U18:X18,AD18) -> 146.25 | AG18: =INDEX(I18:L18,AD18) -> 0.070915904 | AH18: =INDEX(M18:P18,AD18) -> 0.00390625 | AI18: =INDEX(Q18:T18,AD18) -> 14.063496 | AJ18: =AG18*H18 -> 558.25 | AK18: =SUM(INDEX(Forecast_Walkforward!$C:$C,$F18):INDEX(Forecast_Walkforward!$C:$C,$G18)) -> 7961 | AL18: =SUM(INDEX(Forecast_Walkforward!$L:$L,$F18):INDEX(Forecast_Walkforward!$L:$L,$G18))/$AK18 -> 0.10689612 | AM18: =SUM(INDEX(Forecast_Walkforward!$M:$M,$F18):INDEX(Forecast_Walkforward!$M:$M,$G18))/$AK18 -> 0.075493029 | AN18: =SUM(INDEX(Forecast_Walkforward!$N:$N,$F18):INDEX(Forecast_Walkforward!$N:$N,$G18))/$AK18 -> 0.077392915 | AO18: =SUM(INDEX(Forecast_Walkforward!$O:$O,$F18):INDEX(Forecast_Walkforward!$O:$O,$G18))/$AK18 -> 0.077646762 | AP18: =_xlfn.STDEV.S(INDEX(Forecast_Walkforward!$H:$H,$F18):INDEX(Forecast_Walkforward!$H:$H,$G18)) -> 20.935034 | AQ18: =_xlfn.STDEV.S(INDEX(Forecast_Walkforward!$I:$I,$F18):INDEX(Forecast_Walkforward!$I:$I,$G18)) -> 14.78887 | AR18: =_xlfn.STDEV.S(INDEX(Forecast_Walkforward!$J:$J,$F18):INDEX(Forecast_Walkforward!$J:$J,$G18)) -> 15.001634 | AS18: =_xlfn.STDEV.S(INDEX(Forecast_Walkforward!$K:$K,$F18):INDEX(Forecast_Walkforward!$K:$K,$G18)) -> 15.211368 | AT18: =MIN(AL18:AO18) -> 0.075493029 | AU18: =AL18<=$AT18+WAPE_Tol -> FALSE | AV18: =AM18<=$AT18+WAPE_Tol -> TRUE | AW18: =AN18<=$AT18+WAPE_Tol -> TRUE | AX18: =AO18<=$AT18+WAPE_Tol -> TRUE | AY18: =MATCH(TRUE(),AU18:AX18,0) -> 2 | AZ18: =CHOOSE(AY18,"Naive","MA4","MA8","SES") -> MA4 | BA18: =INDEX(AP18:AS18,AY18) -> 14.78887
... A54: =Inputs!B87 -> CLN-011 | B54: =Inputs!C87 -> Oven Cleaner Gel | C54: =MATCH(A54,Demand_History!$C:$C,0) -> 4890 | D54: =C54+Weeks_History-1 -> 4993 | E54: =C54+Eval_Start_Week-1 -> 4942 | F54: =C54+Cal_Start_Week-1 -> 4926 | G54: =C54+Cal_End_Week-1 -> 4977 | H54: =SUM(INDEX(Forecast_Walkforward!$C:$C,$E54):INDEX(Forecast_Walkforward!$C:$C,$D54)) -> 2092 | I54: =SUM(INDEX(Forecast_Walkforward!$L:$L,$E54):INDEX(Forecast_Walkforward!$L:$L,$D54))/$H54 -> 0.12954111 | J54: =SUM(INDEX(Forecast_Walkforward!$M:$M,$E54):INDEX(Forecast_Walkforward!$M:$M,$D54))/$H54 -> 0.10145793 | K54: =SUM(INDEX(Forecast_Walkforward!$N:$N,$E54):INDEX(Forecast_Walkforward!$N:$N,$D54))/$H54 -> 0.09291348 | L54: =SUM(INDEX(Forecast_Walkforward!$O:$O,$E54):INDEX(Forecast_Walkforward!$O:$O,$D54))/$H54 -> 0.10049573 | M54: =SUM(INDEX(Forecast_Walkforward!$H:$H,$E54):INDEX(Forecast_Walkforward!$H:$H,$D54))/$H54 -> -0.0052581262 | N54: =SUM(INDEX(Forecast_Walkforward!$I:$I,$E54):INDEX(Forecast_Walkforward!$I:$I,$D54))/$H54 -> -0.0084847036 | O54: =SUM(INDEX(Forecast_Walkforward!$J:$J,$E54):INDEX(Forecast_Walkforward!$J:$J,$D54))/$H54 -> -0.0096199809 | P54: =SUM(INDEX(Forecast_Walkforward!$K:$K,$E54):INDEX(Forecast_Walkforward!$K:$K,$D54))/$H54 -> -0.0083582647 | Q54: =_xlfn.STDEV.S(INDEX(Forecast_Walkforward!$H:$H,$E54):INDEX(Forecast_Walkforward!$H:$H,$D54)) -> 6.4847832 | R54: =_xlfn.STDEV.S(INDEX(Forecast_Walkforward!$I:$I,$E54):INDEX(Forecast_Walkforward!$I:$I,$D54)) -> 5.0256764 | S54: =_xlfn.STDEV.S(INDEX(Forecast_Walkforward!$J:$J,$E54):INDEX(Forecast_Walkforward!$J:$J,$D54)) -> 4.614705 | T54: =_xlfn.STDEV.S(INDEX(Forecast_Walkforward!$K:$K,$E54):INDEX(Forecast_Walkforward!$K:$K,$D54)) -> 4.9705626 | U54: =INDEX(Forecast_Walkforward!$C:$C,$D54) -> 45 | V54: =AVERAGE(INDEX(Forecast_Walkforward!$C:$C,$D54-3):INDEX(Forecast_Walkforward!$C:$C,$D54)) -> 43.75 | W54: =AVERAGE(INDEX(Forecast_Walkforward!$C:$C,$D54-7):INDEX(Forecast_Walkforward!$C:$C,$D54)) -> 42.125 | X54: =SES_Alpha*INDEX(Forecast_Walkforward!$C:$C,$D54)+(1-SES_Alpha)*INDEX(Forecast_Walkforward!$G:$G,$D54) -> 42.517216 | Y54: =MIN(I54:L54) -> 0.09291348 | Z54: =I54<=$Y54+WAPE_Tol -> FALSE | AA54: =J54<=$Y54+WAPE_Tol -> TRUE | AB54: =K54<=$Y54+WAPE_Tol -> TRUE | AC54: =L54<=$Y54+WAPE_Tol -> TRUE | AD54: =MATCH(TRUE(),Z54:AC54,0) -> 2 | AE54: =CHOOSE(AD54,"Naive","MA4","MA8","SES") -> MA4 | AF54: =INDEX(U54:X54,AD54) -> 43.75 | AG54: =INDEX(I54:L54,AD54) -> 0.10145793 | AH54: =INDEX(M54:P54,AD54) -> -0.0084847036 | AI54: =INDEX(Q54:T54,AD54) -> 5.0256764 | AJ54: =AG54*H54 -> 212.25 | AK54: =SUM(INDEX(Forecast_Walkforward!$C:$C,$F54):INDEX(Forecast_Walkforward!$C:$C,$G54)) -> 2083 | AL54: =SUM(INDEX(Forecast_Walkforward!$L:$L,$F54):INDEX(Forecast_Walkforward!$L:$L,$G54))/$AK54 -> 0.12914066 | AM54: =SUM(INDEX(Forecast_Walkforward!$M:$M,$F54):INDEX(Forecast_Walkforward!$M:$M,$G54))/$AK54 -> 0.10489678 | AN54: =SUM(INDEX(Forecast_Walkforward!$N:$N,$F54):INDEX(Forecast_Walkforward!$N:$N,$G54))/$AK54 -> 0.096675468 | AO54: =SUM(INDEX(Forecast_Walkforward!$O:$O,$F54):INDEX(Forecast_Walkforward!$O:$O,$G54))/$AK54 -> 0.10374716 | AP54: =_xlfn.STDEV.S(INDEX(Forecast_Walkforward!$H:$H,$F54):INDEX(Forecast_Walkforward!$H:$H,$G54)) -> 6.5334445 | AQ54: =_xlfn.STDEV.S(INDEX(Forecast_Walkforward!$I:$I,$F54):INDEX(Forecast_Walkforward!$I:$I,$G54)) -> 5.0277698 | AR54: =_xlfn.STDEV.S(INDEX(Forecast_Walkforward!$J:$J,$F54):INDEX(Forecast_Walkforward!$J:$J,$G54)) -> 4.6432058 | AS54: =_xlfn.STDEV.S(INDEX(Forecast_Walkforward!$K:$K,$F54):INDEX(Forecast_Walkforward!$K:$K,$G54)) -> 5.0089471 | AT54: =MIN(AL54:AO54) -> 0.096675468 | AU54: =AL54<=$AT54+WAPE_Tol -> FALSE | AV54: =AM54<=$AT54+WAPE_Tol -> TRUE | AW54: =AN54<=$AT54+WAPE_Tol -> TRUE | AX54: =AO54<=$AT54+WAPE_Tol -> TRUE | AY54: =MATCH(TRUE(),AU54:AX54,0) -> 2 | AZ54: =CHOOSE(AY54,"Naive","MA4","MA8","SES") -> MA4 | BA54: =INDEX(AP54:AS54,AY54) -> 5.0277698

Sheet Forecast_Walkforward
A1: SKU | B1: Week | C1: Actual Demand | D1: Naive Fcst | E1: MA4 Fcst | F1: MA8 Fcst | G1: SES Fcst | H1: Error Naive (F-A) | I1: Error MA4 (F-A) | J1: Error MA8 (F-A) | K1: Error SES (F-A) | L1: Abs Err Naive | M1: Abs Err MA4 | N1: Abs Err MA8 | O1: Abs Err SES | P1: In Live Evaluation Window? | Q1: In Backtest Calibration Window?
A2: =Demand_History!C2 -> KIT-001 | B2: =Demand_History!A2 -> 1 | C2: =Demand_History!D2 -> 62 | D2: ="" | E2: ="" | F2: ="" | G2: ="" | H2: =IF(D2="","",D2-C2) | I2: =IF(E2="","",E2-C2) | J2: =IF(F2="","",F2-C2) | K2: =IF(G2="","",G2-C2) | L2: =IF(H2="","",ABS(H2)) | M2: =IF(I2="","",ABS(I2)) | N2: =IF(J2="","",ABS(J2)) | O2: =IF(K2="","",ABS(K2)) | P2: =IF(B2>=Eval_Start_Week,"YES","") | Q2: =IF(AND(B2>=Cal_Start_Week,B2<=Cal_End_Week),"YES","")
A3: =Demand_History!C3 -> KIT-001 | B3: =Demand_History!A3 -> 2 | C3: =Demand_History!D3 -> 58 | D3: =IF(B3>=2,C2,"") -> 62 | E3: ="" | F3: ="" | G3: =IF(B3=1,"",IF(B3=2,C2,SES_Alpha*C2+(1-SES_Alpha)*G2)) -> 62 | H3: =IF(D3="","",D3-C3) -> 4 | I3: =IF(E3="","",E3-C3) | J3: =IF(F3="","",F3-C3) | K3: =IF(G3="","",G3-C3) -> 4 | L3: =IF(H3="","",ABS(H3)) -> 4 | M3: =IF(I3="","",ABS(I3)) | N3: =IF(J3="","",ABS(J3)) | O3: =IF(K3="","",ABS(K3)) -> 4 | P3: =IF(B3>=Eval_Start_Week,"YES","") | Q3: =IF(AND(B3>=Cal_Start_Week,B3<=Cal_End_Week),"YES","")
A4: =Demand_History!C4 -> KIT-001 | B4: =Demand_History!A4 -> 3 | C4: =Demand_History!D4 -> 53 | D4: =IF(B4>=2,C3,"") -> 58 | E4: ="" | F4: ="" | G4: =IF(B4=1,"",IF(B4=2,C3,SES_Alpha*C3+(1-SES_Alpha)*G3)) -> 60.8 | H4: =IF(D4="","",D4-C4) -> 5 | I4: =IF(E4="","",E4-C4) | J4: =IF(F4="","",F4-C4) | K4: =IF(G4="","",G4-C4) -> 7.8 | L4: =IF(H4="","",ABS(H4)) -> 5 | M4: =IF(I4="","",ABS(I4)) | N4: =IF(J4="","",ABS(J4)) | O4: =IF(K4="","",ABS(K4)) -> 7.8 | P4: =IF(B4>=Eval_Start_Week,"YES","") | Q4: =IF(AND(B4>=Cal_Start_Week,B4<=Cal_End_Week),"YES","")
A5: =Demand_History!C5 -> KIT-001 | B5: =Demand_History!A5 -> 4 | C5: =Demand_History!D5 -> 56 | D5: =IF(B5>=2,C4,"") -> 53 | E5: ="" | F5: ="" | G5: =IF(B5=1,"",IF(B5=2,C4,SES_Alpha*C4+(1-SES_Alpha)*G4)) -> 58.46 | H5: =IF(D5="","",D5-C5) -> -3 | I5: =IF(E5="","",E5-C5) | J5: =IF(F5="","",F5-C5) | K5: =IF(G5="","",G5-C5) -> 2.46 | L5: =IF(H5="","",ABS(H5)) -> 3 | M5: =IF(I5="","",ABS(I5)) | N5: =IF(J5="","",ABS(J5)) | O5: =IF(K5="","",ABS(K5)) -> 2.46 | P5: =IF(B5>=Eval_Start_Week,"YES","") | Q5: =IF(AND(B5>=Cal_Start_Week,B5<=Cal_End_Week),"YES","")
A6: =Demand_History!C6 -> KIT-001 | B6: =Demand_History!A6 -> 5 | C6: =Demand_History!D6 -> 52 | D6: =IF(B6>=2,C5,"") -> 56 | E6: =IF(B6>=5,AVERAGE(C2:C5),"") -> 57.25 | F6: ="" | G6: =IF(B6=1,"",IF(B6=2,C5,SES_Alpha*C5+(1-SES_Alpha)*G5)) -> 57.722 | H6: =IF(D6="","",D6-C6) -> 4 | I6: =IF(E6="","",E6-C6) -> 5.25 | J6: =IF(F6="","",F6-C6) | K6: =IF(G6="","",G6-C6) -> 5.722 | L6: =IF(H6="","",ABS(H6)) -> 4 | M6: =IF(I6="","",ABS(I6)) -> 5.25 | N6: =IF(J6="","",ABS(J6)) | O6: =IF(K6="","",ABS(K6)) -> 5.722 | P6: =IF(B6>=Eval_Start_Week,"YES","") | Q6: =IF(AND(B6>=Cal_Start_Week,B6<=Cal_End_Week),"YES","")
A7: =Demand_History!C7 -> KIT-001 | B7: =Demand_History!A7 -> 6 | C7: =Demand_History!D7 -> 60 | D7: =IF(B7>=2,C6,"") -> 52 | E7: =IF(B7>=5,AVERAGE(C3:C6),"") -> 54.75 | F7: ="" | G7: =IF(B7=1,"",IF(B7=2,C6,SES_Alpha*C6+(1-SES_Alpha)*G6)) -> 56.0054 | H7: =IF(D7="","",D7-C7) -> -8 | I7: =IF(E7="","",E7-C7) -> -5.25 | J7: =IF(F7="","",F7-C7) | K7: =IF(G7="","",G7-C7) -> -3.9946 | L7: =IF(H7="","",ABS(H7)) -> 8 | M7: =IF(I7="","",ABS(I7)) -> 5.25 | N7: =IF(J7="","",ABS(J7)) | O7: =IF(K7="","",ABS(K7)) -> 3.9946 | P7: =IF(B7>=Eval_Start_Week,"YES","") | Q7: =IF(AND(B7>=Cal_Start_Week,B7<=Cal_End_Week),"YES","")
A8: =Demand_History!C8 -> KIT-001 | B8: =Demand_History!A8 -> 7 | C8: =Demand_History!D8 -> 71 | D8: =IF(B8>=2,C7,"") -> 60 | E8: =IF(B8>=5,AVERAGE(C4:C7),"") -> 55.25 | F8: ="" | G8: =IF(B8=1,"",IF(B8=2,C7,SES_Alpha*C7+(1-SES_Alpha)*G7)) -> 57.20378 | H8: =IF(D8="","",D8-C8) -> -11 | I8: =IF(E8="","",E8-C8) -> -15.75 | J8: =IF(F8="","",F8-C8) | K8: =IF(G8="","",G8-C8) -> -13.79622 | L8: =IF(H8="","",ABS(H8)) -> 11 | M8: =IF(I8="","",ABS(I8)) -> 15.75 | N8: =IF(J8="","",ABS(J8)) | O8: =IF(K8="","",ABS(K8)) -> 13.79622 | P8: =IF(B8>=Eval_Start_Week,"YES","") | Q8: =IF(AND(B8>=Cal_Start_Week,B8<=Cal_End_Week),"YES","")
A9: =Demand_History!C9 -> KIT-001 | B9: =Demand_History!A9 -> 8 | C9: =Demand_History!D9 -> 56 | D9: =IF(B9>=2,C8,"") -> 71 | E9: =IF(B9>=5,AVERAGE(C5:C8),"") -> 59.75 | F9: ="" | G9: =IF(B9=1,"",IF(B9=2,C8,SES_Alpha*C8+(1-SES_Alpha)*G8)) -> 61.342646 | H9: =IF(D9="","",D9-C9) -> 15 | I9: =IF(E9="","",E9-C9) -> 3.75 | J9: =IF(F9="","",F9-C9) | K9: =IF(G9="","",G9-C9) -> 5.342646 | L9: =IF(H9="","",ABS(H9)) -> 15 | M9: =IF(I9="","",ABS(I9)) -> 3.75 | N9: =IF(J9="","",ABS(J9)) | O9: =IF(K9="","",ABS(K9)) -> 5.342646 | P9: =IF(B9>=Eval_Start_Week,"YES","") | Q9: =IF(AND(B9>=Cal_Start_Week,B9<=Cal_End_Week),"YES","")
A10: =Demand_History!C10 -> KIT-001 | B10: =Demand_History!A10 -> 9 | C10: =Demand_History!D10 -> 55 | D10: =IF(B10>=2,C9,"") -> 56 | E10: =IF(B10>=5,AVERAGE(C6:C9),"") -> 59.75 | F10: =IF(B10>=9,AVERAGE(C2:C9),"") -> 58.5 | G10: =IF(B10=1,"",IF(B10=2,C9,SES_Alpha*C9+(1-SES_Alpha)*G9)) -> 59.739852 | H10: =IF(D10="","",D10-C10) -> 1 | I10: =IF(E10="","",E10-C10) -> 4.75 | J10: =IF(F10="","",F10-C10) -> 3.5 | K10: =IF(G10="","",G10-C10) -> 4.7398522 | L10: =IF(H10="","",ABS(H10)) -> 1 | M10: =IF(I10="","",ABS(I10)) -> 4.75 | N10: =IF(J10="","",ABS(J10)) -> 3.5 | O10: =IF(K10="","",ABS(K10)) -> 4.7398522 | P10: =IF(B10>=Eval_Start_Week,"YES","") | Q10: =IF(AND(B10>=Cal_Start_Week,B10<=Cal_End_Week),"YES","")
A11: =Demand_History!C11 -> KIT-001 | B11: =Demand_History!A11 -> 10 | C11: =Demand_History!D11 -> 64 | D11: =IF(B11>=2,C10,"") -> 55 | E11: =IF(B11>=5,AVERAGE(C7:C10),"") -> 60.5 | F11: =IF(B11>=9,AVERAGE(C3:C10),"") -> 57.625 | G11: =IF(B11=1,"",IF(B11=2,C10,SES_Alpha*C10+(1-SES_Alpha)*G10)) -> 58.317897 | H11: =IF(D11="","",D11-C11) -> -9 | I11: =IF(E11="","",E11-C11) -> -3.5 | J11: =IF(F11="","",F11-C11) -> -6.375 | K11: =IF(G11="","",G11-C11) -> -5.6821035 | L11: =IF(H11="","",ABS(H11)) -> 9 | M11: =IF(I11="","",ABS(I11)) -> 3.5 | N11: =IF(J11="","",ABS(J11)) -> 6.375 | O11: =IF(K11="","",ABS(K11)) -> 5.6821035 | P11: =IF(B11>=Eval_Start_Week,"YES","") | Q11: =IF(AND(B11>=Cal_Start_Week,B11<=Cal_End_Week),"YES","")
A12: =Demand_History!C12 -> KIT-001 | B12: =Demand_History!A12 -> 11 | C12: =Demand_History!D12 -> 63 | D12: =IF(B12>=2,C11,"") -> 64 | E12: =IF(B12>=5,AVERAGE(C8:C11),"") -> 61.5 | F12: =IF(B12>=9,AVERAGE(C4:C11),"") -> 58.375 | G12: =IF(B12=1,"",IF(B12=2,C11,SES_Alpha*C11+(1-SES_Alpha)*G11)) -> 60.022528 | H12: =IF(D12="","",D12-C12) -> 1 | I12: =IF(E12="","",E12-C12) -> -1.5 | J12: =IF(F12="","",F12-C12) -> -4.625 | K12: =IF(G12="","",G12-C12) -> -2.9774724 | L12: =IF(H12="","",ABS(H12)) -> 1 | M12: =IF(I12="","",ABS(I12)) -> 1.5 | N12: =IF(J12="","",ABS(J12)) -> 4.625 | O12: =IF(K12="","",ABS(K12)) -> 2.9774724 | P12: =IF(B12>=Eval_Start_Week,"YES","") | Q12: =IF(AND(B12>=Cal_Start_Week,B12<=Cal_End_Week),"YES","")
A13: =Demand_History!C13 -> KIT-001 | B13: =Demand_History!A13 -> 12 | C13: =Demand_History!D13 -> 61 | D13: =IF(B13>=2,C12,"") -> 63 | E13: =IF(B13>=5,AVERAGE(C9:C12),"") -> 59.5 | F13: =IF(B13>=9,AVERAGE(C5:C12),"") -> 59.625 | G13: =IF(B13=1,"",IF(B13=2,C12,SES_Alpha*C12+(1-SES_Alpha)*G12)) -> 60.915769 | H13: =IF(D13="","",D13-C13) -> 2 | I13: =IF(E13="","",E13-C13) -> -1.5 | J13: =IF(F13="","",F13-C13) -> -1.375 | K13: =IF(G13="","",G13-C13) -> -0.084230695 | L13: =IF(H13="","",ABS(H13)) -> 2 | M13: =IF(I13="","",ABS(I13)) -> 1.5 | N13: =IF(J13="","",ABS(J13)) -> 1.375 | O13: =IF(K13="","",ABS(K13)) -> 0.084230695 | P13: =IF(B13>=Eval_Start_Week,"YES","") | Q13: =IF(AND(B13>=Cal_Start_Week,B13<=Cal_End_Week),"YES","")
A14: =Demand_History!C14 -> KIT-001 | B14: =Demand_History!A14 -> 13 | C14: =Demand_History!D14 -> 53 | D14: =IF(B14>=2,C13,"") -> 61 | E14: =IF(B14>=5,AVERAGE(C10:C13),"") -> 60.75 | F14: =IF(B14>=9,AVERAGE(C6:C13),"") -> 60.25 | G14: =IF(B14=1,"",IF(B14=2,C13,SES_Alpha*C13+(1-SES_Alpha)*G13)) -> 60.941039 | H14: =IF(D14="","",D14-C14) -> 8 | I14: =IF(E14="","",E14-C14) -> 7.75 | J14: =IF(F14="","",F14-C14) -> 7.25 | K14: =IF(G14="","",G14-C14) -> 7.9410385 | L14: =IF(H14="","",ABS(H14)) -> 8 | M14: =IF(I14="","",ABS(I14)) -> 7.75 | N14: =IF(J14="","",ABS(J14)) -> 7.25 | O14: =IF(K14="","",ABS(K14)) -> 7.9410385 | P14: =IF(B14>=Eval_Start_Week,"YES","") | Q14: =IF(AND(B14>=Cal_Start_Week,B14<=Cal_End_Week),"YES","")
A15: =Demand_History!C15 -> KIT-001 | B15: =Demand_History!A15 -> 14 | C15: =Demand_History!D15 -> 60 | D15: =IF(B15>=2,C14,"") -> 53 | E15: =IF(B15>=5,AVERAGE(C11:C14),"") -> 60.25 | F15: =IF(B15>=9,AVERAGE(C7:C14),"") -> 60.375 | G15: =IF(B15=1,"",IF(B15=2,C14,SES_Alpha*C14+(1-SES_Alpha)*G14)) -> 58.558727 | H15: =IF(D15="","",D15-C15) -> -7 | I15: =IF(E15="","",E15-C15) -> 0.25 | J15: =IF(F15="","",F15-C15) -> 0.375 | K15: =IF(G15="","",G15-C15) -> -1.441273 | L15: =IF(H15="","",ABS(H15)) -> 7 | M15: =IF(I15="","",ABS(I15)) -> 0.25 | N15: =IF(J15="","",ABS(J15)) -> 0.375 | O15: =IF(K15="","",ABS(K15)) -> 1.441273 | P15: =IF(B15>=Eval_Start_Week,"YES","") | Q15: =IF(AND(B15>=Cal_Start_Week,B15<=Cal_End_Week),"YES","")
A16: =Demand_History!C16 -> KIT-001 | B16: =Demand_History!A16 -> 15 | C16: =Demand_History!D16 -> 65 | D16: =IF(B16>=2,C15,"") -> 60 | E16: =IF(B16>=5,AVERAGE(C12:C15),"") -> 59.25 | F16: =IF(B16>=9,AVERAGE(C8:C15),"") -> 60.375 | G16: =IF(B16=1,"",IF(B16=2,C15,SES_Alpha*C15+(1-SES_Alpha)*G15)) -> 58.991109 | H16: =IF(D16="","",D16-C16) -> -5 | I16: =IF(E16="","",E16-C16) -> -5.75 | J16: =IF(F16="","",F16-C16) -> -4.625 | K16: =IF(G16="","",G16-C16) -> -6.0088911 | L16: =IF(H16="","",ABS(H16)) -> 5 | M16: =IF(I16="","",ABS(I16)) -> 5.75 | N16: =IF(J16="","",ABS(J16)) -> 4.625 | O16: =IF(K16="","",ABS(K16)) -> 6.0088911 | P16: =IF(B16>=Eval_Start_Week,"YES","") | Q16: =IF(AND(B16>=Cal_Start_Week,B16<=Cal_End_Week),"YES","")
A17: =Demand_History!C17 -> KIT-001 | B17: =Demand_History!A17 -> 16 | C17: =Demand_History!D17 -> 49 | D17: =IF(B17>=2,C16,"") -> 65 | E17: =IF(B17>=5,AVERAGE(C13:C16),"") -> 59.75 | F17: =IF(B17>=9,AVERAGE(C9:C16),"") -> 59.625 | G17: =IF(B17=1,"",IF(B17=2,C16,SES_Alpha*C16+(1-SES_Alpha)*G16)) -> 60.793776 | H17: =IF(D17="","",D17-C17) -> 16 | I17: =IF(E17="","",E17-C17) -> 10.75 | J17: =IF(F17="","",F17-C17) -> 10.625 | K17: =IF(G17="","",G17-C17) -> 11.793776 | L17: =IF(H17="","",ABS(H17)) -> 16 | M17: =IF(I17="","",ABS(I17)) -> 10.75 | N17: =IF(J17="","",ABS(J17)) -> 10.625 | O17: =IF(K17="","",ABS(K17)) -> 11.793776 | P17: =IF(B17>=Eval_Start_Week,"YES","") | Q17: =IF(AND(B17>=Cal_Start_Week,B17<=Cal_End_Week),"YES","")
A18: =Demand_History!C18 -> KIT-001 | B18: =Demand_History!A18 -> 17 | C18: =Demand_History!D18 -> 56 | D18: =IF(B18>=2,C17,"") -> 49 | E18: =IF(B18>=5,AVERAGE(C14:C17),"") -> 56.75 | F18: =IF(B18>=9,AVERAGE(C10:C17),"") -> 58.75 | G18: =IF(B18=1,"",IF(B18=2,C17,SES_Alpha*C17+(1-SES_Alpha)*G17)) -> 57.255643 | H18: =IF(D18="","",D18-C18) -> -7 | I18: =IF(E18="","",E18-C18) -> 0.75 | J18: =IF(F18="","",F18-C18) -> 2.75 | K18: =IF(G18="","",G18-C18) -> 1.2556433 | L18: =IF(H18="","",ABS(H18)) -> 7 | M18: =IF(I18="","",ABS(I18)) -> 0.75 | N18: =IF(J18="","",ABS(J18)) -> 2.75 | O18: =IF(K18="","",ABS(K18)) -> 1.2556433 | P18: =IF(B18>=Eval_Start_Week,"YES","") | Q18: =IF(AND(B18>=Cal_Start_Week,B18<=Cal_End_Week),"YES","")
A19: =Demand_History!C19 -> KIT-001 | B19: =Demand_History!A19 -> 18 | C19: =Demand_History!D19 -> 45 | D19: =IF(B19>=2,C18,"") -> 56 | E19: =IF(B19>=5,AVERAGE(C15:C18),"") -> 57.5 | F19: =IF(B19>=9,AVERAGE(C11:C18),"") -> 58.875 | G19: =IF(B19=1,"",IF(B19=2,C18,SES_Alpha*C18+(1-SES_Alpha)*G18)) -> 56.87895 | H19: =IF(D19="","",D19-C19) -> 11 | I19: =IF(E19="","",E19-C19) -> 12.5 | J19: =IF(F19="","",F19-C19) -> 13.875 | K19: =IF(G19="","",G19-C19) -> 11.87895 | L19: =IF(H19="","",ABS(H19)) -> 11 | M19: =IF(I19="","",ABS(I19)) -> 12.5 | N19: =IF(J19="","",ABS(J19)) -> 13.875 | O19: =IF(K19="","",ABS(K19)) -> 11.87895 | P19: =IF(B19>=Eval_Start_Week,"YES","") | Q19: =IF(AND(B19>=Cal_Start_Week,B19<=Cal_End_Week),"YES","")
A20: =Demand_History!C20 -> KIT-001 | B20: =Demand_History!A20 -> 19 | C20: =Demand_History!D20 -> 50 | D20: =IF(B20>=2,C19,"") -> 45 | E20: =IF(B20>=5,AVERAGE(C16:C19),"") -> 53.75 | F20: =IF(B20>=9,AVERAGE(C12:C19),"") -> 56.5 | G20: =IF(B20=1,"",IF(B20=2,C19,SES_Alpha*C19+(1-SES_Alpha)*G19)) -> 53.315265 | H20: =IF(D20="","",D20-C20) -> -5 | I20: =IF(E20="","",E20-C20) -> 3.75 | J20: =IF(F20="","",F20-C20) -> 6.5 | K20: =IF(G20="","",G20-C20) -> 3.3152652 | L20: =IF(H20="","",ABS(H20)) -> 5 | M20: =IF(I20="","",ABS(I20)) -> 3.75 | N20: =IF(J20="","",ABS(J20)) -> 6.5 | O20: =IF(K20="","",ABS(K20)) -> 3.3152652 | P20: =IF(B20>=Eval_Start_Week,"YES","") | Q20: =IF(AND(B20>=Cal_Start_Week,B20<=Cal_End_Week),"YES","")
A21: =Demand_History!C21 -> KIT-001 | B21: =Demand_History!A21 -> 20 | C21: =Demand_History!D21 -> 45 | D21: =IF(B21>=2,C20,"") -> 50 | E21: =IF(B21>=5,AVERAGE(C17:C20),"") -> 50 | F21: =IF(B21>=9,AVERAGE(C13:C20),"") -> 54.875 | G21: =IF(B21=1,"",IF(B21=2,C20,SES_Alpha*C20+(1-SES_Alpha)*G20)) -> 52.320686 | H21: =IF(D21="","",D21-C21) -> 5 | I21: =IF(E21="","",E21-C21) -> 5 | J21: =IF(F21="","",F21-C21) -> 9.875 | K21: =IF(G21="","",G21-C21) -> 7.3206857 | L21: =IF(H21="","",ABS(H21)) -> 5 | M21: =IF(I21="","",ABS(I21)) -> 5 | N21: =IF(J21="","",ABS(J21)) -> 9.875 | O21: =IF(K21="","",ABS(K21)) -> 7.3206857 | P21: =IF(B21>=Eval_Start_Week,"YES","") | Q21: =IF(AND(B21>=Cal_Start_Week,B21<=Cal_End_Week),"YES","")
... A4993: =Demand_History!C4993 -> CLN-011 | B4993: =Demand_History!A4993 -> 104 | C4993: =Demand_History!D4993 -> 45 | D4993: =IF(B4993>=2,C4992,"") -> 42 | E4993: =IF(B4993>=5,AVERAGE(C4989:C4992),"") -> 41.75 | F4993: =IF(B4993>=9,AVERAGE(C4985:C4992),"") -> 41.75 | G4993: =IF(B4993=1,"",IF(B4993=2,C4992,SES_Alpha*C4992+(1-SES_Alpha)*G4992)) -> 41.453165 | H4993: =IF(D4993="","",D4993-C4993) -> -3 | I4993: =IF(E4993="","",E4993-C4993) -> -3.25 | J4993: =IF(F4993="","",F4993-C4993) -> -3.25 | K4993: =IF(G4993="","",G4993-C4993) -> -3.5468345 | L4993: =IF(H4993="","",ABS(H4993)) -> 3 | M4993: =IF(I4993="","",ABS(I4993)) -> 3.25 | N4993: =IF(J4993="","",ABS(J4993)) -> 3.25 | O4993: =IF(K4993="","",ABS(K4993)) -> 3.5468345 | P4993: =IF(B4993>=Eval_Start_Week,"YES","") -> YES | Q4993: =IF(AND(B4993>=Cal_Start_Week,B4993<=Cal_End_Week),"YES","")

Sheet Replenishment_Plan
A1: Replenishment Plan: when to order (ROP) and approximately how much (EOQ)
A2: Which products need attention, when should we reorder them, and approximately how much should we order?
A3: Decision rule: Inventory Position > Reorder Point -> Recommended Order = 0. Inventory Position <= Reorder Point -> Recommended Order = EOQ rounded up to the case pack.
A5: PRODUCT | D5: FORECAST | I5: SAFETY STOCK AND REORDER POINT (WHEN) | O5: INVENTORY POSITION | U5: EOQ (HOW MUCH) | AC5: DECISION AND STATUS
A6: SKU | B6: Product | C6: Supplier | D6: Forecast Method | E6: Weekly Forecast (units) | F6: WAPE | G6: Bias | H6: Forecast Error SD (units) | I6: Target Service Level | J6: z-value | K6: Lead Time (weeks) | L6: Safety Stock (units) | M6: Lead-Time Demand (units) | N6: Reorder Point (units) | O6: On Hand | P6: On Order | Q6: Backorders | R6: Inventory Position | S6: Weeks of Cover (Inv. Position) | T6: Weeks of Cover (On Hand) | U6: Annual Forecast Demand (units) | V6: Unit Cost (€) | W6: Ordering Cost per Order (€) | X6: Annual Holding Rate | Y6: Annual Holding Cost per Unit (€) | Z6: EOQ (units, calculated) | AA6: Case Pack | AB6: EOQ Rounded to Case Pack | AC6: Reorder Trigger (IP <= ROP?) | AD6: Recommended Order (units) | AE6: First Projected Zero Week | AF6: Zero Within Lead Time? | AG6: Status | AH6: Reason (plain English) | AI6: On-Hand Inventory Value (€) | AJ6: Attention Sort Key | AK6: Attention Rank
A7: =Forecast!A7 -> KIT-001 | B7: =Forecast!B7 -> Chef's Knife 20cm | C7: =Inputs!E40 -> SUP-01 | D7: =Forecast!AE7 -> MA4 | E7: =Forecast!AF7 -> 61.25 | F7: =Forecast!AG7 -> 0.10647552 | G7: =Forecast!AH7 -> -0.0012886598 | H7: =Forecast!AI7 -> 8.0702398 | I7: =TSL -> 0.95 | J7: =Z_Value -> 1.6448536 | K7: =Inputs!F40 -> 2 | L7: =J7*H7*SQRT(K7) -> 18.772785 | M7: =E7*K7 -> 122.5 | N7: =M7+L7 -> 141.27278 | O7: =Inputs!J40 -> 236 | P7: =Inputs!K40 -> 0 | Q7: =Inputs!M40 -> 0 | R7: =O7+P7-Q7 -> 236 | S7: =IF(E7>0,R7/E7,0) -> 3.8530612 | T7: =IF(E7>0,O7/E7,0) -> 3.8530612 | U7: =E7*Weeks_Per_Year -> 3185 | V7: =Inputs!H40 -> 18 | W7: =Inputs!G40 -> 40 | X7: =Holding_Rate -> 0.2 | Y7: =V7*X7 -> 3.6 | Z7: =SQRT((2*U7*W7)/Y7) -> 266.04093 | AA7: =Inputs!I40 -> 6 | AB7: =ROUNDUP(Z7/AA7,0)*AA7 -> 270 | AC7: =IF(R7<=N7,"YES","NO") -> NO | AD7: =IF(AC7="YES",AB7,0) -> 0 | AE7: =Projection!BQ7 -> 4 | AF7: =Projection!BR7 -> NO | AG7: =IF(AF7="YES","STOCKOUT RISK",IF(AC7="YES","REORDER REQUIRED",IF(S7>Excess_WoC,"EXCESS STOCK","HEALTHY"))) -> HEALTHY | AH7: =IF(AG7="STOCKOUT RISK","Projected inventory reaches zero in week "&AE7&", before a new order placed now could arrive (week "&(K7+1)&"). "&IF(AC7="YES","Inventory position of "&FIXED(R7,0)&" units is at or below the reorder point of "&FIXED(N7,0)&", so an order of "&FIXED(AD7,0)&" units is recommended (EOQ "&FIXED(Z7,0)&", case pack "&AA7&"), but it cannot arrive in time: expedite supply or manage the shortfall.","No new order is triggered because inventory position of "&FIXED(R7,0)&" units is above the reorder point of "&FIXED(N7,0)&", but the open PO of "&FIXED(P7,0)&" units is due in week "&Inputs!L40&", which is too late: expedite the open PO."),IF(AG7="REORDER REQUIRED","Inventory position of "&FIXED(R7,0)&" units is "&FIXED(N7-R7,0)&" units below the reorder point of "&FIXED(N7,0)&" units. Replenishment is required. EOQ recommends approximately "&FIXED(Z7,0)&" units, rounded to "&FIXED(AD7,0)&" (case pack "&AA7&").",IF(AG7="EXCESS STOCK","Inventory position represents "&FIXED(S7,1)&" weeks of expected demand, above the "&Excess_WoC&"-week excess-stock threshold. No replenishment is triggered.","Inventory position of "&FIXED(R7,0)&" units is above the reorder point of "&FIXED(N7,0)&" units and covers "&FIXED(S7,1)&" weeks of forecast demand. No order needed now."))) -> Inventory position of 236 units is above the reorder point of 141 units and covers 3.9 weeks of forecast demand. No order needed now. | AI7: =O7*V7 -> 4248 | AJ7: =IF(AG7="STOCKOUT RISK",1000,IF(AG7="REORDER REQUIRED",2000,IF(AG7="EXCESS STOCK",3000,4000)))+IF(AG7="EXCESS STOCK",500-MIN(S7,499),MAX(MIN(S7,499),-499)) -> 4003.8531 | AK7: =SUMPRODUCT(--($AJ$7:$AJ$54<AJ7))+SUMPRODUCT(--($AJ$7:AJ7=AJ7)) -> 30
A8: =Forecast!A8 -> KIT-002 | B8: =Forecast!B8 -> Non-Stick Frying Pan 28cm | C8: =Inputs!E41 -> SUP-01 | D8: =Forecast!AE8 -> MA4 | E8: =Forecast!AF8 -> 33.5 | F8: =Forecast!AG8 -> 0.27276542 | G8: =Forecast!AH8 -> -0.0035669324 | H8: =Forecast!AI8 -> 16.126331 | I8: =TSL -> 0.95 | J8: =Z_Value -> 1.6448536 | K8: =Inputs!F41 -> 2 | L8: =J8*H8*SQRT(K8) -> 37.512656 | M8: =E8*K8 -> 67 | N8: =M8+L8 -> 104.51266 | O8: =Inputs!J41 -> 6 | P8: =Inputs!K41 -> 92 | Q8: =Inputs!M41 -> 0 | R8: =O8+P8-Q8 -> 98 | S8: =IF(E8>0,R8/E8,0) -> 2.9253731 | T8: =IF(E8>0,O8/E8,0) -> 0.17910448 | U8: =E8*Weeks_Per_Year -> 1742 | V8: =Inputs!H41 -> 22 | W8: =Inputs!G41 -> 40 | X8: =Holding_Rate -> 0.2 | Y8: =V8*X8 -> 4.4 | Z8: =SQRT((2*U8*W8)/Y8) -> 177.96833 | AA8: =Inputs!I41 -> 4 | AB8: =ROUNDUP(Z8/AA8,0)*AA8 -> 180 | AC8: =IF(R8<=N8,"YES","NO") -> YES | AD8: =IF(AC8="YES",AB8,0) -> 180 | AE8: =Projection!BQ8 -> 9 | AF8: =Projection!BR8 -> NO | AG8: =IF(AF8="YES","STOCKOUT RISK",IF(AC8="YES","REORDER REQUIRED",IF(S8>Excess_WoC,"EXCESS STOCK","HEALTHY"))) -> REORDER REQUIRED | AH8: =IF(AG8="STOCKOUT RISK","Projected inventory reaches zero in week "&AE8&", before a new order placed now could arrive (week "&(K8+1)&"). "&IF(AC8="YES","Inventory position of "&FIXED(R8,0)&" units is at or below the reorder point of "&FIXED(N8,0)&", so an order of "&FIXED(AD8,0)&" units is recommended (EOQ "&FIXED(Z8,0)&", case pack "&AA8&"), but it cannot arrive in time: expedite supply or manage the shortfall.","No new order is triggered because inventory position of "&FIXED(R8,0)&" units is above the reorder point of "&FIXED(N8,0)&", but the open PO of "&FIXED(P8,0)&" units is due in week "&Inputs!L41&", which is too late: expedite the open PO."),IF(AG8="REORDER REQUIRED","Inventory position of "&FIXED(R8,0)&" units is "&FIXED(N8-R8,0)&" units below the reorder point of "&FIXED(N8,0)&" units. Replenishment is required. EOQ recommends approximately "&FIXED(Z8,0)&" units, rounded to "&FIXED(AD8,0)&" (case pack "&AA8&").",IF(AG8="EXCESS STOCK","Inventory position represents "&FIXED(S8,1)&" weeks of expected demand, above the "&Excess_WoC&"-week excess-stock threshold. No replenishment is triggered.","Inventory position of "&FIXED(R8,0)&" units is above the reorder point of "&FIXED(N8,0)&" units and covers "&FIXED(S8,1)&" weeks of forecast demand. No order needed now."))) -> Inventory position of 98 units is 7 units below the reorder point of 105 units. Replenishment is required. EOQ recommends approximately 178 units, rounded to 180 (case pack 4). | AI8: =O8*V8 -> 132 | AJ8: =IF(AG8="STOCKOUT RISK",1000,IF(AG8="REORDER REQUIRED",2000,IF(AG8="EXCESS STOCK",3000,4000)))+IF(AG8="EXCESS STOCK",500-MIN(S8,499),MAX(MIN(S8,499),-499)) -> 2002.9254 | AK8: =SUMPRODUCT(--($AJ$7:$AJ$54<AJ8))+SUMPRODUCT(--($AJ$7:AJ8=AJ8)) -> 12
A9: =Forecast!A9 -> KIT-003 | B9: =Forecast!B9 -> Glass Food Storage Set 5pc | C9: =Inputs!E42 -> SUP-01 | D9: =Forecast!AE9 -> MA8 | E9: =Forecast!AF9 -> 95.125 | F9: =Forecast!AG9 -> 0.10336538 | G9: =Forecast!AH9 -> -0.022976297 | H9: =Forecast!AI9 -> 11.354526 | I9: =TSL -> 0.95 | J9: =Z_Value -> 1.6448536 | K9: =Inputs!F42 -> 2 | L9: =J9*H9*SQRT(K9) -> 26.412607 | M9: =E9*K9 -> 190.25 | N9: =M9+L9 -> 216.66261 | O9: =Inputs!J42 -> 0 | P9: =Inputs!K42 -> 0 | Q9: =Inputs!M42 -> 36 | R9: =O9+P9-Q9 -> -36 | S9: =IF(E9>0,R9/E9,0) -> -0.37844941 | T9: =IF(E9>0,O9/E9,0) -> 0 | U9: =E9*Weeks_Per_Year -> 4946.5 | V9: =Inputs!H42 -> 15 | W9: =Inputs!G42 -> 40 | X9: =Holding_Rate -> 0.2 | Y9: =V9*X9 -> 3 | Z9: =SQRT((2*U9*W9)/Y9) -> 363.18957 | AA9: =Inputs!I42 -> 6 | AB9: =ROUNDUP(Z9/AA9,0)*AA9 -> 366 | AC9: =IF(R9<=N9,"YES","NO") -> YES | AD9: =IF(AC9="YES",AB9,0) -> 366 | AE9: =Projection!BQ9 -> 1 | AF9: =Projection!BR9 -> YES | AG9: =IF(AF9="YES","STOCKOUT RISK",IF(AC9="YES","REORDER REQUIRED",IF(S9>Excess_WoC,"EXCESS STOCK","HEALTHY"))) -> STOCKOUT RISK | AH9: =IF(AG9="STOCKOUT RISK","Projected inventory reaches zero in week "&AE9&", before a new order placed now could arrive (week "&(K9+1)&"). "&IF(AC9="YES","Inventory position of "&FIXED(R9,0)&" units is at or below the reorder point of "&FIXED(N9,0)&", so an order of "&FIXED(AD9,0)&" units is recommended (EOQ "&FIXED(Z9,0)&", case pack "&AA9&"), but it cannot arrive in time: expedite supply or manage the shortfall.","No new order is triggered because inventory position of "&FIXED(R9,0)&" units is above the reorder point of "&FIXED(N9,0)&", but the open PO of "&FIXED(P9,0)&" units is due in week "&Inputs!L42&", which is too late: expedite the open PO."),IF(AG9="REORDER REQUIRED","Inventory position of "&FIXED(R9,0)&" units is "&FIXED(N9-R9,0)&" units below the reorder point of "&FIXED(N9,0)&" units. Replenishment is required. EOQ recommends approximately "&FIXED(Z9,0)&" units, rounded to "&FIXED(AD9,0)&" (case pack "&AA9&").",IF(AG9="EXCESS STOCK","Inventory position represents "&FIXED(S9,1)&" weeks of expected demand, above the "&Excess_WoC&"-week excess-stock threshold. No replenishment is triggered.","Inventory position of "&FIXED(R9,0)&" units is above the reorder point of "&FIXED(N9,0)&" units and covers "&FIXED(S9,1)&" weeks of forecast demand. No order needed now."))) -> Projected inventory reaches zero in week 1, before a new order placed now could arrive (week 3). Inventory position of -36 units is at or below the reorder point of 217, so an order of 366 units is recommended (EOQ 363, case pack 6), but it cannot arrive in time: expedite supply or manage the shortfall. | AI9: =O9*V9 -> 0 | AJ9: =IF(AG9="STOCKOUT RISK",1000,IF(AG9="REORDER REQUIRED",2000,IF(AG9="EXCESS STOCK",3000,4000)))+IF(AG9="EXCESS STOCK",500-MIN(S9,499),MAX(MIN(S9,499),-499)) -> 999.62155 | AK9: =SUMPRODUCT(--($AJ$7:$AJ$54<AJ9))+SUMPRODUCT(--($AJ$7:AJ9=AJ9)) -> 3
A10: =Forecast!A10 -> KIT-004 | B10: =Forecast!B10 -> Bamboo Cutting Board | C10: =Inputs!E43 -> SUP-01 | D10: =Forecast!AE10 -> MA4 | E10: =Forecast!AF10 -> 96.5 | F10: =Forecast!AG10 -> 0.10689803 | G10: =Forecast!AH10 -> -0.0099614396 | H10: =Forecast!AI10 -> 11.467916 | I10: =TSL -> 0.95 | J10: =Z_Value -> 1.6448536 | K10: =Inputs!F43 -> 2 | L10: =J10*H10*SQRT(K10) -> 26.676372 | M10: =E10*K10 -> 193 | N10: =M10+L10 -> 219.67637 | O10: =Inputs!J43 -> 270 | P10: =Inputs!K43 -> 0 | Q10: =Inputs!M43 -> 0 | R10: =O10+P10-Q10 -> 270 | S10: =IF(E10>0,R10/E10,0) -> 2.7979275 | T10: =IF(E10>0,O10/E10,0) -> 2.7979275 | U10: =E10*Weeks_Per_Year -> 5018 | V10: =Inputs!H43 -> 9 | W10: =Inputs!G43 -> 40 | X10: =Holding_Rate -> 0.2 | Y10: =V10*X10 -> 1.8 | Z10: =SQRT((2*U10*W10)/Y10) -> 472.25229 | AA10: =Inputs!I43 -> 12 | AB10: =ROUNDUP(Z10/AA10,0)*AA10 -> 480 | AC10: =IF(R10<=N10,"YES","NO") -> NO | AD10: =IF(AC10="YES",AB10,0) -> 0 | AE10: =Projection!BQ10 -> 3 | AF10: =Projection!BR10 -> NO | AG10: =IF(AF10="YES","STOCKOUT RISK",IF(AC10="YES","REORDER REQUIRED",IF(S10>Excess_WoC,"EXCESS STOCK","HEALTHY"))) -> HEALTHY | AH10: =IF(AG10="STOCKOUT RISK","Projected inventory reaches zero in week "&AE10&", before a new order placed now could arrive (week "&(K10+1)&"). "&IF(AC10="YES","Inventory position of "&FIXED(R10,0)&" units is at or below the reorder point of "&FIXED(N10,0)&", so an order of "&FIXED(AD10,0)&" units is recommended (EOQ "&FIXED(Z10,0)&", case pack "&AA10&"), but it cannot arrive in time: expedite supply or manage the shortfall.","No new order is triggered because inventory position of "&FIXED(R10,0)&" units is above the reorder point of "&FIXED(N10,0)&", but the open PO of "&FIXED(P10,0)&" units is due in week "&Inputs!L43&", which is too late: expedite the open PO."),IF(AG10="REORDER REQUIRED","Inventory position of "&FIXED(R10,0)&" units is "&FIXED(N10-R10,0)&" units below the reorder point of "&FIXED(N10,0)&" units. Replenishment is required. EOQ recommends approximately "&FIXED(Z10,0)&" units, rounded to "&FIXED(AD10,0)&" (case pack "&AA10&").",IF(AG10="EXCESS STOCK","Inventory position represents "&FIXED(S10,1)&" weeks of expected demand, above the "&Excess_WoC&"-week excess-stock threshold. No replenishment is triggered.","Inventory position of "&FIXED(R10,0)&" units is above the reorder point of "&FIXED(N10,0)&" units and covers "&FIXED(S10,1)&" weeks of forecast demand. No order needed now."))) -> Inventory position of 270 units is above the reorder point of 220 units and covers 2.8 weeks of forecast demand. No order needed now. | AI10: =O10*V10 -> 2430 | AJ10: =IF(AG10="STOCKOUT RISK",1000,IF(AG10="REORDER REQUIRED",2000,IF(AG10="EXCESS STOCK",3000,4000)))+IF(AG10="EXCESS STOCK",500-MIN(S10,499),MAX(MIN(S10,499),-499)) -> 4002.7979 | AK10: =SUMPRODUCT(--($AJ$7:$AJ$54<AJ10))+SUMPRODUCT(--($AJ$7:AJ10=AJ10)) -> 27
A11: =Forecast!A11 -> KIT-005 | B11: =Forecast!B11 -> Stainless Saucepan 2L | C11: =Inputs!E44 -> SUP-01 | D11: =Forecast!AE11 -> MA8 | E11: =Forecast!AF11 -> 23.875 | F11: =Forecast!AG11 -> 0.13861901 | G11: =Forecast!AH11 -> 0.031575295 | H11: =Forecast!AI11 -> 4.6755649 | I11: =TSL -> 0.95 | J11: =Z_Value -> 1.6448536 | K11: =Inputs!F44 -> 2 | L11: =J11*H11*SQRT(K11) -> 10.876179 | M11: =E11*K11 -> 47.75 | N11: =M11+L11 -> 58.626179 | O11: =Inputs!J44 -> 334 | P11: =Inputs!K44 -> 0 | Q11: =Inputs!M44 -> 0 | R11: =O11+P11-Q11 -> 334 | S11: =IF(E11>0,R11/E11,0) -> 13.989529 | T11: =IF(E11>0,O11/E11,0) -> 13.989529 | U11: =E11*Weeks_Per_Year -> 1241.5 | V11: =Inputs!H44 -> 28 | W11: =Inputs!G44 -> 40 | X11: =Holding_Rate -> 0.2 | Y11: =V11*X11 -> 5.6 | Z11: =SQRT((2*U11*W11)/Y11) -> 133.1755 | AA11: =Inputs!I44 -> 4 | AB11: =ROUNDUP(Z11/AA11,0)*AA11 -> 136 | AC11: =IF(R11<=N11,"YES","NO") -> NO | AD11: =IF(AC11="YES",AB11,0) -> 0 | AE11: =Projection!BQ11 -> None | AF11: =Projection!BR11 -> NO | AG11: =IF(AF11="YES","STOCKOUT RISK",IF(AC11="YES","REORDER REQUIRED",IF(S11>Excess_WoC,"EXCESS STOCK","HEALTHY"))) -> EXCESS STOCK | AH11: =IF(AG11="STOCKOUT RISK","Projected inventory reaches zero in week "&AE11&", before a new order placed now could arrive (week "&(K11+1)&"). "&IF(AC11="YES","Inventory position of "&FIXED(R11,0)&" units is at or below the reorder point of "&FIXED(N11,0)&", so an order of "&FIXED(AD11,0)&" units is recommended (EOQ "&FIXED(Z11,0)&", case pack "&AA11&"), but it cannot arrive in time: expedite supply or manage the shortfall.","No new order is triggered because inventory position of "&FIXED(R11,0)&" units is above the reorder point of "&FIXED(N11,0)&", but the open PO of "&FIXED(P11,0)&" units is due in week "&Inputs!L44&", which is too late: expedite the open PO."),IF(AG11="REORDER REQUIRED","Inventory position of "&FIXED(R11,0)&" units is "&FIXED(N11-R11,0)&" units below the reorder point of "&FIXED(N11,0)&" units. Replenishment is required. EOQ recommends approximately "&FIXED(Z11,0)&" units, rounded to "&FIXED(AD11,0)&" (case pack "&AA11&").",IF(AG11="EXCESS STOCK","Inventory position represents "&FIXED(S11,1)&" weeks of expected demand, above the "&Excess_WoC&"-week excess-stock threshold. No replenishment is triggered.","Inventory position of "&FIXED(R11,0)&" units is above the reorder point of "&FIXED(N11,0)&" units and covers "&FIXED(S11,1)&" weeks of forecast demand. No order needed now."))) -> Inventory position represents 14.0 weeks of expected demand, above the 12-week excess-stock threshold. No replenishment is triggered. | AI11: =O11*V11 -> 9352 | AJ11: =IF(AG11="STOCKOUT RISK",1000,IF(AG11="REORDER REQUIRED",2000,IF(AG11="EXCESS STOCK",3000,4000)))+IF(AG11="EXCESS STOCK",500-MIN(S11,499),MAX(MIN(S11,499),-499)) -> 3486.0105 | AK11: =SUMPRODUCT(--($AJ$7:$AJ$54<AJ11))+SUMPRODUCT(--($AJ$7:AJ11=AJ11)) -> 25
A12: =Forecast!A12 -> KIT-006 | B12: =Forecast!B12 -> Silicone Utensil Set | C12: =Inputs!E45 -> SUP-01 | D12: =Forecast!AE12 -> MA8 | E12: =Forecast!AF12 -> 66.625 | F12: =Forecast!AG12 -> 0.27079038 | G12: =Forecast!AH12 -> -0.041237113 | H12: =Forecast!AI12 -> 19.838 | I12: =TSL -> 0.95 | J12: =Z_Value -> 1.6448536 | K12: =Inputs!F45 -> 2 | L12: =J12*H12*SQRT(K12) -> 46.146646 | M12: =E12*K12 -> 133.25 | N12: =M12+L12 -> 179.39665 | O12: =Inputs!J45 -> 378 | P12: =Inputs!K45 -> 0 | Q12: =Inputs!M45 -> 0 | R12: =O12+P12-Q12 -> 378 | S12: =IF(E12>0,R12/E12,0) -> 5.673546 | T12: =IF(E12>0,O12/E12,0) -> 5.673546 | U12: =E12*Weeks_Per_Year -> 3464.5 | V12: =Inputs!H45 -> 12 | W12: =Inputs!G45 -> 40 | X12: =Holding_Rate -> 0.2 | Y12: =V12*X12 -> 2.4 | Z12: =SQRT((2*U12*W12)/Y12) -> 339.82839 | AA12: =Inputs!I45 -> 10 | AB12: =ROUNDUP(Z12/AA12,0)*AA12 -> 340 | AC12: =IF(R12<=N12,"YES","NO") -> NO | AD12: =IF(AC12="YES",AB12,0) -> 0 | AE12: =Projection!BQ12 -> 6 | AF12: =Projection!BR12 -> NO | AG12: =IF(AF12="YES","STOCKOUT RISK",IF(AC12="YES","REORDER REQUIRED",IF(S12>Excess_WoC,"EXCESS STOCK","HEALTHY"))) -> HEALTHY | AH12: =IF(AG12="STOCKOUT RISK","Projected inventory reaches zero in week "&AE12&", before a new order placed now could arrive (week "&(K12+1)&"). "&IF(AC12="YES","Inventory position of "&FIXED(R12,0)&" units is at or below the reorder point of "&FIXED(N12,0)&", so an order of "&FIXED(AD12,0)&" units is recommended (EOQ "&FIXED(Z12,0)&", case pack "&AA12&"), but it cannot arrive in time: expedite supply or manage the shortfall.","No new order is triggered because inventory position of "&FIXED(R12,0)&" units is above the reorder point of "&FIXED(N12,0)&", but the open PO of "&FIXED(P12,0)&" units is due in week "&Inputs!L45&", which is too late: expedite the open PO."),IF(AG12="REORDER REQUIRED","Inventory position of "&FIXED(R12,0)&" units is "&FIXED(N12-R12,0)&" units below the reorder point of "&FIXED(N12,0)&" units. Replenishment is required. EOQ recommends approximately "&FIXED(Z12,0)&" units, rounded to "&FIXED(AD12,0)&" (case pack "&AA12&").",IF(AG12="EXCESS STOCK","Inventory position represents "&FIXED(S12,1)&" weeks of expected demand, above the "&Excess_WoC&"-week excess-stock threshold. No replenishment is triggered.","Inventory position of "&FIXED(R12,0)&" units is above the reorder point of "&FIXED(N12,0)&" units and covers "&FIXED(S12,1)&" weeks of forecast demand. No order needed now."))) -> Inventory position of 378 units is above the reorder point of 179 units and covers 5.7 weeks of forecast demand. No order needed now. | AI12: =O12*V12 -> 4536 | AJ12: =IF(AG12="STOCKOUT RISK",1000,IF(AG12="REORDER REQUIRED",2000,IF(AG12="EXCESS STOCK",3000,4000)))+IF(AG12="EXCESS STOCK",500-MIN(S12,499),MAX(MIN(S12,499),-499)) -> 4005.6735 | AK12: =SUMPRODUCT(--($AJ$7:$AJ$54<AJ12))+SUMPRODUCT(--($AJ$7:AJ12=AJ12)) -> 35
A13: =Forecast!A13 -> KIT-007 | B13: =Forecast!B13 -> Cast Iron Casserole 5L | C13: =Inputs!E46 -> SUP-01 | D13: =Forecast!AE13 -> MA8 | E13: =Forecast!AF13 -> 8.875 | F13: =Forecast!AG13 -> 0.29371762 | G13: =Forecast!AH13 -> -0.028173575 | H13: =Forecast!AI13 -> 2.8252539 | I13: =TSL -> 0.95 | J13: =Z_Value -> 1.6448536 | K13: =Inputs!F46 -> 2 | L13: =J13*H13*SQRT(K13) -> 6.572033 | M13: =E13*K13 -> 17.75 | N13: =M13+L13 -> 24.322033 | O13: =Inputs!J46 -> 21 | P13: =Inputs!K46 -> 0 | Q13: =Inputs!M46 -> 0 | R13: =O13+P13-Q13 -> 21 | S13: =IF(E13>0,R13/E13,0) -> 2.3661972 | T13: =IF(E13>0,O13/E13,0) -> 2.3661972 | U13: =E13*Weeks_Per_Year -> 461.5 | V13: =Inputs!H46 -> 85 | W13: =Inputs!G46 -> 40 | X13: =Holding_Rate -> 0.2 | Y13: =V13*X13 -> 17 | Z13: =SQRT((2*U13*W13)/Y13) -> 46.602196 | AA13: =Inputs!I46 -> 1 | AB13: =ROUNDUP(Z13/AA13,0)*AA13 -> 47 | AC13: =IF(R13<=N13,"YES","NO") -> YES | AD13: =IF(AC13="YES",AB13,0) -> 47 | AE13: =Projection!BQ13 -> 8 | AF13: =Projection!BR13 -> NO | AG13: =IF(AF13="YES","STOCKOUT RISK",IF(AC13="YES","REORDER REQUIRED",IF(S13>Excess_WoC,"EXCESS STOCK","HEALTHY"))) -> REORDER REQUIRED | AH13: =IF(AG13="STOCKOUT RISK","Projected inventory reaches zero in week "&AE13&", before a new order placed now could arrive (week "&(K13+1)&"). "&IF(AC13="YES","Inventory position of "&FIXED(R13,0)&" units is at or below the reorder point of "&FIXED(N13,0)&", so an order of "&FIXED(AD13,0)&" units is recommended (EOQ "&FIXED(Z13,0)&", case pack "&AA13&"), but it cannot arrive in time: expedite supply or manage the shortfall.","No new order is triggered because inventory position of "&FIXED(R13,0)&" units is above the reorder point of "&FIXED(N13,0)&", but the open PO of "&FIXED(P13,0)&" units is due in week "&Inputs!L46&", which is too late: expedite the open PO."),IF(AG13="REORDER REQUIRED","Inventory position of "&FIXED(R13,0)&" units is "&FIXED(N13-R13,0)&" units below the reorder point of "&FIXED(N13,0)&" units. Replenishment is required. EOQ recommends approximately "&FIXED(Z13,0)&" units, rounded to "&FIXED(AD13,0)&" (case pack "&AA13&").",IF(AG13="EXCESS STOCK","Inventory position represents "&FIXED(S13,1)&" weeks of expected demand, above the "&Excess_WoC&"-week excess-stock threshold. No replenishment is triggered.","Inventory position of "&FIXED(R13,0)&" units is above the reorder point of "&FIXED(N13,0)&" units and covers "&FIXED(S13,1)&" weeks of forecast demand. No order needed now."))) -> Inventory position of 21 units is 3 units below the reorder point of 24 units. Replenishment is required. EOQ recommends approximately 47 units, rounded to 47 (case pack 1). | AI13: =O13*V13 -> 1785 | AJ13: =IF(AG13="STOCKOUT RISK",1000,IF(AG13="REORDER REQUIRED",2000,IF(AG13="EXCESS STOCK",3000,4000)))+IF(AG13="EXCESS STOCK",500-MIN(S13,499),MAX(MIN(S13,499),-499)) -> 2002.3662 | AK13: =SUMPRODUCT(--($AJ$7:$AJ$54<AJ13))+SUMPRODUCT(--($AJ$7:AJ13=AJ13)) -> 11
A14: =Forecast!A14 -> KIT-008 | B14: =Forecast!B14 -> Espresso Cup Set 6pc | C14: =Inputs!E47 -> SUP-01 | D14: =Forecast!AE14 -> MA4 | E14: =Forecast!AF14 -> 41.5 | F14: =Forecast!AG14 -> 0.087411765 | G14: =Forecast!AH14 -> -0.00011764706 | H14: =Forecast!AI14 -> 4.6122945 | I14: =TSL -> 0.95 | J14: =Z_Value -> 1.6448536 | K14: =Inputs!F47 -> 2 | L14: =J14*H14*SQRT(K14) -> 10.729001 | M14: =E14*K14 -> 83 | N14: =M14+L14 -> 93.729001 | O14: =Inputs!J47 -> 766 | P14: =Inputs!K47 -> 0 | Q14: =Inputs!M47 -> 0 | R14: =O14+P14-Q14 -> 766 | S14: =IF(E14>0,R14/E14,0) -> 18.457831 | T14: =IF(E14>0,O14/E14,0) -> 18.457831 | U14: =E14*Weeks_Per_Year -> 2158 | V14: =Inputs!H47 -> 19 | W14: =Inputs!G47 -> 40 | X14: =Holding_Rate -> 0.2 | Y14: =V14*X14 -> 3.8 | Z14: =SQRT((2*U14*W14)/Y14) -> 213.14685 | AA14: =Inputs!I47 -> 6 | AB14: =ROUNDUP(Z14/AA14,0)*AA14 -> 216 | AC14: =IF(R14<=N14,"YES","NO") -> NO | AD14: =IF(AC14="YES",AB14,0) -> 0 | AE14: =Projection!BQ14 -> None | AF14: =Projection!BR14 -> NO | AG14: =IF(AF14="YES","STOCKOUT RISK",IF(AC14="YES","REORDER REQUIRED",IF(S14>Excess_WoC,"EXCESS STOCK","HEALTHY"))) -> EXCESS STOCK | AH14: =IF(AG14="STOCKOUT RISK","Projected inventory reaches zero in week "&AE14&", before a new order placed now could arrive (week "&(K14+1)&"). "&IF(AC14="YES","Inventory position of "&FIXED(R14,0)&" units is at or below the reorder point of "&FIXED(N14,0)&", so an order of "&FIXED(AD14,0)&" units is recommended (EOQ "&FIXED(Z14,0)&", case pack "&AA14&"), but it cannot arrive in time: expedite supply or manage the shortfall.","No new order is triggered because inventory position of "&FIXED(R14,0)&" units is above the reorder point of "&FIXED(N14,0)&", but the open PO of "&FIXED(P14,0)&" units is due in week "&Inputs!L47&", which is too late: expedite the open PO."),IF(AG14="REORDER REQUIRED","Inventory position of "&FIXED(R14,0)&" units is "&FIXED(N14-R14,0)&" units below the reorder point of "&FIXED(N14,0)&" units. Replenishment is required. EOQ recommends approximately "&FIXED(Z14,0)&" units, rounded to "&FIXED(AD14,0)&" (case pack "&AA14&").",IF(AG14="EXCESS STOCK","Inventory position represents "&FIXED(S14,1)&" weeks of expected demand, above the "&Excess_WoC&"-week excess-stock threshold. No replenishment is triggered.","Inventory position of "&FIXED(R14,0)&" units is above the reorder point of "&FIXED(N14,0)&" units and covers "&FIXED(S14,1)&" weeks of forecast demand. No order needed now."))) -> Inventory position represents 18.5 weeks of expected demand, above the 12-week excess-stock threshold. No replenishment is triggered. | AI14: =O14*V14 -> 14554 | AJ14: =IF(AG14="STOCKOUT RISK",1000,IF(AG14="REORDER REQUIRED",2000,IF(AG14="EXCESS STOCK",3000,4000)))+IF(AG14="EXCESS STOCK",500-MIN(S14,499),MAX(MIN(S14,499),-499)) -> 3481.5422 | AK14: =SUMPRODUCT(--($AJ$7:$AJ$54<AJ14))+SUMPRODUCT(--($AJ$7:AJ14=AJ14)) -> 22
A15: =Forecast!A15 -> KIT-009 | B15: =Forecast!B15 -> Digital Kitchen Scale | C15: =Inputs!E48 -> SUP-01 | D15: =Forecast!AE15 -> MA4 | E15: =Forecast!AF15 -> 39.5 | F15: =Forecast!AG15 -> 0.10921409 | G15: =Forecast!AH15 -> -0.01598916 | H15: =Forecast!AI15 -> 4.8535199 | I15: =TSL -> 0.95 | J15: =Z_Value -> 1.6448536 | K15: =Inputs!F48 -> 2 | L15: =J15*H15*SQRT(K15) -> 11.290133 | M15: =E15*K15 -> 79 | N15: =M15+L15 -> 90.290133 | O15: =Inputs!J48 -> 80 | P15: =Inputs!K48 -> 0 | Q15: =Inputs!M48 -> 0 | R15: =O15+P15-Q15 -> 80 | S15: =IF(E15>0,R15/E15,0) -> 2.0253165 | T15: =IF(E15>0,O15/E15,0) -> 2.0253165 | U15: =E15*Weeks_Per_Year -> 2054 | V15: =Inputs!H48 -> 24 | W15: =Inputs!G48 -> 40 | X15: =Holding_Rate -> 0.2 | Y15: =V15*X15 -> 4.8 | Z15: =SQRT((2*U15*W15)/Y15) -> 185.02252 | AA15: =Inputs!I48 -> 5 | AB15: =ROUNDUP(Z15/AA15,0)*AA15 -> 190 | AC15: =IF(R15<=N15,"YES","NO") -> YES | AD15: =IF(AC15="YES",AB15,0) -> 190 | AE15: =Projection!BQ15 -> 7 | AF15: =Projection!BR15 -> NO | AG15: =IF(AF15="YES","STOCKOUT RISK",IF(AC15="YES","REORDER REQUIRED",IF(S15>Excess_WoC,"EXCESS STOCK","HEALTHY"))) -> REORDER REQUIRED | AH15: =IF(AG15="STOCKOUT RISK","Projected inventory reaches zero in week "&AE15&", before a new order placed now could arrive (week "&(K15+1)&"). "&IF(AC15="YES","Inventory position of "&FIXED(R15,0)&" units is at or below the reorder point of "&FIXED(N15,0)&", so an order of "&FIXED(AD15,0)&" units is recommended (EOQ "&FIXED(Z15,0)&", case pack "&AA15&"), but it cannot arrive in time: expedite supply or manage the shortfall.","No new order is triggered because inventory position of "&FIXED(R15,0)&" units is above the reorder point of "&FIXED(N15,0)&", but the open PO of "&FIXED(P15,0)&" units is due in week "&Inputs!L48&", which is too late: expedite the open PO."),IF(AG15="REORDER REQUIRED","Inventory position of "&FIXED(R15,0)&" units is "&FIXED(N15-R15,0)&" units below the reorder point of "&FIXED(N15,0)&" units. Replenishment is required. EOQ recommends approximately "&FIXED(Z15,0)&" units, rounded to "&FIXED(AD15,0)&" (case pack "&AA15&").",IF(AG15="EXCESS STOCK","Inventory position represents "&FIXED(S15,1)&" weeks of expected demand, above the "&Excess_WoC&"-week excess-stock threshold. No replenishment is triggered.","Inventory position of "&FIXED(R15,0)&" units is above the reorder point of "&FIXED(N15,0)&" units and covers "&FIXED(S15,1)&" weeks of forecast demand. No order needed now."))) -> Inventory position of 80 units is 10 units below the reorder point of 90 units. Replenishment is required. EOQ recommends approximately 185 units, rounded to 190 (case pack 5). | AI15: =O15*V15 -> 1920 | AJ15: =IF(AG15="STOCKOUT RISK",1000,IF(AG15="REORDER REQUIRED",2000,IF(AG15="EXCESS STOCK",3000,4000)))+IF(AG15="EXCESS STOCK",500-MIN(S15,499),MAX(MIN(S15,499),-499)) -> 2002.0253 | AK15: =SUMPRODUCT(--($AJ$7:$AJ$54<AJ15))+SUMPRODUCT(--($AJ$7:AJ15=AJ15)) -> 10
A16: =Forecast!A16 -> KIT-010 | B16: =Forecast!B16 -> Measuring Jug 1L | C16: =Inputs!E49 -> SUP-01 | D16: =Forecast!AE16 -> MA4 | E16: =Forecast!AF16 -> 101 | F16: =Forecast!AG16 -> 0.08956905 | G16: =Forecast!AH16 -> -0.0020078355 | H16: =Forecast!AI16 -> 10.37535 | I16: =TSL -> 0.95 | J16: =Z_Value -> 1.6448536 | K16: =Inputs!F49 -> 2 | L16: =J16*H16*SQRT(K16) -> 24.134872 | M16: =E16*K16 -> 202 | N16: =M16+L16 -> 226.13487 | O16: =Inputs!J49 -> 304 | P16: =Inputs!K49 -> 0 | Q16: =Inputs!M49 -> 0 | R16: =O16+P16-Q16 -> 304 | S16: =IF(E16>0,R16/E16,0) -> 3.009901 | T16: =IF(E16>0,O16/E16,0) -> 3.009901 | U16: =E16*Weeks_Per_Year -> 5252 | V16: =Inputs!H49 -> 6 | W16: =Inputs!G49 -> 40 | X16: =Holding_Rate -> 0.2 | Y16: =V16*X16 -> 1.2 | Z16: =SQRT((2*U16*W16)/Y16) -> 591.72065 | AA16: =Inputs!I49 -> 24 | AB16: =ROUNDUP(Z16/AA16,0)*AA16 -> 600 | AC16: =IF(R16<=N16,"YES","NO") -> NO | AD16: =IF(AC16="YES",AB16,0) -> 0 | AE16: =Projection!BQ16 -> 4 | AF16: =Projection!BR16 -> NO | AG16: =IF(AF16="YES","STOCKOUT RISK",IF(AC16="YES","REORDER REQUIRED",IF(S16>Excess_WoC,"EXCESS STOCK","HEALTHY"))) -> HEALTHY | AH16: =IF(AG16="STOCKOUT RISK","Projected inventory reaches zero in week "&AE16&", before a new order placed now could arrive (week "&(K16+1)&"). "&IF(AC16="YES","Inventory position of "&FIXED(R16,0)&" units is at or below the reorder point of "&FIXED(N16,0)&", so an order of "&FIXED(AD16,0)&" units is recommended (EOQ "&FIXED(Z16,0)&", case pack "&AA16&"), but it cannot arrive in time: expedite supply or manage the shortfall.","No new order is triggered because inventory position of "&FIXED(R16,0)&" units is above the reorder point of "&FIXED(N16,0)&", but the open PO of "&FIXED(P16,0)&" units is due in week "&Inputs!L49&", which is too late: expedite the open PO."),IF(AG16="REORDER REQUIRED","Inventory position of "&FIXED(R16,0)&" units is "&FIXED(N16-R16,0)&" units below the reorder point of "&FIXED(N16,0)&" units. Replenishment is required. EOQ recommends approximately "&FIXED(Z16,0)&" units, rounded to "&FIXED(AD16,0)&" (case pack "&AA16&").",IF(AG16="EXCESS STOCK","Inventory position represents "&FIXED(S16,1)&" weeks of expected demand, above the "&Excess_WoC&"-week excess-stock threshold. No replenishment is triggered.","Inventory position of "&FIXED(R16,0)&" units is above the reorder point of "&FIXED(N16,0)&" units and covers "&FIXED(S16,1)&" weeks of forecast demand. No order needed now."))) -> Inventory position of 304 units is above the reorder point of 226 units and covers 3.0 weeks of forecast demand. No order needed now. | AI16: =O16*V16 -> 1824 | AJ16: =IF(AG16="STOCKOUT RISK",1000,IF(AG16="REORDER REQUIRED",2000,IF(AG16="EXCESS STOCK",3000,4000)))+IF(AG16="EXCESS STOCK",500-MIN(S16,499),MAX(MIN(S16,499),-499)) -> 4003.0099 | AK16: =SUMPRODUCT(--($AJ$7:$AJ$54<AJ16))+SUMPRODUCT(--($AJ$7:AJ16=AJ16)) -> 28
A17: =Forecast!A17 -> BTH-001 | B17: =Forecast!B17 -> Bath Towel 70x140 Grey | C17: =Inputs!E50 -> SUP-02 | D17: =Forecast!AE17 -> MA4 | E17: =Forecast!AF17 -> 106 | F17: =Forecast!AG17 -> 0.13323747 | G17: =Forecast!AH17 -> 0.0022596549 | H17: =Forecast!AI17 -> 18.698158 | I17: =TSL -> 0.95 | J17: =Z_Value -> 1.6448536 | K17: =Inputs!F50 -> 3 | L17: =J17*H17*SQRT(K17) -> 53.270492 | M17: =E17*K17 -> 318 | N17: =M17+L17 -> 371.27049 | O17: =Inputs!J50 -> 486 | P17: =Inputs!K50 -> 0 | Q17: =Inputs!M50 -> 0 | R17: =O17+P17-Q17 -> 486 | S17: =IF(E17>0,R17/E17,0) -> 4.5849057 | T17: =IF(E17>0,O17/E17,0) -> 4.5849057 | U17: =E17*Weeks_Per_Year -> 5512 | V17: =Inputs!H50 -> 11 | W17: =Inputs!G50 -> 45 | X17: =Holding_Rate -> 0.2 | Y17: =V17*X17 -> 2.2 | Z17: =SQRT((2*U17*W17)/Y17) -> 474.85883 | AA17: =Inputs!I50 -> 10 | AB17: =ROUNDUP(Z17/AA17,0)*AA17 -> 480 | AC17: =IF(R17<=N17,"YES","NO") -> NO | AD17: =IF(AC17="YES",AB17,0) -> 0 | AE17: =Projection!BQ17 -> 5 | AF17: =Projection!BR17 -> NO | AG17: =IF(AF17="YES","STOCKOUT RISK",IF(AC17="YES","REORDER REQUIRED",IF(S17>Excess_WoC,"EXCESS STOCK","HEALTHY"))) -> HEALTHY | AH17: =IF(AG17="STOCKOUT RISK","Projected inventory reaches zero in week "&AE17&", before a new order placed now could arrive (week "&(K17+1)&"). "&IF(AC17="YES","Inventory position of "&FIXED(R17,0)&" units is at or below the reorder point of "&FIXED(N17,0)&", so an order of "&FIXED(AD17,0)&" units is recommended (EOQ "&FIXED(Z17,0)&", case pack "&AA17&"), but it cannot arrive in time: expedite supply or manage the shortfall.","No new order is triggered because inventory position of "&FIXED(R17,0)&" units is above the reorder point of "&FIXED(N17,0)&", but the open PO of "&FIXED(P17,0)&" units is due in week "&Inputs!L50&", which is too late: expedite the open PO."),IF(AG17="REORDER REQUIRED","Inventory position of "&FIXED(R17,0)&" units is "&FIXED(N17-R17,0)&" units below the reorder point of "&FIXED(N17,0)&" units. Replenishment is required. EOQ recommends approximately "&FIXED(Z17,0)&" units, rounded to "&FIXED(AD17,0)&" (case pack "&AA17&").",IF(AG17="EXCESS STOCK","Inventory position represents "&FIXED(S17,1)&" weeks of expected demand, above the "&Excess_WoC&"-week excess-stock threshold. No replenishment is triggered.","Inventory position of "&FIXED(R17,0)&" units is above the reorder point of "&FIXED(N17,0)&" units and covers "&FIXED(S17,1)&" weeks of forecast demand. No order needed now."))) -> Inventory position of 486 units is above the reorder point of 371 units and covers 4.6 weeks of forecast demand. No order needed now. | AI17: =O17*V17 -> 5346 | AJ17: =IF(AG17="STOCKOUT RISK",1000,IF(AG17="REORDER REQUIRED",2000,IF(AG17="EXCESS STOCK",3000,4000)))+IF(AG17="EXCESS STOCK",500-MIN(S17,499),MAX(MIN(S17,499),-499)) -> 4004.5849 | AK17: =SUMPRODUCT(--($AJ$7:$AJ$54<AJ17))+SUMPRODUCT(--($AJ$7:AJ17=AJ17)) -> 34
A18: =Forecast!A18 -> BTH-002 | B18: =Forecast!B18 -> Hand Towel 50x100 White | C18: =Inputs!E51 -> SUP-02 | D18: =Forecast!AE18 -> MA4 | E18: =Forecast!AF18 -> 146.25 | F18: =Forecast!AG18 -> 0.070915904 | G18: =Forecast!AH18 -> 0.00390625 | H18: =Forecast!AI18 -> 14.063496 | I18: =TSL -> 0.95 | J18: =Z_Value -> 1.6448536 | K18: =Inputs!F51 -> 3 | L18: =J18*H18*SQRT(K18) -> 40.06648 | M18: =E18*K18 -> 438.75 | N18: =M18+L18 -> 478.81648 | O18: =Inputs!J51 -> 75 | P18: =Inputs!K51 -> 380 | Q18: =Inputs!M51 -> 0 | R18: =O18+P18-Q18 -> 455 | S18: =IF(E18>0,R18/E18,0) -> 3.1111111 | T18: =IF(E18>0,O18/E18,0) -> 0.51282051 | U18: =E18*Weeks_Per_Year -> 7605 | V18: =Inputs!H51 -> 6 | W18: =Inputs!G51 -> 45 | X18: =Holding_Rate -> 0.2 | Y18: =V18*X18 -> 1.2 | Z18: =SQRT((2*U18*W18)/Y18) -> 755.23175 | AA18: =Inputs!I51 -> 20 | AB18: =ROUNDUP(Z18/AA18,0)*AA18 -> 760 | AC18: =IF(R18<=N18,"YES","NO") -> YES | AD18: =IF(AC18="YES",AB18,0) -> 760 | AE18: =Projection!BQ18 -> 9 | AF18: =Projection!BR18 -> NO | AG18: =IF(AF18="YES","STOCKOUT RISK",IF(AC18="YES","REORDER REQUIRED",IF(S18>Excess_WoC,"EXCESS STOCK","HEALTHY"))) -> REORDER REQUIRED | AH18: =IF(AG18="STOCKOUT RISK","Projected inventory reaches zero in week "&AE18&", before a new order placed now could arrive (week "&(K18+1)&"). "&IF(AC18="YES","Inventory position of "&FIXED(R18,0)&" units is at or below the reorder point of "&FIXED(N18,0)&", so an order of "&FIXED(AD18,0)&" units is recommended (EOQ "&FIXED(Z18,0)&", case pack "&AA18&"), but it cannot arrive in time: expedite supply or manage the shortfall.","No new order is triggered because inventory position of "&FIXED(R18,0)&" units is above the reorder point of "&FIXED(N18,0)&", but the open PO of "&FIXED(P18,0)&" units is due in week "&Inputs!L51&", which is too late: expedite the open PO."),IF(AG18="REORDER REQUIRED","Inventory position of "&FIXED(R18,0)&" units is "&FIXED(N18-R18,0)&" units below the reorder point of "&FIXED(N18,0)&" units. Replenishment is required. EOQ recommends approximately "&FIXED(Z18,0)&" units, rounded to "&FIXED(AD18,0)&" (case pack "&AA18&").",IF(AG18="EXCESS STOCK","Inventory position represents "&FIXED(S18,1)&" weeks of expected demand, above the "&Excess_WoC&"-week excess-stock threshold. No replenishment is triggered.","Inventory position of "&FIXED(R18,0)&" units is above the reorder point of "&FIXED(N18,0)&" units and covers "&FIXED(S18,1)&" weeks of forecast demand. No order needed now."))) -> Inventory position of 455 units is 24 units below the reorder point of 479 units. Replenishment is required. EOQ recommends approximately 755 units, rounded to 760 (case pack 20). | AI18: =O18*V18 -> 450 | AJ18: =IF(AG18="STOCKOUT RISK",1000,IF(AG18="REORDER REQUIRED",2000,IF(AG18="EXCESS STOCK",3000,4000)))+IF(AG18="EXCESS STOCK",500-MIN(S18,499),MAX(MIN(S18,499),-499)) -> 2003.1111 | AK18: =SUMPRODUCT(--($AJ$7:$AJ$54<AJ18))+SUMPRODUCT(--($AJ$7:AJ18=AJ18)) -> 13
... A54: =Forecast!A54 -> CLN-011 | B54: =Forecast!B54 -> Oven Cleaner Gel | C54: =Inputs!E87 -> SUP-05 | D54: =Forecast!AE54 -> MA4 | E54: =Forecast!AF54 -> 43.75 | F54: =Forecast!AG54 -> 0.10145793 | G54: =Forecast!AH54 -> -0.0084847036 | H54: =Forecast!AI54 -> 5.0256764 | I54: =TSL -> 0.95 | J54: =Z_Value -> 1.6448536 | K54: =Inputs!F87 -> 1 | L54: =J54*H54*SQRT(K54) -> 8.2665021 | M54: =E54*K54 -> 43.75 | N54: =M54+L54 -> 52.016502 | O54: =Inputs!J87 -> 102 | P54: =Inputs!K87 -> 0 | Q54: =Inputs!M87 -> 0 | R54: =O54+P54-Q54 -> 102 | S54: =IF(E54>0,R54/E54,0) -> 2.3314286 | T54: =IF(E54>0,O54/E54,0) -> 2.3314286 | U54: =E54*Weeks_Per_Year -> 2275 | V54: =Inputs!H87 -> 14 | W54: =Inputs!G87 -> 35 | X54: =Holding_Rate -> 0.2 | Y54: =V54*X54 -> 2.8 | Z54: =SQRT((2*U54*W54)/Y54) -> 238.4848 | AA54: =Inputs!I87 -> 12 | AB54: =ROUNDUP(Z54/AA54,0)*AA54 -> 240 | AC54: =IF(R54<=N54,"YES","NO") -> NO | AD54: =IF(AC54="YES",AB54,0) -> 0 | AE54: =Projection!BQ54 -> 3 | AF54: =Projection!BR54 -> NO | AG54: =IF(AF54="YES","STOCKOUT RISK",IF(AC54="YES","REORDER REQUIRED",IF(S54>Excess_WoC,"EXCESS STOCK","HEALTHY"))) -> HEALTHY | AH54: =IF(AG54="STOCKOUT RISK","Projected inventory reaches zero in week "&AE54&", before a new order placed now could arrive (week "&(K54+1)&"). "&IF(AC54="YES","Inventory position of "&FIXED(R54,0)&" units is at or below the reorder point of "&FIXED(N54,0)&", so an order of "&FIXED(AD54,0)&" units is recommended (EOQ "&FIXED(Z54,0)&", case pack "&AA54&"), but it cannot arrive in time: expedite supply or manage the shortfall.","No new order is triggered because inventory position of "&FIXED(R54,0)&" units is above the reorder point of "&FIXED(N54,0)&", but the open PO of "&FIXED(P54,0)&" units is due in week "&Inputs!L87&", which is too late: expedite the open PO."),IF(AG54="REORDER REQUIRED","Inventory position of "&FIXED(R54,0)&" units is "&FIXED(N54-R54,0)&" units below the reorder point of "&FIXED(N54,0)&" units. Replenishment is required. EOQ recommends approximately "&FIXED(Z54,0)&" units, rounded to "&FIXED(AD54,0)&" (case pack "&AA54&").",IF(AG54="EXCESS STOCK","Inventory position represents "&FIXED(S54,1)&" weeks of expected demand, above the "&Excess_WoC&"-week excess-stock threshold. No replenishment is triggered.","Inventory position of "&FIXED(R54,0)&" units is above the reorder point of "&FIXED(N54,0)&" units and covers "&FIXED(S54,1)&" weeks of forecast demand. No order needed now."))) -> Inventory position of 102 units is above the reorder point of 52 units and covers 2.3 weeks of forecast demand. No order needed now. | AI54: =O54*V54 -> 1428 | AJ54: =IF(AG54="STOCKOUT RISK",1000,IF(AG54="REORDER REQUIRED",2000,IF(AG54="EXCESS STOCK",3000,4000)))+IF(AG54="EXCESS STOCK",500-MIN(S54,499),MAX(MIN(S54,499),-499)) -> 4002.3314 | AK54: =SUMPRODUCT(--($AJ$7:$AJ$54<AJ54))+SUMPRODUCT(--($AJ$7:AJ54=AJ54)) -> 26

Sheet Projection
A1: 12-Week Projected Inventory (deterministic, flat forecast)
A2: Closing = Opening + Existing PO Receipt + New Order Receipt - Forecast Demand. Week 1 opening = On Hand - Backorders. Receipts arrive at the start of the week. Negative = projected shortfall. Only today's recommended order is included; future reorders are not simulated.
A4: SKU INPUTS | I4: EXISTING PO RECEIPTS | U4: NEW RECOMMENDED ORDER RECEIPTS (arrives week Lead Time + 1) | AG4: FORECAST DEMAND | AS4: PROJECTED CLOSING INVENTORY | BE4: ZERO FLAG (1 = closing <= 0) | BQ4: RESULT
A5: Week start date -> | I5: =Snapshot_Date+7*(I$6-1) -> 46202 | J5: =Snapshot_Date+7*(J$6-1) -> 46209 | K5: =Snapshot_Date+7*(K$6-1) -> 46216 | L5: =Snapshot_Date+7*(L$6-1) -> 46223 | M5: =Snapshot_Date+7*(M$6-1) -> 46230 | N5: =Snapshot_Date+7*(N$6-1) -> 46237 | O5: =Snapshot_Date+7*(O$6-1) -> 46244 | P5: =Snapshot_Date+7*(P$6-1) -> 46251 | ... BP5: =Snapshot_Date+7*(BP$6-1) -> 46279
A6: SKU | B6: Lead Time (weeks) | C6: Weekly Forecast | D6: Net Opening Inventory (On Hand - Backorders) | E6: Open PO Qty | F6: Open PO Due Week | G6: Recommended New Order | H6: New Order Receipt Week | I6: 1 | J6: 2 | K6: 3 | L6: 4 | M6: 5 | N6: 6 | O6: 7 | P6: 8 | Q6: 9 | R6: 10 | S6: 11 | T6: 12 | U6: 1 | V6: 2 | W6: 3 | X6: 4 | Y6: 5 | Z6: 6 | AA6: 7 | AB6: 8 | AC6: 9 | AD6: 10 | AE6: 11 | AF6: 12 | AG6: 1 | AH6: 2 | AI6: 3 | AJ6: 4 | AK6: 5 | AL6: 6 | AM6: 7 | AN6: 8 | AO6: 9 | AP6: 10 | AQ6: 11 | AR6: 12 | AS6: 1 | AT6: 2 | AU6: 3 | AV6: 4 | AW6: 5 | AX6: 6 | AY6: 7 | AZ6: 8 | BA6: 9 | BB6: 10 | BC6: 11 | BD6: 12 | BE6: 1 | BF6: 2 | BG6: 3 | BH6: 4 | BI6: 5 | BJ6: 6 | BK6: 7 | BL6: 8 | BM6: 9 | BN6: 10 | BO6: 11 | BP6: 12 | BQ6: First Projected Zero Week | BR6: Zero Within Lead Time? | BS6: Min Projected Inventory
A7: =Replenishment_Plan!A7 -> KIT-001 | B7: =Replenishment_Plan!K7 -> 2 | C7: =Replenishment_Plan!E7 -> 61.25 | D7: =Replenishment_Plan!O7-Replenishment_Plan!Q7 -> 236 | E7: =Replenishment_Plan!P7 -> 0 | F7: =Inputs!L40 -> 0 | G7: =Replenishment_Plan!AD7 -> 0 | H7: =IF(G7>0,B7+1,"none") -> none | I7: =IF(AND($E7>0,I$6=$F7),$E7,0) -> 0 | J7: =IF(AND($E7>0,J$6=$F7),$E7,0) -> 0 | K7: =IF(AND($E7>0,K$6=$F7),$E7,0) -> 0 | L7: =IF(AND($E7>0,L$6=$F7),$E7,0) -> 0 | M7: =IF(AND($E7>0,M$6=$F7),$E7,0) -> 0 | N7: =IF(AND($E7>0,N$6=$F7),$E7,0) -> 0 | O7: =IF(AND($E7>0,O$6=$F7),$E7,0) -> 0 | P7: =IF(AND($E7>0,P$6=$F7),$E7,0) -> 0 | ... T7: =IF(AND($E7>0,T$6=$F7),$E7,0) -> 0 | U7: =IF(AND($G7>0,U$6=$H7),$G7,0) -> 0 | V7: =IF(AND($G7>0,V$6=$H7),$G7,0) -> 0 | W7: =IF(AND($G7>0,W$6=$H7),$G7,0) -> 0 | X7: =IF(AND($G7>0,X$6=$H7),$G7,0) -> 0 | Y7: =IF(AND($G7>0,Y$6=$H7),$G7,0) -> 0 | Z7: =IF(AND($G7>0,Z$6=$H7),$G7,0) -> 0 | AA7: =IF(AND($G7>0,AA$6=$H7),$G7,0) -> 0 | AB7: =IF(AND($G7>0,AB$6=$H7),$G7,0) -> 0 | ... AF7: =IF(AND($G7>0,AF$6=$H7),$G7,0) -> 0 | AG7: =$C7 -> 61.25 | AH7: =$C7 -> 61.25 | AI7: =$C7 -> 61.25 | AJ7: =$C7 -> 61.25 | AK7: =$C7 -> 61.25 | AL7: =$C7 -> 61.25 | AM7: =$C7 -> 61.25 | AN7: =$C7 -> 61.25 | ... AR7: =$C7 -> 61.25 | AS7: =$D7+I7+U7-AG7 -> 174.75 | AT7: =AS7+J7+V7-AH7 -> 113.5 | AU7: =AT7+K7+W7-AI7 -> 52.25 | AV7: =AU7+L7+X7-AJ7 -> -9 | AW7: =AV7+M7+Y7-AK7 -> -70.25 | AX7: =AW7+N7+Z7-AL7 -> -131.5 | AY7: =AX7+O7+AA7-AM7 -> -192.75 | AZ7: =AY7+P7+AB7-AN7 -> -254 | BA7: =AZ7+Q7+AC7-AO7 -> -315.25 | ... BD7: =BC7+T7+AF7-AR7 -> -499 | BE7: =IF(AS7<=0,1,0) -> 0 | BF7: =IF(AT7<=0,1,0) -> 0 | BG7: =IF(AU7<=0,1,0) -> 0 | BH7: =IF(AV7<=0,1,0) -> 1 | BI7: =IF(AW7<=0,1,0) -> 1 | BJ7: =IF(AX7<=0,1,0) -> 1 | BK7: =IF(AY7<=0,1,0) -> 1 | BL7: =IF(AZ7<=0,1,0) -> 1 | ... BP7: =IF(BD7<=0,1,0) -> 1 | BQ7: =IF(COUNTIF(BE7:BP7,1)=0,"None",MATCH(1,BE7:BP7,0)) -> 4 | BR7: =IF(COUNTIFS(BE$6:BP$6,"<="&$B7,BE7:BP7,1)>0,"YES","NO") -> NO | BS7: =MIN(AS7:BD7) -> -499
A8: =Replenishment_Plan!A8 -> KIT-002 | B8: =Replenishment_Plan!K8 -> 2 | C8: =Replenishment_Plan!E8 -> 33.5 | D8: =Replenishment_Plan!O8-Replenishment_Plan!Q8 -> 6 | E8: =Replenishment_Plan!P8 -> 92 | F8: =Inputs!L41 -> 1 | G8: =Replenishment_Plan!AD8 -> 180 | H8: =IF(G8>0,B8+1,"none") -> 3 | I8: =IF(AND($E8>0,I$6=$F8),$E8,0) -> 92 | J8: =IF(AND($E8>0,J$6=$F8),$E8,0) -> 0 | K8: =IF(AND($E8>0,K$6=$F8),$E8,0) -> 0 | L8: =IF(AND($E8>0,L$6=$F8),$E8,0) -> 0 | M8: =IF(AND($E8>0,M$6=$F8),$E8,0) -> 0 | N8: =IF(AND($E8>0,N$6=$F8),$E8,0) -> 0 | O8: =IF(AND($E8>0,O$6=$F8),$E8,0) -> 0 | P8: =IF(AND($E8>0,P$6=$F8),$E8,0) -> 0 | ... T8: =IF(AND($E8>0,T$6=$F8),$E8,0) -> 0 | U8: =IF(AND($G8>0,U$6=$H8),$G8,0) -> 0 | V8: =IF(AND($G8>0,V$6=$H8),$G8,0) -> 0 | W8: =IF(AND($G8>0,W$6=$H8),$G8,0) -> 180 | X8: =IF(AND($G8>0,X$6=$H8),$G8,0) -> 0 | Y8: =IF(AND($G8>0,Y$6=$H8),$G8,0) -> 0 | Z8: =IF(AND($G8>0,Z$6=$H8),$G8,0) -> 0 | AA8: =IF(AND($G8>0,AA$6=$H8),$G8,0) -> 0 | AB8: =IF(AND($G8>0,AB$6=$H8),$G8,0) -> 0 | ... AF8: =IF(AND($G8>0,AF$6=$H8),$G8,0) -> 0 | AG8: =$C8 -> 33.5 | AH8: =$C8 -> 33.5 | AI8: =$C8 -> 33.5 | AJ8: =$C8 -> 33.5 | AK8: =$C8 -> 33.5 | AL8: =$C8 -> 33.5 | AM8: =$C8 -> 33.5 | AN8: =$C8 -> 33.5 | ... AR8: =$C8 -> 33.5 | AS8: =$D8+I8+U8-AG8 -> 64.5 | AT8: =AS8+J8+V8-AH8 -> 31 | AU8: =AT8+K8+W8-AI8 -> 177.5 | AV8: =AU8+L8+X8-AJ8 -> 144 | AW8: =AV8+M8+Y8-AK8 -> 110.5 | AX8: =AW8+N8+Z8-AL8 -> 77 | AY8: =AX8+O8+AA8-AM8 -> 43.5 | AZ8: =AY8+P8+AB8-AN8 -> 10 | BA8: =AZ8+Q8+AC8-AO8 -> -23.5 | ... BD8: =BC8+T8+AF8-AR8 -> -124 | BE8: =IF(AS8<=0,1,0) -> 0 | BF8: =IF(AT8<=0,1,0) -> 0 | BG8: =IF(AU8<=0,1,0) -> 0 | BH8: =IF(AV8<=0,1,0) -> 0 | BI8: =IF(AW8<=0,1,0) -> 0 | BJ8: =IF(AX8<=0,1,0) -> 0 | BK8: =IF(AY8<=0,1,0) -> 0 | BL8: =IF(AZ8<=0,1,0) -> 0 | ... BP8: =IF(BD8<=0,1,0) -> 1 | BQ8: =IF(COUNTIF(BE8:BP8,1)=0,"None",MATCH(1,BE8:BP8,0)) -> 9 | BR8: =IF(COUNTIFS(BE$6:BP$6,"<="&$B8,BE8:BP8,1)>0,"YES","NO") -> NO | BS8: =MIN(AS8:BD8) -> -124
A9: =Replenishment_Plan!A9 -> KIT-003 | B9: =Replenishment_Plan!K9 -> 2 | C9: =Replenishment_Plan!E9 -> 95.125 | D9: =Replenishment_Plan!O9-Replenishment_Plan!Q9 -> -36 | E9: =Replenishment_Plan!P9 -> 0 | F9: =Inputs!L42 -> 0 | G9: =Replenishment_Plan!AD9 -> 366 | H9: =IF(G9>0,B9+1,"none") -> 3 | I9: =IF(AND($E9>0,I$6=$F9),$E9,0) -> 0 | J9: =IF(AND($E9>0,J$6=$F9),$E9,0) -> 0 | K9: =IF(AND($E9>0,K$6=$F9),$E9,0) -> 0 | L9: =IF(AND($E9>0,L$6=$F9),$E9,0) -> 0 | M9: =IF(AND($E9>0,M$6=$F9),$E9,0) -> 0 | N9: =IF(AND($E9>0,N$6=$F9),$E9,0) -> 0 | O9: =IF(AND($E9>0,O$6=$F9),$E9,0) -> 0 | P9: =IF(AND($E9>0,P$6=$F9),$E9,0) -> 0 | ... T9: =IF(AND($E9>0,T$6=$F9),$E9,0) -> 0 | U9: =IF(AND($G9>0,U$6=$H9),$G9,0) -> 0 | V9: =IF(AND($G9>0,V$6=$H9),$G9,0) -> 0 | W9: =IF(AND($G9>0,W$6=$H9),$G9,0) -> 366 | X9: =IF(AND($G9>0,X$6=$H9),$G9,0) -> 0 | Y9: =IF(AND($G9>0,Y$6=$H9),$G9,0) -> 0 | Z9: =IF(AND($G9>0,Z$6=$H9),$G9,0) -> 0 | AA9: =IF(AND($G9>0,AA$6=$H9),$G9,0) -> 0 | AB9: =IF(AND($G9>0,AB$6=$H9),$G9,0) -> 0 | ... AF9: =IF(AND($G9>0,AF$6=$H9),$G9,0) -> 0 | AG9: =$C9 -> 95.125 | AH9: =$C9 -> 95.125 | AI9: =$C9 -> 95.125 | AJ9: =$C9 -> 95.125 | AK9: =$C9 -> 95.125 | AL9: =$C9 -> 95.125 | AM9: =$C9 -> 95.125 | AN9: =$C9 -> 95.125 | ... AR9: =$C9 -> 95.125 | AS9: =$D9+I9+U9-AG9 -> -131.125 | AT9: =AS9+J9+V9-AH9 -> -226.25 | AU9: =AT9+K9+W9-AI9 -> 44.625 | AV9: =AU9+L9+X9-AJ9 -> -50.5 | AW9: =AV9+M9+Y9-AK9 -> -145.625 | AX9: =AW9+N9+Z9-AL9 -> -240.75 | AY9: =AX9+O9+AA9-AM9 -> -335.875 | AZ9: =AY9+P9+AB9-AN9 -> -431 | BA9: =AZ9+Q9+AC9-AO9 -> -526.125 | ... BD9: =BC9+T9+AF9-AR9 -> -811.5 | BE9: =IF(AS9<=0,1,0) -> 1 | BF9: =IF(AT9<=0,1,0) -> 1 | BG9: =IF(AU9<=0,1,0) -> 0 | BH9: =IF(AV9<=0,1,0) -> 1 | BI9: =IF(AW9<=0,1,0) -> 1 | BJ9: =IF(AX9<=0,1,0) -> 1 | BK9: =IF(AY9<=0,1,0) -> 1 | BL9: =IF(AZ9<=0,1,0) -> 1 | ... BP9: =IF(BD9<=0,1,0) -> 1 | BQ9: =IF(COUNTIF(BE9:BP9,1)=0,"None",MATCH(1,BE9:BP9,0)) -> 1 | BR9: =IF(COUNTIFS(BE$6:BP$6,"<="&$B9,BE9:BP9,1)>0,"YES","NO") -> YES | BS9: =MIN(AS9:BD9) -> -811.5
A10: =Replenishment_Plan!A10 -> KIT-004 | B10: =Replenishment_Plan!K10 -> 2 | C10: =Replenishment_Plan!E10 -> 96.5 | D10: =Replenishment_Plan!O10-Replenishment_Plan!Q10 -> 270 | E10: =Replenishment_Plan!P10 -> 0 | F10: =Inputs!L43 -> 0 | G10: =Replenishment_Plan!AD10 -> 0 | H10: =IF(G10>0,B10+1,"none") -> none | I10: =IF(AND($E10>0,I$6=$F10),$E10,0) -> 0 | J10: =IF(AND($E10>0,J$6=$F10),$E10,0) -> 0 | K10: =IF(AND($E10>0,K$6=$F10),$E10,0) -> 0 | L10: =IF(AND($E10>0,L$6=$F10),$E10,0) -> 0 | M10: =IF(AND($E10>0,M$6=$F10),$E10,0) -> 0 | N10: =IF(AND($E10>0,N$6=$F10),$E10,0) -> 0 | O10: =IF(AND($E10>0,O$6=$F10),$E10,0) -> 0 | P10: =IF(AND($E10>0,P$6=$F10),$E10,0) -> 0 | ... T10: =IF(AND($E10>0,T$6=$F10),$E10,0) -> 0 | U10: =IF(AND($G10>0,U$6=$H10),$G10,0) -> 0 | V10: =IF(AND($G10>0,V$6=$H10),$G10,0) -> 0 | W10: =IF(AND($G10>0,W$6=$H10),$G10,0) -> 0 | X10: =IF(AND($G10>0,X$6=$H10),$G10,0) -> 0 | Y10: =IF(AND($G10>0,Y$6=$H10),$G10,0) -> 0 | Z10: =IF(AND($G10>0,Z$6=$H10),$G10,0) -> 0 | AA10: =IF(AND($G10>0,AA$6=$H10),$G10,0) -> 0 | AB10: =IF(AND($G10>0,AB$6=$H10),$G10,0) -> 0 | ... AF10: =IF(AND($G10>0,AF$6=$H10),$G10,0) -> 0 | AG10: =$C10 -> 96.5 | AH10: =$C10 -> 96.5 | AI10: =$C10 -> 96.5 | AJ10: =$C10 -> 96.5 | AK10: =$C10 -> 96.5 | AL10: =$C10 -> 96.5 | AM10: =$C10 -> 96.5 | AN10: =$C10 -> 96.5 | ... AR10: =$C10 -> 96.5 | AS10: =$D10+I10+U10-AG10 -> 173.5 | AT10: =AS10+J10+V10-AH10 -> 77 | AU10: =AT10+K10+W10-AI10 -> -19.5 | AV10: =AU10+L10+X10-AJ10 -> -116 | AW10: =AV10+M10+Y10-AK10 -> -212.5 | AX10: =AW10+N10+Z10-AL10 -> -309 | AY10: =AX10+O10+AA10-AM10 -> -405.5 | AZ10: =AY10+P10+AB10-AN10 -> -502 | BA10: =AZ10+Q10+AC10-AO10 -> -598.5 | ... BD10: =BC10+T10+AF10-AR10 -> -888 | BE10: =IF(AS10<=0,1,0) -> 0 | BF10: =IF(AT10<=0,1,0) -> 0 | BG10: =IF(AU10<=0,1,0) -> 1 | BH10: =IF(AV10<=0,1,0) -> 1 | BI10: =IF(AW10<=0,1,0) -> 1 | BJ10: =IF(AX10<=0,1,0) -> 1 | BK10: =IF(AY10<=0,1,0) -> 1 | BL10: =IF(AZ10<=0,1,0) -> 1 | ... BP10: =IF(BD10<=0,1,0) -> 1 | BQ10: =IF(COUNTIF(BE10:BP10,1)=0,"None",MATCH(1,BE10:BP10,0)) -> 3 | BR10: =IF(COUNTIFS(BE$6:BP$6,"<="&$B10,BE10:BP10,1)>0,"YES","NO") -> NO | BS10: =MIN(AS10:BD10) -> -888
A11: =Replenishment_Plan!A11 -> KIT-005 | B11: =Replenishment_Plan!K11 -> 2 | C11: =Replenishment_Plan!E11 -> 23.875 | D11: =Replenishment_Plan!O11-Replenishment_Plan!Q11 -> 334 | E11: =Replenishment_Plan!P11 -> 0 | F11: =Inputs!L44 -> 0 | G11: =Replenishment_Plan!AD11 -> 0 | H11: =IF(G11>0,B11+1,"none") -> none | I11: =IF(AND($E11>0,I$6=$F11),$E11,0) -> 0 | J11: =IF(AND($E11>0,J$6=$F11),$E11,0) -> 0 | K11: =IF(AND($E11>0,K$6=$F11),$E11,0) -> 0 | L11: =IF(AND($E11>0,L$6=$F11),$E11,0) -> 0 | M11: =IF(AND($E11>0,M$6=$F11),$E11,0) -> 0 | N11: =IF(AND($E11>0,N$6=$F11),$E11,0) -> 0 | O11: =IF(AND($E11>0,O$6=$F11),$E11,0) -> 0 | P11: =IF(AND($E11>0,P$6=$F11),$E11,0) -> 0 | ... T11: =IF(AND($E11>0,T$6=$F11),$E11,0) -> 0 | U11: =IF(AND($G11>0,U$6=$H11),$G11,0) -> 0 | V11: =IF(AND($G11>0,V$6=$H11),$G11,0) -> 0 | W11: =IF(AND($G11>0,W$6=$H11),$G11,0) -> 0 | X11: =IF(AND($G11>0,X$6=$H11),$G11,0) -> 0 | Y11: =IF(AND($G11>0,Y$6=$H11),$G11,0) -> 0 | Z11: =IF(AND($G11>0,Z$6=$H11),$G11,0) -> 0 | AA11: =IF(AND($G11>0,AA$6=$H11),$G11,0) -> 0 | AB11: =IF(AND($G11>0,AB$6=$H11),$G11,0) -> 0 | ... AF11: =IF(AND($G11>0,AF$6=$H11),$G11,0) -> 0 | AG11: =$C11 -> 23.875 | AH11: =$C11 -> 23.875 | AI11: =$C11 -> 23.875 | AJ11: =$C11 -> 23.875 | AK11: =$C11 -> 23.875 | AL11: =$C11 -> 23.875 | AM11: =$C11 -> 23.875 | AN11: =$C11 -> 23.875 | ... AR11: =$C11 -> 23.875 | AS11: =$D11+I11+U11-AG11 -> 310.125 | AT11: =AS11+J11+V11-AH11 -> 286.25 | AU11: =AT11+K11+W11-AI11 -> 262.375 | AV11: =AU11+L11+X11-AJ11 -> 238.5 | AW11: =AV11+M11+Y11-AK11 -> 214.625 | AX11: =AW11+N11+Z11-AL11 -> 190.75 | AY11: =AX11+O11+AA11-AM11 -> 166.875 | AZ11: =AY11+P11+AB11-AN11 -> 143 | BA11: =AZ11+Q11+AC11-AO11 -> 119.125 | ... BD11: =BC11+T11+AF11-AR11 -> 47.5 | BE11: =IF(AS11<=0,1,0) -> 0 | BF11: =IF(AT11<=0,1,0) -> 0 | BG11: =IF(AU11<=0,1,0) -> 0 | BH11: =IF(AV11<=0,1,0) -> 0 | BI11: =IF(AW11<=0,1,0) -> 0 | BJ11: =IF(AX11<=0,1,0) -> 0 | BK11: =IF(AY11<=0,1,0) -> 0 | BL11: =IF(AZ11<=0,1,0) -> 0 | ... BP11: =IF(BD11<=0,1,0) -> 0 | BQ11: =IF(COUNTIF(BE11:BP11,1)=0,"None",MATCH(1,BE11:BP11,0)) -> None | BR11: =IF(COUNTIFS(BE$6:BP$6,"<="&$B11,BE11:BP11,1)>0,"YES","NO") -> NO | BS11: =MIN(AS11:BD11) -> 47.5
A12: =Replenishment_Plan!A12 -> KIT-006 | B12: =Replenishment_Plan!K12 -> 2 | C12: =Replenishment_Plan!E12 -> 66.625 | D12: =Replenishment_Plan!O12-Replenishment_Plan!Q12 -> 378 | E12: =Replenishment_Plan!P12 -> 0 | F12: =Inputs!L45 -> 0 | G12: =Replenishment_Plan!AD12 -> 0 | H12: =IF(G12>0,B12+1,"none") -> none | I12: =IF(AND($E12>0,I$6=$F12),$E12,0) -> 0 | J12: =IF(AND($E12>0,J$6=$F12),$E12,0) -> 0 | K12: =IF(AND($E12>0,K$6=$F12),$E12,0) -> 0 | L12: =IF(AND($E12>0,L$6=$F12),$E12,0) -> 0 | M12: =IF(AND($E12>0,M$6=$F12),$E12,0) -> 0 | N12: =IF(AND($E12>0,N$6=$F12),$E12,0) -> 0 | O12: =IF(AND($E12>0,O$6=$F12),$E12,0) -> 0 | P12: =IF(AND($E12>0,P$6=$F12),$E12,0) -> 0 | ... T12: =IF(AND($E12>0,T$6=$F12),$E12,0) -> 0 | U12: =IF(AND($G12>0,U$6=$H12),$G12,0) -> 0 | V12: =IF(AND($G12>0,V$6=$H12),$G12,0) -> 0 | W12: =IF(AND($G12>0,W$6=$H12),$G12,0) -> 0 | X12: =IF(AND($G12>0,X$6=$H12),$G12,0) -> 0 | Y12: =IF(AND($G12>0,Y$6=$H12),$G12,0) -> 0 | Z12: =IF(AND($G12>0,Z$6=$H12),$G12,0) -> 0 | AA12: =IF(AND($G12>0,AA$6=$H12),$G12,0) -> 0 | AB12: =IF(AND($G12>0,AB$6=$H12),$G12,0) -> 0 | ... AF12: =IF(AND($G12>0,AF$6=$H12),$G12,0) -> 0 | AG12: =$C12 -> 66.625 | AH12: =$C12 -> 66.625 | AI12: =$C12 -> 66.625 | AJ12: =$C12 -> 66.625 | AK12: =$C12 -> 66.625 | AL12: =$C12 -> 66.625 | AM12: =$C12 -> 66.625 | AN12: =$C12 -> 66.625 | ... AR12: =$C12 -> 66.625 | AS12: =$D12+I12+U12-AG12 -> 311.375 | AT12: =AS12+J12+V12-AH12 -> 244.75 | AU12: =AT12+K12+W12-AI12 -> 178.125 | AV12: =AU12+L12+X12-AJ12 -> 111.5 | AW12: =AV12+M12+Y12-AK12 -> 44.875 | AX12: =AW12+N12+Z12-AL12 -> -21.75 | AY12: =AX12+O12+AA12-AM12 -> -88.375 | AZ12: =AY12+P12+AB12-AN12 -> -155 | BA12: =AZ12+Q12+AC12-AO12 -> -221.625 | ... BD12: =BC12+T12+AF12-AR12 -> -421.5 | BE12: =IF(AS12<=0,1,0) -> 0 | BF12: =IF(AT12<=0,1,0) -> 0 | BG12: =IF(AU12<=0,1,0) -> 0 | BH12: =IF(AV12<=0,1,0) -> 0 | BI12: =IF(AW12<=0,1,0) -> 0 | BJ12: =IF(AX12<=0,1,0) -> 1 | BK12: =IF(AY12<=0,1,0) -> 1 | BL12: =IF(AZ12<=0,1,0) -> 1 | ... BP12: =IF(BD12<=0,1,0) -> 1 | BQ12: =IF(COUNTIF(BE12:BP12,1)=0,"None",MATCH(1,BE12:BP12,0)) -> 6 | BR12: =IF(COUNTIFS(BE$6:BP$6,"<="&$B12,BE12:BP12,1)>0,"YES","NO") -> NO | BS12: =MIN(AS12:BD12) -> -421.5
A13: =Replenishment_Plan!A13 -> KIT-007 | B13: =Replenishment_Plan!K13 -> 2 | C13: =Replenishment_Plan!E13 -> 8.875 | D13: =Replenishment_Plan!O13-Replenishment_Plan!Q13 -> 21 | E13: =Replenishment_Plan!P13 -> 0 | F13: =Inputs!L46 -> 0 | G13: =Replenishment_Plan!AD13 -> 47 | H13: =IF(G13>0,B13+1,"none") -> 3 | I13: =IF(AND($E13>0,I$6=$F13),$E13,0) -> 0 | J13: =IF(AND($E13>0,J$6=$F13),$E13,0) -> 0 | K13: =IF(AND($E13>0,K$6=$F13),$E13,0) -> 0 | L13: =IF(AND($E13>0,L$6=$F13),$E13,0) -> 0 | M13: =IF(AND($E13>0,M$6=$F13),$E13,0) -> 0 | N13: =IF(AND($E13>0,N$6=$F13),$E13,0) -> 0 | O13: =IF(AND($E13>0,O$6=$F13),$E13,0) -> 0 | P13: =IF(AND($E13>0,P$6=$F13),$E13,0) -> 0 | ... T13: =IF(AND($E13>0,T$6=$F13),$E13,0) -> 0 | U13: =IF(AND($G13>0,U$6=$H13),$G13,0) -> 0 | V13: =IF(AND($G13>0,V$6=$H13),$G13,0) -> 0 | W13: =IF(AND($G13>0,W$6=$H13),$G13,0) -> 47 | X13: =IF(AND($G13>0,X$6=$H13),$G13,0) -> 0 | Y13: =IF(AND($G13>0,Y$6=$H13),$G13,0) -> 0 | Z13: =IF(AND($G13>0,Z$6=$H13),$G13,0) -> 0 | AA13: =IF(AND($G13>0,AA$6=$H13),$G13,0) -> 0 | AB13: =IF(AND($G13>0,AB$6=$H13),$G13,0) -> 0 | ... AF13: =IF(AND($G13>0,AF$6=$H13),$G13,0) -> 0 | AG13: =$C13 -> 8.875 | AH13: =$C13 -> 8.875 | AI13: =$C13 -> 8.875 | AJ13: =$C13 -> 8.875 | AK13: =$C13 -> 8.875 | AL13: =$C13 -> 8.875 | AM13: =$C13 -> 8.875 | AN13: =$C13 -> 8.875 | ... AR13: =$C13 -> 8.875 | AS13: =$D13+I13+U13-AG13 -> 12.125 | AT13: =AS13+J13+V13-AH13 -> 3.25 | AU13: =AT13+K13+W13-AI13 -> 41.375 | AV13: =AU13+L13+X13-AJ13 -> 32.5 | AW13: =AV13+M13+Y13-AK13 -> 23.625 | AX13: =AW13+N13+Z13-AL13 -> 14.75 | AY13: =AX13+O13+AA13-AM13 -> 5.875 | AZ13: =AY13+P13+AB13-AN13 -> -3 | BA13: =AZ13+Q13+AC13-AO13 -> -11.875 | ... BD13: =BC13+T13+AF13-AR13 -> -38.5 | BE13: =IF(AS13<=0,1,0) -> 0 | BF13: =IF(AT13<=0,1,0) -> 0 | BG13: =IF(AU13<=0,1,0) -> 0 | BH13: =IF(AV13<=0,1,0) -> 0 | BI13: =IF(AW13<=0,1,0) -> 0 | BJ13: =IF(AX13<=0,1,0) -> 0 | BK13: =IF(AY13<=0,1,0) -> 0 | BL13: =IF(AZ13<=0,1,0) -> 1 | ... BP13: =IF(BD13<=0,1,0) -> 1 | BQ13: =IF(COUNTIF(BE13:BP13,1)=0,"None",MATCH(1,BE13:BP13,0)) -> 8 | BR13: =IF(COUNTIFS(BE$6:BP$6,"<="&$B13,BE13:BP13,1)>0,"YES","NO") -> NO | BS13: =MIN(AS13:BD13) -> -38.5
A14: =Replenishment_Plan!A14 -> KIT-008 | B14: =Replenishment_Plan!K14 -> 2 | C14: =Replenishment_Plan!E14 -> 41.5 | D14: =Replenishment_Plan!O14-Replenishment_Plan!Q14 -> 766 | E14: =Replenishment_Plan!P14 -> 0 | F14: =Inputs!L47 -> 0 | G14: =Replenishment_Plan!AD14 -> 0 | H14: =IF(G14>0,B14+1,"none") -> none | I14: =IF(AND($E14>0,I$6=$F14),$E14,0) -> 0 | J14: =IF(AND($E14>0,J$6=$F14),$E14,0) -> 0 | K14: =IF(AND($E14>0,K$6=$F14),$E14,0) -> 0 | L14: =IF(AND($E14>0,L$6=$F14),$E14,0) -> 0 | M14: =IF(AND($E14>0,M$6=$F14),$E14,0) -> 0 | N14: =IF(AND($E14>0,N$6=$F14),$E14,0) -> 0 | O14: =IF(AND($E14>0,O$6=$F14),$E14,0) -> 0 | P14: =IF(AND($E14>0,P$6=$F14),$E14,0) -> 0 | ... T14: =IF(AND($E14>0,T$6=$F14),$E14,0) -> 0 | U14: =IF(AND($G14>0,U$6=$H14),$G14,0) -> 0 | V14: =IF(AND($G14>0,V$6=$H14),$G14,0) -> 0 | W14: =IF(AND($G14>0,W$6=$H14),$G14,0) -> 0 | X14: =IF(AND($G14>0,X$6=$H14),$G14,0) -> 0 | Y14: =IF(AND($G14>0,Y$6=$H14),$G14,0) -> 0 | Z14: =IF(AND($G14>0,Z$6=$H14),$G14,0) -> 0 | AA14: =IF(AND($G14>0,AA$6=$H14),$G14,0) -> 0 | AB14: =IF(AND($G14>0,AB$6=$H14),$G14,0) -> 0 | ... AF14: =IF(AND($G14>0,AF$6=$H14),$G14,0) -> 0 | AG14: =$C14 -> 41.5 | AH14: =$C14 -> 41.5 | AI14: =$C14 -> 41.5 | AJ14: =$C14 -> 41.5 | AK14: =$C14 -> 41.5 | AL14: =$C14 -> 41.5 | AM14: =$C14 -> 41.5 | AN14: =$C14 -> 41.5 | ... AR14: =$C14 -> 41.5 | AS14: =$D14+I14+U14-AG14 -> 724.5 | AT14: =AS14+J14+V14-AH14 -> 683 | AU14: =AT14+K14+W14-AI14 -> 641.5 | AV14: =AU14+L14+X14-AJ14 -> 600 | AW14: =AV14+M14+Y14-AK14 -> 558.5 | AX14: =AW14+N14+Z14-AL14 -> 517 | AY14: =AX14+O14+AA14-AM14 -> 475.5 | AZ14: =AY14+P14+AB14-AN14 -> 434 | BA14: =AZ14+Q14+AC14-AO14 -> 392.5 | ... BD14: =BC14+T14+AF14-AR14 -> 268 | BE14: =IF(AS14<=0,1,0) -> 0 | BF14: =IF(AT14<=0,1,0) -> 0 | BG14: =IF(AU14<=0,1,0) -> 0 | BH14: =IF(AV14<=0,1,0) -> 0 | BI14: =IF(AW14<=0,1,0) -> 0 | BJ14: =IF(AX14<=0,1,0) -> 0 | BK14: =IF(AY14<=0,1,0) -> 0 | BL14: =IF(AZ14<=0,1,0) -> 0 | ... BP14: =IF(BD14<=0,1,0) -> 0 | BQ14: =IF(COUNTIF(BE14:BP14,1)=0,"None",MATCH(1,BE14:BP14,0)) -> None | BR14: =IF(COUNTIFS(BE$6:BP$6,"<="&$B14,BE14:BP14,1)>0,"YES","NO") -> NO | BS14: =MIN(AS14:BD14) -> 268
A15: =Replenishment_Plan!A15 -> KIT-009 | B15: =Replenishment_Plan!K15 -> 2 | C15: =Replenishment_Plan!E15 -> 39.5 | D15: =Replenishment_Plan!O15-Replenishment_Plan!Q15 -> 80 | E15: =Replenishment_Plan!P15 -> 0 | F15: =Inputs!L48 -> 0 | G15: =Replenishment_Plan!AD15 -> 190 | H15: =IF(G15>0,B15+1,"none") -> 3 | I15: =IF(AND($E15>0,I$6=$F15),$E15,0) -> 0 | J15: =IF(AND($E15>0,J$6=$F15),$E15,0) -> 0 | K15: =IF(AND($E15>0,K$6=$F15),$E15,0) -> 0 | L15: =IF(AND($E15>0,L$6=$F15),$E15,0) -> 0 | M15: =IF(AND($E15>0,M$6=$F15),$E15,0) -> 0 | N15: =IF(AND($E15>0,N$6=$F15),$E15,0) -> 0 | O15: =IF(AND($E15>0,O$6=$F15),$E15,0) -> 0 | P15: =IF(AND($E15>0,P$6=$F15),$E15,0) -> 0 | ... T15: =IF(AND($E15>0,T$6=$F15),$E15,0) -> 0 | U15: =IF(AND($G15>0,U$6=$H15),$G15,0) -> 0 | V15: =IF(AND($G15>0,V$6=$H15),$G15,0) -> 0 | W15: =IF(AND($G15>0,W$6=$H15),$G15,0) -> 190 | X15: =IF(AND($G15>0,X$6=$H15),$G15,0) -> 0 | Y15: =IF(AND($G15>0,Y$6=$H15),$G15,0) -> 0 | Z15: =IF(AND($G15>0,Z$6=$H15),$G15,0) -> 0 | AA15: =IF(AND($G15>0,AA$6=$H15),$G15,0) -> 0 | AB15: =IF(AND($G15>0,AB$6=$H15),$G15,0) -> 0 | ... AF15: =IF(AND($G15>0,AF$6=$H15),$G15,0) -> 0 | AG15: =$C15 -> 39.5 | AH15: =$C15 -> 39.5 | AI15: =$C15 -> 39.5 | AJ15: =$C15 -> 39.5 | AK15: =$C15 -> 39.5 | AL15: =$C15 -> 39.5 | AM15: =$C15 -> 39.5 | AN15: =$C15 -> 39.5 | ... AR15: =$C15 -> 39.5 | AS15: =$D15+I15+U15-AG15 -> 40.5 | AT15: =AS15+J15+V15-AH15 -> 1 | AU15: =AT15+K15+W15-AI15 -> 151.5 | AV15: =AU15+L15+X15-AJ15 -> 112 | AW15: =AV15+M15+Y15-AK15 -> 72.5 | AX15: =AW15+N15+Z15-AL15 -> 33 | AY15: =AX15+O15+AA15-AM15 -> -6.5 | AZ15: =AY15+P15+AB15-AN15 -> -46 | BA15: =AZ15+Q15+AC15-AO15 -> -85.5 | ... BD15: =BC15+T15+AF15-AR15 -> -204 | BE15: =IF(AS15<=0,1,0) -> 0 | BF15: =IF(AT15<=0,1,0) -> 0 | BG15: =IF(AU15<=0,1,0) -> 0 | BH15: =IF(AV15<=0,1,0) -> 0 | BI15: =IF(AW15<=0,1,0) -> 0 | BJ15: =IF(AX15<=0,1,0) -> 0 | BK15: =IF(AY15<=0,1,0) -> 1 | BL15: =IF(AZ15<=0,1,0) -> 1 | ... BP15: =IF(BD15<=0,1,0) -> 1 | BQ15: =IF(COUNTIF(BE15:BP15,1)=0,"None",MATCH(1,BE15:BP15,0)) -> 7 | BR15: =IF(COUNTIFS(BE$6:BP$6,"<="&$B15,BE15:BP15,1)>0,"YES","NO") -> NO | BS15: =MIN(AS15:BD15) -> -204
A16: =Replenishment_Plan!A16 -> KIT-010 | B16: =Replenishment_Plan!K16 -> 2 | C16: =Replenishment_Plan!E16 -> 101 | D16: =Replenishment_Plan!O16-Replenishment_Plan!Q16 -> 304 | E16: =Replenishment_Plan!P16 -> 0 | F16: =Inputs!L49 -> 0 | G16: =Replenishment_Plan!AD16 -> 0 | H16: =IF(G16>0,B16+1,"none") -> none | I16: =IF(AND($E16>0,I$6=$F16),$E16,0) -> 0 | J16: =IF(AND($E16>0,J$6=$F16),$E16,0) -> 0 | K16: =IF(AND($E16>0,K$6=$F16),$E16,0) -> 0 | L16: =IF(AND($E16>0,L$6=$F16),$E16,0) -> 0 | M16: =IF(AND($E16>0,M$6=$F16),$E16,0) -> 0 | N16: =IF(AND($E16>0,N$6=$F16),$E16,0) -> 0 | O16: =IF(AND($E16>0,O$6=$F16),$E16,0) -> 0 | P16: =IF(AND($E16>0,P$6=$F16),$E16,0) -> 0 | ... T16: =IF(AND($E16>0,T$6=$F16),$E16,0) -> 0 | U16: =IF(AND($G16>0,U$6=$H16),$G16,0) -> 0 | V16: =IF(AND($G16>0,V$6=$H16),$G16,0) -> 0 | W16: =IF(AND($G16>0,W$6=$H16),$G16,0) -> 0 | X16: =IF(AND($G16>0,X$6=$H16),$G16,0) -> 0 | Y16: =IF(AND($G16>0,Y$6=$H16),$G16,0) -> 0 | Z16: =IF(AND($G16>0,Z$6=$H16),$G16,0) -> 0 | AA16: =IF(AND($G16>0,AA$6=$H16),$G16,0) -> 0 | AB16: =IF(AND($G16>0,AB$6=$H16),$G16,0) -> 0 | ... AF16: =IF(AND($G16>0,AF$6=$H16),$G16,0) -> 0 | AG16: =$C16 -> 101 | AH16: =$C16 -> 101 | AI16: =$C16 -> 101 | AJ16: =$C16 -> 101 | AK16: =$C16 -> 101 | AL16: =$C16 -> 101 | AM16: =$C16 -> 101 | AN16: =$C16 -> 101 | ... AR16: =$C16 -> 101 | AS16: =$D16+I16+U16-AG16 -> 203 | AT16: =AS16+J16+V16-AH16 -> 102 | AU16: =AT16+K16+W16-AI16 -> 1 | AV16: =AU16+L16+X16-AJ16 -> -100 | AW16: =AV16+M16+Y16-AK16 -> -201 | AX16: =AW16+N16+Z16-AL16 -> -302 | AY16: =AX16+O16+AA16-AM16 -> -403 | AZ16: =AY16+P16+AB16-AN16 -> -504 | BA16: =AZ16+Q16+AC16-AO16 -> -605 | ... BD16: =BC16+T16+AF16-AR16 -> -908 | BE16: =IF(AS16<=0,1,0) -> 0 | BF16: =IF(AT16<=0,1,0) -> 0 | BG16: =IF(AU16<=0,1,0) -> 0 | BH16: =IF(AV16<=0,1,0) -> 1 | BI16: =IF(AW16<=0,1,0) -> 1 | BJ16: =IF(AX16<=0,1,0) -> 1 | BK16: =IF(AY16<=0,1,0) -> 1 | BL16: =IF(AZ16<=0,1,0) -> 1 | ... BP16: =IF(BD16<=0,1,0) -> 1 | BQ16: =IF(COUNTIF(BE16:BP16,1)=0,"None",MATCH(1,BE16:BP16,0)) -> 4 | BR16: =IF(COUNTIFS(BE$6:BP$6,"<="&$B16,BE16:BP16,1)>0,"YES","NO") -> NO | BS16: =MIN(AS16:BD16) -> -908
A17: =Replenishment_Plan!A17 -> BTH-001 | B17: =Replenishment_Plan!K17 -> 3 | C17: =Replenishment_Plan!E17 -> 106 | D17: =Replenishment_Plan!O17-Replenishment_Plan!Q17 -> 486 | E17: =Replenishment_Plan!P17 -> 0 | F17: =Inputs!L50 -> 0 | G17: =Replenishment_Plan!AD17 -> 0 | H17: =IF(G17>0,B17+1,"none") -> none | I17: =IF(AND($E17>0,I$6=$F17),$E17,0) -> 0 | J17: =IF(AND($E17>0,J$6=$F17),$E17,0) -> 0 | K17: =IF(AND($E17>0,K$6=$F17),$E17,0) -> 0 | L17: =IF(AND($E17>0,L$6=$F17),$E17,0) -> 0 | M17: =IF(AND($E17>0,M$6=$F17),$E17,0) -> 0 | N17: =IF(AND($E17>0,N$6=$F17),$E17,0) -> 0 | O17: =IF(AND($E17>0,O$6=$F17),$E17,0) -> 0 | P17: =IF(AND($E17>0,P$6=$F17),$E17,0) -> 0 | ... T17: =IF(AND($E17>0,T$6=$F17),$E17,0) -> 0 | U17: =IF(AND($G17>0,U$6=$H17),$G17,0) -> 0 | V17: =IF(AND($G17>0,V$6=$H17),$G17,0) -> 0 | W17: =IF(AND($G17>0,W$6=$H17),$G17,0) -> 0 | X17: =IF(AND($G17>0,X$6=$H17),$G17,0) -> 0 | Y17: =IF(AND($G17>0,Y$6=$H17),$G17,0) -> 0 | Z17: =IF(AND($G17>0,Z$6=$H17),$G17,0) -> 0 | AA17: =IF(AND($G17>0,AA$6=$H17),$G17,0) -> 0 | AB17: =IF(AND($G17>0,AB$6=$H17),$G17,0) -> 0 | ... AF17: =IF(AND($G17>0,AF$6=$H17),$G17,0) -> 0 | AG17: =$C17 -> 106 | AH17: =$C17 -> 106 | AI17: =$C17 -> 106 | AJ17: =$C17 -> 106 | AK17: =$C17 -> 106 | AL17: =$C17 -> 106 | AM17: =$C17 -> 106 | AN17: =$C17 -> 106 | ... AR17: =$C17 -> 106 | AS17: =$D17+I17+U17-AG17 -> 380 | AT17: =AS17+J17+V17-AH17 -> 274 | AU17: =AT17+K17+W17-AI17 -> 168 | AV17: =AU17+L17+X17-AJ17 -> 62 | AW17: =AV17+M17+Y17-AK17 -> -44 | AX17: =AW17+N17+Z17-AL17 -> -150 | AY17: =AX17+O17+AA17-AM17 -> -256 | AZ17: =AY17+P17+AB17-AN17 -> -362 | BA17: =AZ17+Q17+AC17-AO17 -> -468 | ... BD17: =BC17+T17+AF17-AR17 -> -786 | BE17: =IF(AS17<=0,1,0) -> 0 | BF17: =IF(AT17<=0,1,0) -> 0 | BG17: =IF(AU17<=0,1,0) -> 0 | BH17: =IF(AV17<=0,1,0) -> 0 | BI17: =IF(AW17<=0,1,0) -> 1 | BJ17: =IF(AX17<=0,1,0) -> 1 | BK17: =IF(AY17<=0,1,0) -> 1 | BL17: =IF(AZ17<=0,1,0) -> 1 | ... BP17: =IF(BD17<=0,1,0) -> 1 | BQ17: =IF(COUNTIF(BE17:BP17,1)=0,"None",MATCH(1,BE17:BP17,0)) -> 5 | BR17: =IF(COUNTIFS(BE$6:BP$6,"<="&$B17,BE17:BP17,1)>0,"YES","NO") -> NO | BS17: =MIN(AS17:BD17) -> -786
A18: =Replenishment_Plan!A18 -> BTH-002 | B18: =Replenishment_Plan!K18 -> 3 | C18: =Replenishment_Plan!E18 -> 146.25 | D18: =Replenishment_Plan!O18-Replenishment_Plan!Q18 -> 75 | E18: =Replenishment_Plan!P18 -> 380 | F18: =Inputs!L51 -> 1 | G18: =Replenishment_Plan!AD18 -> 760 | H18: =IF(G18>0,B18+1,"none") -> 4 | I18: =IF(AND($E18>0,I$6=$F18),$E18,0) -> 380 | J18: =IF(AND($E18>0,J$6=$F18),$E18,0) -> 0 | K18: =IF(AND($E18>0,K$6=$F18),$E18,0) -> 0 | L18: =IF(AND($E18>0,L$6=$F18),$E18,0) -> 0 | M18: =IF(AND($E18>0,M$6=$F18),$E18,0) -> 0 | N18: =IF(AND($E18>0,N$6=$F18),$E18,0) -> 0 | O18: =IF(AND($E18>0,O$6=$F18),$E18,0) -> 0 | P18: =IF(AND($E18>0,P$6=$F18),$E18,0) -> 0 | ... T18: =IF(AND($E18>0,T$6=$F18),$E18,0) -> 0 | U18: =IF(AND($G18>0,U$6=$H18),$G18,0) -> 0 | V18: =IF(AND($G18>0,V$6=$H18),$G18,0) -> 0 | W18: =IF(AND($G18>0,W$6=$H18),$G18,0) -> 0 | X18: =IF(AND($G18>0,X$6=$H18),$G18,0) -> 760 | Y18: =IF(AND($G18>0,Y$6=$H18),$G18,0) -> 0 | Z18: =IF(AND($G18>0,Z$6=$H18),$G18,0) -> 0 | AA18: =IF(AND($G18>0,AA$6=$H18),$G18,0) -> 0 | AB18: =IF(AND($G18>0,AB$6=$H18),$G18,0) -> 0 | ... AF18: =IF(AND($G18>0,AF$6=$H18),$G18,0) -> 0 | AG18: =$C18 -> 146.25 | AH18: =$C18 -> 146.25 | AI18: =$C18 -> 146.25 | AJ18: =$C18 -> 146.25 | AK18: =$C18 -> 146.25 | AL18: =$C18 -> 146.25 | AM18: =$C18 -> 146.25 | AN18: =$C18 -> 146.25 | ... AR18: =$C18 -> 146.25 | AS18: =$D18+I18+U18-AG18 -> 308.75 | AT18: =AS18+J18+V18-AH18 -> 162.5 | AU18: =AT18+K18+W18-AI18 -> 16.25 | AV18: =AU18+L18+X18-AJ18 -> 630 | AW18: =AV18+M18+Y18-AK18 -> 483.75 | AX18: =AW18+N18+Z18-AL18 -> 337.5 | AY18: =AX18+O18+AA18-AM18 -> 191.25 | AZ18: =AY18+P18+AB18-AN18 -> 45 | BA18: =AZ18+Q18+AC18-AO18 -> -101.25 | ... BD18: =BC18+T18+AF18-AR18 -> -540 | BE18: =IF(AS18<=0,1,0) -> 0 | BF18: =IF(AT18<=0,1,0) -> 0 | BG18: =IF(AU18<=0,1,0) -> 0 | BH18: =IF(AV18<=0,1,0) -> 0 | BI18: =IF(AW18<=0,1,0) -> 0 | BJ18: =IF(AX18<=0,1,0) -> 0 | BK18: =IF(AY18<=0,1,0) -> 0 | BL18: =IF(AZ18<=0,1,0) -> 0 | ... BP18: =IF(BD18<=0,1,0) -> 1 | BQ18: =IF(COUNTIF(BE18:BP18,1)=0,"None",MATCH(1,BE18:BP18,0)) -> 9 | BR18: =IF(COUNTIFS(BE$6:BP$6,"<="&$B18,BE18:BP18,1)>0,"YES","NO") -> NO | BS18: =MIN(AS18:BD18) -> -540
... A54: =Replenishment_Plan!A54 -> CLN-011 | B54: =Replenishment_Plan!K54 -> 1 | C54: =Replenishment_Plan!E54 -> 43.75 | D54: =Replenishment_Plan!O54-Replenishment_Plan!Q54 -> 102 | E54: =Replenishment_Plan!P54 -> 0 | F54: =Inputs!L87 -> 0 | G54: =Replenishment_Plan!AD54 -> 0 | H54: =IF(G54>0,B54+1,"none") -> none | I54: =IF(AND($E54>0,I$6=$F54),$E54,0) -> 0 | J54: =IF(AND($E54>0,J$6=$F54),$E54,0) -> 0 | K54: =IF(AND($E54>0,K$6=$F54),$E54,0) -> 0 | L54: =IF(AND($E54>0,L$6=$F54),$E54,0) -> 0 | M54: =IF(AND($E54>0,M$6=$F54),$E54,0) -> 0 | N54: =IF(AND($E54>0,N$6=$F54),$E54,0) -> 0 | O54: =IF(AND($E54>0,O$6=$F54),$E54,0) -> 0 | P54: =IF(AND($E54>0,P$6=$F54),$E54,0) -> 0 | ... T54: =IF(AND($E54>0,T$6=$F54),$E54,0) -> 0 | U54: =IF(AND($G54>0,U$6=$H54),$G54,0) -> 0 | V54: =IF(AND($G54>0,V$6=$H54),$G54,0) -> 0 | W54: =IF(AND($G54>0,W$6=$H54),$G54,0) -> 0 | X54: =IF(AND($G54>0,X$6=$H54),$G54,0) -> 0 | Y54: =IF(AND($G54>0,Y$6=$H54),$G54,0) -> 0 | Z54: =IF(AND($G54>0,Z$6=$H54),$G54,0) -> 0 | AA54: =IF(AND($G54>0,AA$6=$H54),$G54,0) -> 0 | AB54: =IF(AND($G54>0,AB$6=$H54),$G54,0) -> 0 | ... AF54: =IF(AND($G54>0,AF$6=$H54),$G54,0) -> 0 | AG54: =$C54 -> 43.75 | AH54: =$C54 -> 43.75 | AI54: =$C54 -> 43.75 | AJ54: =$C54 -> 43.75 | AK54: =$C54 -> 43.75 | AL54: =$C54 -> 43.75 | AM54: =$C54 -> 43.75 | AN54: =$C54 -> 43.75 | ... AR54: =$C54 -> 43.75 | AS54: =$D54+I54+U54-AG54 -> 58.25 | AT54: =AS54+J54+V54-AH54 -> 14.5 | AU54: =AT54+K54+W54-AI54 -> -29.25 | AV54: =AU54+L54+X54-AJ54 -> -73 | AW54: =AV54+M54+Y54-AK54 -> -116.75 | AX54: =AW54+N54+Z54-AL54 -> -160.5 | AY54: =AX54+O54+AA54-AM54 -> -204.25 | AZ54: =AY54+P54+AB54-AN54 -> -248 | BA54: =AZ54+Q54+AC54-AO54 -> -291.75 | ... BD54: =BC54+T54+AF54-AR54 -> -423 | BE54: =IF(AS54<=0,1,0) -> 0 | BF54: =IF(AT54<=0,1,0) -> 0 | BG54: =IF(AU54<=0,1,0) -> 1 | BH54: =IF(AV54<=0,1,0) -> 1 | BI54: =IF(AW54<=0,1,0) -> 1 | BJ54: =IF(AX54<=0,1,0) -> 1 | BK54: =IF(AY54<=0,1,0) -> 1 | BL54: =IF(AZ54<=0,1,0) -> 1 | ... BP54: =IF(BD54<=0,1,0) -> 1 | BQ54: =IF(COUNTIF(BE54:BP54,1)=0,"None",MATCH(1,BE54:BP54,0)) -> 3 | BR54: =IF(COUNTIFS(BE$6:BP$6,"<="&$B54,BE54:BP54,1)>0,"YES","NO") -> NO | BS54: =MIN(AS54:BD54) -> -423

Sheet SKU_Deep_Dive
A1: SKU Deep Dive: the complete planning chain for one SKU
A2: Pick a SKU in the yellow cell. Every result below is recalculated on this sheet from the displayed inputs and checked against Replenishment_Plan.
C4: Select SKU >> | D4: BTH-002
C5: Helper: row # in plan tables | D5: =MATCH($D$4,Replenishment_Plan!$A$7:$A$54,0) -> 12
C6: Helper: week-1 row in Demand_History | D6: =MATCH($D$4,Demand_History!$C:$C,0) -> 1146
C7: Helper: selected method # (1-4) | D7: =INDEX(Forecast!$AD$7:$AD$54,$D$5) -> 2
B9: A. SKU FACTS
C10: Product | D10: =INDEX(Replenishment_Plan!$B$7:$B$54,$D$5) -> Hand Towel 50x100 White | F10: STATUS | G10: =INDEX(Replenishment_Plan!$AG$7:$AG$54,$D$5) -> REORDER REQUIRED
C11: Supplier | D11: =INDEX(Inputs!$E$40:$E$87,$D$5)&" "&INDEX(Inputs!$B$31:$B$35,MATCH(INDEX(Inputs!$E$40:$E$87,$D$5),Inputs!$A$31:$A$35,0)) -> SUP-02 Alpina Bath & Textile AG | F11: Reason | G11: =INDEX(Replenishment_Plan!$AH$7:$AH$54,$D$5) -> Inventory position of 455 units is 24 units below the reorder point of 479 units. Replenishment is required. EOQ recommends approximately 755 units, rounded to 760 (case pack 20).
C12: Supplier lead time (weeks) | D12: =INDEX(Replenishment_Plan!$K$7:$K$54,$D$5) -> 3
C13: Unit cost (€) | D13: =INDEX(Replenishment_Plan!$V$7:$V$54,$D$5) -> 6
C14: Case pack (units) | D14: =INDEX(Replenishment_Plan!$AA$7:$AA$54,$D$5) -> 20
C15: Synthetic demand pattern | D15: =INDEX(Inputs!$N$40:$N$87,$D$5) -> stable
B17: B. FORECAST METHOD COMPARISON (walk-forward, evaluation window)
C18: Method | D18: WAPE | E18: Bias | F18: Forecast Error SD (units) | G18: Next-Week Forecast | H18: Within tolerance of best? | I18: Selected?
C19: Naive | D19: =INDEX(Forecast!$I$7:$I$54,$D$5) -> 0.10086382 | E19: =INDEX(Forecast!$M$7:$M$54,$D$5) -> 0.0017784553 | F19: =INDEX(Forecast!$Q$7:$Q$54,$D$5) -> 19.981477 | G19: =INDEX(Forecast!$U$7:$U$54,$D$5) -> 148 | H19: =IF(INDEX(Forecast!$Z$7:$Z$54,$D$5),"yes","no") -> no | I19: =IF($D$7=1,"<< SELECTED (first within tolerance, simplest first)","")
C20: MA4 | D20: =INDEX(Forecast!$J$7:$J$54,$D$5) -> 0.070915904 | E20: =INDEX(Forecast!$N$7:$N$54,$D$5) -> 0.00390625 | F20: =INDEX(Forecast!$R$7:$R$54,$D$5) -> 14.063496 | G20: =INDEX(Forecast!$V$7:$V$54,$D$5) -> 146.25 | H20: =IF(INDEX(Forecast!$AA$7:$AA$54,$D$5),"yes","no") -> yes | I20: =IF($D$7=2,"<< SELECTED (first within tolerance, simplest first)","") -> << SELECTED (first within tolerance, simplest first)
C21: MA8 | D21: =INDEX(Forecast!$K$7:$K$54,$D$5) -> 0.070296621 | E21: =INDEX(Forecast!$O$7:$O$54,$D$5) -> 0.0066533283 | F21: =INDEX(Forecast!$S$7:$S$54,$D$5) -> 13.872613 | G21: =INDEX(Forecast!$W$7:$W$54,$D$5) -> 148.125 | H21: =IF(INDEX(Forecast!$AB$7:$AB$54,$D$5),"yes","no") -> yes | I21: =IF($D$7=3,"<< SELECTED (first within tolerance, simplest first)","")
C22: SES | D22: =INDEX(Forecast!$L$7:$L$54,$D$5) -> 0.072404702 | E22: =INDEX(Forecast!$P$7:$P$54,$D$5) -> 0.004717227 | F22: =INDEX(Forecast!$T$7:$T$54,$D$5) -> 14.388641 | G22: =INDEX(Forecast!$X$7:$X$54,$D$5) -> 145.85158 | H22: =IF(INDEX(Forecast!$AC$7:$AC$54,$D$5),"yes","no") -> yes | I22: =IF($D$7=4,"<< SELECTED (first within tolerance, simplest first)","")
C23: Best WAPE / tolerance | D23: =MIN(D19:D22) -> 0.070296621 | E23: ="tolerance "&FIXED(WAPE_Tol*100,1)&" pts" -> tolerance 1.0 pts
C24: Eval window actual demand sum | D24: =SUM(INDEX(Forecast_Walkforward!$C:$C,$D$6+Eval_Start_Week-1):INDEX(Forecast_Walkforward!$C:$C,$D$6+Weeks_History-1)) -> 7872
C25: Selected method: sum |F-A| | D25: =SUM(INDEX(Forecast_Walkforward!$L:$O,$D$6+Eval_Start_Week-1,$D$7):INDEX(Forecast_Walkforward!$L:$O,$D$6+Weeks_History-1,$D$7)) -> 558.25
C26: Selected method: sum (F-A) | D26: =SUM(INDEX(Forecast_Walkforward!$H:$K,$D$6+Eval_Start_Week-1,$D$7):INDEX(Forecast_Walkforward!$H:$K,$D$6+Weeks_History-1,$D$7)) -> 30.75
C27: Number of weekly errors in window | D27: =COUNT(INDEX(Forecast_Walkforward!$H:$K,$D$6+Eval_Start_Week-1,$D$7):INDEX(Forecast_Walkforward!$H:$K,$D$6+Weeks_History-1,$D$7)) -> 52
B29: C. STEP-BY-STEP PLANNING CHAIN
B30: Step | C30: Calculation | D30: Formula in plain English | E30: Actual Excel formula (of the Result cell) | F30: Numbers substituted | G30: Result | H30: Unit | I30: Business interpretation | J30: Matches Replenishment_Plan?
B31: 1 | C31: Historical demand (evaluation window) | D31: Sum of actual weekly demand in the evaluation window | E31: =D24 | F31: ="Weeks "&Eval_Start_Week&"-"&Weeks_History&"; average "&FIXED(D24/Eval_Weeks,1)&" units per week" -> Weeks 53-104; average 151.4 units per week | G31: =D24 -> 7872 | H31: units | I31: ="The four methods are scored on these "&Eval_Weeks&" weeks. Each weekly forecast used only earlier weeks (walk-forward), so the scores are out-of-sample." -> The four methods are scored on these 52 weeks. Each weekly forecast used only earlier weeks (walk-forward), so the scores are out-of-sample. | J31: n/a
B32: 2 | C32: Selected forecast method | D32: Lowest WAPE; a simpler method wins if within the tolerance | E32: =INDEX(C19:C22,$D$7) | F32: ="Best WAPE "&FIXED(D23*100,1)&"%, tolerance "&FIXED(WAPE_Tol*100,1)&" pts" -> Best WAPE 7.0%, tolerance 1.0 pts | G32: =INDEX(C19:C22,$D$7) -> MA4 | I32: ="The first method in the order Naive, MA4, MA8, SES whose WAPE is within tolerance of the best is used for planning." -> The first method in the order Naive, MA4, MA8, SES whose WAPE is within tolerance of the best is used for planning. | J32: =IF(G32=INDEX(Replenishment_Plan!$D$7:$D$54,$D$5),"OK","MISMATCH") -> OK
B33: 3 | C33: Current weekly forecast | D33: =CHOOSE($D$7,"Naive: last actual (week 104)","4-week MA: AVERAGE of weeks 101-104","8-week MA: AVERAGE of weeks 97-104","SES: alpha x A(104) + (1-alpha) x F(104)") -> 4-week MA: AVERAGE of weeks 101-104 | E33: =INDEX(G19:G22,$D$7) | F33: =CHOOSE($D$7,"Actual week 104 = "&FIXED(INDEX(Demand_History!$D:$D,$D$6+104-1),0),"AVERAGE("&FIXED(INDEX(Demand_History!$D:$D,$D$6+101-1),0)&", "&FIXED(INDEX(Demand_History!$D:$D,$D$6+102-1),0)&", "&FIXED(INDEX(Demand_History!$D:$D,$D$6+103-1),0)&", "&FIXED(INDEX(Demand_History!$D:$D,$D$6+104-1),0)&")","AVERAGE("&FIXED(INDEX(Demand_History!$D:$D,$D$6+97-1),0)&", "&FIXED(INDEX(Demand_History!$D:$D,$D$6+98-1),0)&", "&FIXED(INDEX(Demand_History!$D:$D,$D$6+99-1),0)&", "&FIXED(INDEX(Demand_History!$D:$D,$D$6+100-1),0)&", "&FIXED(INDEX(Demand_History!$D:$D,$D$6+101-1),0)&", "&FIXED(INDEX(Demand_History!$D:$D,$D$6+102-1),0)&", "&FIXED(INDEX(Demand_History!$D:$D,$D$6+103-1),0)&", "&FIXED(INDEX(Demand_History!$D:$D,$D$6+104-1),0)&")",FIXED(SES_Alpha,2)&" x "&FIXED(INDEX(Demand_History!$D:$D,$D$6+104-1),0)&" + "&FIXED(1-SES_Alpha,2)&" x "&FIXED(INDEX(Forecast_Walkforward!$G:$G,$D$6+103),1)) -> AVERAGE(144, 157, 136, 148) | G33: =INDEX(G19:G22,$D$7) -> 146.25 | H33: units/week | I33: ="Expected demand of about "&FIXED(G33,1)&" units in each of the next 12 weeks (all four methods give a flat forecast)." -> Expected demand of about 146.3 units in each of the next 12 weeks (all four methods give a flat forecast). | J33: =IF(ABS(G33-INDEX(Replenishment_Plan!$E$7:$E$54,$D$5))<0.0001,"OK","MISMATCH") -> OK
B34: 4 | C34: WAPE | D34: SUM(|Forecast - Actual|) / SUM(Actual) | E34: =D25/D24 | F34: =FIXED(D25,0)&" / "&FIXED(D24,0) -> 558 / 7,872 | G34: =D25/D24 -> 0.070915904 | H34: % | I34: ="On average the forecast misses by "&FIXED(G34*100,1)&"% of actual volume, ignoring direction. Volume-weighted, so zero-demand weeks do not break it (unlike MAPE)." -> On average the forecast misses by 7.1% of actual volume, ignoring direction. Volume-weighted, so zero-demand weeks do not break it (unlike MAPE). | J34: =IF(ABS(G34-INDEX(Replenishment_Plan!$F$7:$F$54,$D$5))<0.000001,"OK","MISMATCH") -> OK
B35: 5 | C35: Forecast bias | D35: SUM(Forecast - Actual) / SUM(Actual) | E35: =D26/D24 | F35: =FIXED(D26,0)&" / "&FIXED(D24,0) -> 31 / 7,872 | G35: =D26/D24 -> 0.00390625 | H35: % | I35: =IF(G35>0,"Positive: on balance the method over-forecast by "&FIXED(G35*100,1)&"%.",IF(G35<0,"Negative: on balance the method under-forecast by "&FIXED(-G35*100,1)&"%.","No net bias."))&" WAPE = size of misses, Bias = direction." -> Positive: on balance the method over-forecast by 0.4%. WAPE = size of misses, Bias = direction. | J35: =IF(ABS(G35-INDEX(Replenishment_Plan!$G$7:$G$54,$D$5))<0.000001,"OK","MISMATCH") -> OK
B36: 6 | C36: Forecast error standard deviation | D36: STDEV.S of the weekly errors (Forecast - Actual) in the window | E36: =_xlfn.STDEV.S(INDEX(Forecast_Walkforward!$H:$K,$D$6+Eval_Start_Week-1,$D$7):INDEX(Forecast_Walkforward!$H:$K,$D$6+Weeks_History-1,$D$7)) | F36: ="STDEV.S of "&D27&" errors; mean error "&FIXED(D26/D27,1)&" units" -> STDEV.S of 52 errors; mean error 0.6 units | G36: =_xlfn.STDEV.S(INDEX(Forecast_Walkforward!$H:$K,$D$6+Eval_Start_Week-1,$D$7):INDEX(Forecast_Walkforward!$H:$K,$D$6+Weeks_History-1,$D$7)) -> 14.063496 | H36: units | I36: ="A typical weekly forecast miss is about "&FIXED(G36,1)&" units. The bigger the typical miss, the more safety stock is needed." -> A typical weekly forecast miss is about 14.1 units. The bigger the typical miss, the more safety stock is needed. | J36: =IF(ABS(G36-INDEX(Replenishment_Plan!$H$7:$H$54,$D$5))<0.0001,"OK","MISMATCH") -> OK
B37: 7 | C37: Target service level | D37: Input on the Inputs sheet | E37: =TSL | F37: ="Input" -> Input | G37: =TSL -> 0.95 | H37: % | I37: ="Aim: no stockout during lead time in about "&FIXED(G37*100,1)&"% of replenishment cycles." -> Aim: no stockout during lead time in about 95.0% of replenishment cycles. | J37: n/a
B38: 8 | C38: z-value | D38: NORM.S.INV(Target Service Level) | E38: =_xlfn.NORM.S.INV(G37) | F38: ="NORM.S.INV("&FIXED(G37,3)&")" -> NORM.S.INV(0.950) | G38: =_xlfn.NORM.S.INV(G37) -> 1.6448536 | I38: ="Safety stock protects against forecast errors up to "&FIXED(G38,3)&" standard deviations." -> Safety stock protects against forecast errors up to 1.645 standard deviations. | J38: =IF(ABS(G38-INDEX(Replenishment_Plan!$J$7:$J$54,$D$5))<0.000001,"OK","MISMATCH") -> OK
B39: 9 | C39: Supplier lead time | D39: Fixed lead time of the supplier | E39: =INDEX(Replenishment_Plan!$K$7:$K$54,$D$5) | F39: ="Supplier "&INDEX(Replenishment_Plan!$C$7:$C$54,$D$5) -> Supplier SUP-02 | G39: =INDEX(Replenishment_Plan!$K$7:$K$54,$D$5) -> 3 | H39: weeks | I39: ="Weeks from placing an order until the goods can be used. Assumed fixed (no lead-time variability in V1)." -> Weeks from placing an order until the goods can be used. Assumed fixed (no lead-time variability in V1). | J39: n/a
B40: 10 | C40: Safety stock | D40: z x Forecast Error SD x SQRT(Lead Time) | E40: =G38*G36*SQRT(G39) | F40: =FIXED(G38,3)&" x "&FIXED(G36,1)&" x SQRT("&G39&")" -> 1.645 x 14.1 x SQRT(3) | G40: =G38*G36*SQRT(G39) -> 40.06648 | H40: units | I40: ="A buffer of about "&FIXED(G40,0)&" units against forecast error over the "&G39&"-week lead time." -> A buffer of about 40 units against forecast error over the 3-week lead time. | J40: =IF(ABS(G40-INDEX(Replenishment_Plan!$L$7:$L$54,$D$5))<0.0001,"OK","MISMATCH") -> OK
B41: 11 | C41: Lead-time demand | D41: Weekly Forecast x Lead Time | E41: =G33*G39 | F41: =FIXED(G33,1)&" x "&G39 -> 146.3 x 3 | G41: =G33*G39 -> 438.75 | H41: units | I41: ="Expected customer demand of about "&FIXED(G41,0)&" units while waiting for a new order to arrive." -> Expected customer demand of about 439 units while waiting for a new order to arrive. | J41: =IF(ABS(G41-INDEX(Replenishment_Plan!$M$7:$M$54,$D$5))<0.0001,"OK","MISMATCH") -> OK
B42: 12 | C42: Reorder point (WHEN) | D42: Lead-Time Demand + Safety Stock | E42: =G41+G40 | F42: =FIXED(G41,1)&" + "&FIXED(G40,1) -> 438.8 + 40.1 | G42: =G41+G40 -> 478.81648 | H42: units | I42: ="When inventory position reaches about "&FIXED(G42,0)&" units or less, replenishment should be triggered." -> When inventory position reaches about 479 units or less, replenishment should be triggered. | J42: =IF(ABS(G42-INDEX(Replenishment_Plan!$N$7:$N$54,$D$5))<0.0001,"OK","MISMATCH") -> OK
B43: 13 | C43: On hand | D43: Physical stock in the warehouse | E43: =INDEX(Replenishment_Plan!$O$7:$O$54,$D$5) | F43: ="Input" -> Input | G43: =INDEX(Replenishment_Plan!$O$7:$O$54,$D$5) -> 75 | H43: units | I43: ="Stock that can ship today." -> Stock that can ship today. | J43: n/a
B44: 14 | C44: + On order | D44: Open purchase order quantity | E44: =INDEX(Replenishment_Plan!$P$7:$P$54,$D$5) | F44: =IF(G44>0,"Open PO due in week "&INDEX(Inputs!$L$40:$L$87,$D$5),"No open PO") -> Open PO due in week 1 | G44: =INDEX(Replenishment_Plan!$P$7:$P$54,$D$5) -> 380 | H44: units | I44: ="Already ordered but not yet received. Counting it prevents a duplicate order just because shelves look low." -> Already ordered but not yet received. Counting it prevents a duplicate order just because shelves look low. | J44: n/a
B45: 15 | C45: - Backorders | D45: Customer demand already owed | E45: =INDEX(Replenishment_Plan!$Q$7:$Q$54,$D$5) | F45: ="Input" -> Input | G45: =INDEX(Replenishment_Plan!$Q$7:$Q$54,$D$5) -> 0 | H45: units | I45: ="Owed to customers, so it will consume the next stock that arrives." -> Owed to customers, so it will consume the next stock that arrives. | J45: n/a
B46: 16 | C46: Inventory position | D46: On Hand + On Order - Backorders | E46: =G43+G44-G45 | F46: =FIXED(G43,0)&" + "&FIXED(G44,0)&" - "&FIXED(G45,0) -> 75 + 380 - 0 | G46: =G43+G44-G45 -> 455 | H46: units | I46: ="Stock available or already on its way, net of what is owed: "&FIXED(G46,0)&" units. This, not on-hand stock, is compared with the reorder point." -> Stock available or already on its way, net of what is owed: 455 units. This, not on-hand stock, is compared with the reorder point. | J46: =IF(ABS(G46-INDEX(Replenishment_Plan!$R$7:$R$54,$D$5))<0.0001,"OK","MISMATCH") -> OK
B47: 17 | C47: Reorder decision | D47: Is Inventory Position <= Reorder Point? | E47: =IF(G46<=G42,"YES","NO") | F47: =FIXED(G46,0)&" <= "&FIXED(G42,1)&" ?" -> 455 <= 478.8 ? | G47: =IF(G46<=G42,"YES","NO") -> YES | I47: =IF(G47="YES","Inventory position is "&FIXED(G42-G46,0)&" units at or below the reorder point: place an order now.","Inventory position is "&FIXED(G46-G42,0)&" units above the reorder point: no order yet.") -> Inventory position is 24 units at or below the reorder point: place an order now. | J47: =IF(G47=INDEX(Replenishment_Plan!$AC$7:$AC$54,$D$5),"OK","MISMATCH") -> OK
B48: 18 | C48: Annual forecast demand | D48: Weekly Forecast x 52 | E48: =G33*Weeks_Per_Year | F48: =FIXED(G33,1)&" x "&Weeks_Per_Year -> 146.3 x 52 | G48: =G33*Weeks_Per_Year -> 7605 | H48: units/year | I48: ="Annualised demand needed for the EOQ trade-off (orders per year = annual demand / order size)." -> Annualised demand needed for the EOQ trade-off (orders per year = annual demand / order size). | J48: =IF(ABS(G48-INDEX(Replenishment_Plan!$U$7:$U$54,$D$5))<0.0001,"OK","MISMATCH") -> OK
B49: 19 | C49: Ordering cost per order | D49: Supplier input | E49: =INDEX(Replenishment_Plan!$W$7:$W$54,$D$5) | F49: ="Input (Suppliers table)" -> Input (Suppliers table) | G49: =INDEX(Replenishment_Plan!$W$7:$W$54,$D$5) -> 45 | H49: €/order | I49: ="Fixed cost of placing and receiving one order (admin, freight handling, goods receipt)." -> Fixed cost of placing and receiving one order (admin, freight handling, goods receipt). | J49: n/a
B50: 20 | C50: Annual holding cost per unit | D50: Unit Cost x Annual Holding Rate | E50: =INDEX(Replenishment_Plan!$V$7:$V$54,$D$5)*Holding_Rate | F50: ="€"&FIXED(INDEX(Replenishment_Plan!$V$7:$V$54,$D$5),2)&" x "&FIXED(Holding_Rate*100,1)&"%" -> €6.00 x 20.0% | G50: =INDEX(Replenishment_Plan!$V$7:$V$54,$D$5)*Holding_Rate -> 1.2 | H50: €/unit/year | I50: ="Keeping one unit in stock for a year costs about €"&FIXED(G50,2)&" (capital, storage, risk)." -> Keeping one unit in stock for a year costs about €1.20 (capital, storage, risk). | J50: =IF(ABS(G50-INDEX(Replenishment_Plan!$Y$7:$Y$54,$D$5))<0.0001,"OK","MISMATCH") -> OK
B51: 21 | C51: Economic order quantity (HOW MUCH) | D51: SQRT((2 x Annual Demand x Ordering Cost) / Annual Holding Cost per Unit) | E51: =SQRT((2*G48*G49)/G50) | F51: ="SQRT((2 x "&FIXED(G48,0)&" x "&FIXED(G49,2)&") / "&FIXED(G50,2)&")" -> SQRT((2 x 7,605 x 45.00) / 1.20) | G51: =SQRT((2*G48*G49)/G50) -> 755.23175 | H51: units | I51: ="EOQ suggests ordering approximately "&FIXED(G51,0)&" units (about "&FIXED(G51/G33,1)&" weeks of demand) when replenishment is triggered, balancing ordering cost against holding cost." -> EOQ suggests ordering approximately 755 units (about 5.2 weeks of demand) when replenishment is triggered, balancing ordering cost against holding cost. | J51: =IF(ABS(G51-INDEX(Replenishment_Plan!$Z$7:$Z$54,$D$5))<0.0001,"OK","MISMATCH") -> OK
B52: 22 | C52: EOQ rounded to case pack | D52: ROUNDUP(EOQ / Case Pack) x Case Pack | E52: =ROUNDUP(G51/INDEX(Replenishment_Plan!$AA$7:$AA$54,$D$5),0)*INDEX(Replenishment_Plan!$AA$7:$AA$54,$D$5) | F52: ="ROUNDUP("&FIXED(G51,1)&" / "&INDEX(Replenishment_Plan!$AA$7:$AA$54,$D$5)&") x "&INDEX(Replenishment_Plan!$AA$7:$AA$54,$D$5) -> ROUNDUP(755.2 / 20) x 20 | G52: =ROUNDUP(G51/INDEX(Replenishment_Plan!$AA$7:$AA$54,$D$5),0)*INDEX(Replenishment_Plan!$AA$7:$AA$54,$D$5) -> 760 | H52: units | I52: ="Suppliers ship full cases, so EOQ is rounded up to the next full case." -> Suppliers ship full cases, so EOQ is rounded up to the next full case. | J52: =IF(ABS(G52-INDEX(Replenishment_Plan!$AB$7:$AB$54,$D$5))<0.0001,"OK","MISMATCH") -> OK
B53: 23 | C53: Recommended order | D53: IF Reorder Trigger = YES THEN rounded EOQ ELSE 0 | E53: =IF(G47="YES",G52,0) | F53: ="Trigger "&G47&" -> "&FIXED(G53,0) -> Trigger YES -> 760 | G53: =IF(G47="YES",G52,0) -> 760 | H53: units | I53: =IF(G53>0,"Order "&FIXED(G53,0)&" units now; with a "&G39&"-week lead time it is received at the start of week "&(G39+1)&".","No order recommended this week.") -> Order 760 units now; with a 3-week lead time it is received at the start of week 4. | J53: =IF(ABS(G53-INDEX(Replenishment_Plan!$AD$7:$AD$54,$D$5))<0.0001,"OK","MISMATCH") -> OK
B54: 24 | C54: Weeks of cover | D54: Inventory Position / Weekly Forecast | E54: =IF(G33>0,G46/G33,0) | F54: =FIXED(G46,0)&" / "&FIXED(G33,1) -> 455 / 146.3 | G54: =IF(G33>0,G46/G33,0) -> 3.1111111 | H54: weeks | I54: ="Inventory position lasts about "&FIXED(G54,1)&" weeks at forecast demand (excess threshold "&Excess_WoC&" weeks). On-hand alone covers "&FIXED(G43/G33,1)&" weeks." -> Inventory position lasts about 3.1 weeks at forecast demand (excess threshold 12 weeks). On-hand alone covers 0.5 weeks. | J54: =IF(ABS(G54-INDEX(Replenishment_Plan!$S$7:$S$54,$D$5))<0.0001,"OK","MISMATCH") -> OK
B55: 25 | C55: Projected inventory, end of week 12 | D55: Opening + receipts - forecast demand, week by week (table D) | E55: =J71 | F55: ="First projected week at or below zero: "&INDEX(Replenishment_Plan!$AE$7:$AE$54,$D$5) -> First projected week at or below zero: 9 | G55: =J71 -> -540 | H55: units | I55: =IF(INDEX(Replenishment_Plan!$AF$7:$AF$54,$D$5)="YES","Stock is projected to run out within the lead time, before a new order could arrive.",IF(ISNUMBER(INDEX(Replenishment_Plan!$AE$7:$AE$54,$D$5)),"Projected zero in week "&INDEX(Replenishment_Plan!$AE$7:$AE$54,$D$5)&", after the lead time: the next weekly review will trigger an order before then.","Projected inventory stays above zero for 12 weeks.")) -> Projected zero in week 9, after the lead time: the next weekly review will trigger an order before then. | J55: =IF(ABS(G55-INDEX(Projection!$BD$7:$BD$54,$D$5))<0.0001,"OK","MISMATCH") -> OK
B56: 26 | C56: Planning status | D56: STOCKOUT RISK -> REORDER REQUIRED -> EXCESS STOCK -> HEALTHY | E56: =INDEX(Replenishment_Plan!$AG$7:$AG$54,$D$5) | F56: ="See reason in section A" -> See reason in section A | G56: =INDEX(Replenishment_Plan!$AG$7:$AG$54,$D$5) -> REORDER REQUIRED | I56: =INDEX(Replenishment_Plan!$AH$7:$AH$54,$D$5) -> Inventory position of 455 units is 24 units below the reorder point of 479 units. Replenishment is required. EOQ recommends approximately 755 units, rounded to 760 (case pack 20). | J56: n/a
B58: D. 12-WEEK PROJECTED INVENTORY (existing PO + recommended order + flat forecast)
C59: Planning week (receipts at start of week) | D59: Model week | E59: Week start date | F59: Opening inventory | G59: Existing PO receipt | H59: New order receipt | I59: Forecast demand | J59: Closing inventory | K59: Safety stock | L59: Reorder point
C60: 1 | D60: =Weeks_History+C60 -> 105 | E60: =Snapshot_Date+7*(C60-1) -> 46202 | F60: =G43-G45 -> 75 | G60: =INDEX(Projection!$I$7:$T$54,$D$5,C60) -> 380 | H60: =INDEX(Projection!$U$7:$AF$54,$D$5,C60) -> 0 | I60: =G33 -> 146.25 | J60: =F60+G60+H60-I60 -> 308.75 | K60: =G40 -> 40.06648 | L60: =G42 -> 478.81648
C61: 2 | D61: =Weeks_History+C61 -> 106 | E61: =Snapshot_Date+7*(C61-1) -> 46209 | F61: =J60 -> 308.75 | G61: =INDEX(Projection!$I$7:$T$54,$D$5,C61) -> 0 | H61: =INDEX(Projection!$U$7:$AF$54,$D$5,C61) -> 0 | I61: =G33 -> 146.25 | J61: =F61+G61+H61-I61 -> 162.5 | K61: =G40 -> 40.06648 | L61: =G42 -> 478.81648
C62: 3 | D62: =Weeks_History+C62 -> 107 | E62: =Snapshot_Date+7*(C62-1) -> 46216 | F62: =J61 -> 162.5 | G62: =INDEX(Projection!$I$7:$T$54,$D$5,C62) -> 0 | H62: =INDEX(Projection!$U$7:$AF$54,$D$5,C62) -> 0 | I62: =G33 -> 146.25 | J62: =F62+G62+H62-I62 -> 16.25 | K62: =G40 -> 40.06648 | L62: =G42 -> 478.81648
C63: 4 | D63: =Weeks_History+C63 -> 108 | E63: =Snapshot_Date+7*(C63-1) -> 46223 | F63: =J62 -> 16.25 | G63: =INDEX(Projection!$I$7:$T$54,$D$5,C63) -> 0 | H63: =INDEX(Projection!$U$7:$AF$54,$D$5,C63) -> 760 | I63: =G33 -> 146.25 | J63: =F63+G63+H63-I63 -> 630 | K63: =G40 -> 40.06648 | L63: =G42 -> 478.81648
C64: 5 | D64: =Weeks_History+C64 -> 109 | E64: =Snapshot_Date+7*(C64-1) -> 46230 | F64: =J63 -> 630 | G64: =INDEX(Projection!$I$7:$T$54,$D$5,C64) -> 0 | H64: =INDEX(Projection!$U$7:$AF$54,$D$5,C64) -> 0 | I64: =G33 -> 146.25 | J64: =F64+G64+H64-I64 -> 483.75 | K64: =G40 -> 40.06648 | L64: =G42 -> 478.81648
C65: 6 | D65: =Weeks_History+C65 -> 110 | E65: =Snapshot_Date+7*(C65-1) -> 46237 | F65: =J64 -> 483.75 | G65: =INDEX(Projection!$I$7:$T$54,$D$5,C65) -> 0 | H65: =INDEX(Projection!$U$7:$AF$54,$D$5,C65) -> 0 | I65: =G33 -> 146.25 | J65: =F65+G65+H65-I65 -> 337.5 | K65: =G40 -> 40.06648 | L65: =G42 -> 478.81648
C66: 7 | D66: =Weeks_History+C66 -> 111 | E66: =Snapshot_Date+7*(C66-1) -> 46244 | F66: =J65 -> 337.5 | G66: =INDEX(Projection!$I$7:$T$54,$D$5,C66) -> 0 | H66: =INDEX(Projection!$U$7:$AF$54,$D$5,C66) -> 0 | I66: =G33 -> 146.25 | J66: =F66+G66+H66-I66 -> 191.25 | K66: =G40 -> 40.06648 | L66: =G42 -> 478.81648
C67: 8 | D67: =Weeks_History+C67 -> 112 | E67: =Snapshot_Date+7*(C67-1) -> 46251 | F67: =J66 -> 191.25 | G67: =INDEX(Projection!$I$7:$T$54,$D$5,C67) -> 0 | H67: =INDEX(Projection!$U$7:$AF$54,$D$5,C67) -> 0 | I67: =G33 -> 146.25 | J67: =F67+G67+H67-I67 -> 45 | K67: =G40 -> 40.06648 | L67: =G42 -> 478.81648
C68: 9 | D68: =Weeks_History+C68 -> 113 | E68: =Snapshot_Date+7*(C68-1) -> 46258 | F68: =J67 -> 45 | G68: =INDEX(Projection!$I$7:$T$54,$D$5,C68) -> 0 | H68: =INDEX(Projection!$U$7:$AF$54,$D$5,C68) -> 0 | I68: =G33 -> 146.25 | J68: =F68+G68+H68-I68 -> -101.25 | K68: =G40 -> 40.06648 | L68: =G42 -> 478.81648
C69: 10 | D69: =Weeks_History+C69 -> 114 | E69: =Snapshot_Date+7*(C69-1) -> 46265 | F69: =J68 -> -101.25 | G69: =INDEX(Projection!$I$7:$T$54,$D$5,C69) -> 0 | H69: =INDEX(Projection!$U$7:$AF$54,$D$5,C69) -> 0 | I69: =G33 -> 146.25 | J69: =F69+G69+H69-I69 -> -247.5 | K69: =G40 -> 40.06648 | L69: =G42 -> 478.81648
C70: 11 | D70: =Weeks_History+C70 -> 115 | E70: =Snapshot_Date+7*(C70-1) -> 46272 | F70: =J69 -> -247.5 | G70: =INDEX(Projection!$I$7:$T$54,$D$5,C70) -> 0 | H70: =INDEX(Projection!$U$7:$AF$54,$D$5,C70) -> 0 | I70: =G33 -> 146.25 | J70: =F70+G70+H70-I70 -> -393.75 | K70: =G40 -> 40.06648 | L70: =G42 -> 478.81648
C71: 12 | D71: =Weeks_History+C71 -> 116 | E71: =Snapshot_Date+7*(C71-1) -> 46279 | F71: =J70 -> -393.75 | G71: =INDEX(Projection!$I$7:$T$54,$D$5,C71) -> 0 | H71: =INDEX(Projection!$U$7:$AF$54,$D$5,C71) -> 0 | I71: =G33 -> 146.25 | J71: =F71+G71+H71-I71 -> -540 | K71: =G40 -> 40.06648 | L71: =G42 -> 478.81648
B73: E. PLANNING CHART: last 26 weeks of history, 12-week forward view
B100: F. LAST 26 WEEKS: actual demand and walk-forward forecasts
C101: Model week | D101: Week start date | E101: Actual demand | F101: Naive | G101: MA4 | H101: MA8 | I101: SES | J101: Selected method forecast | K101: Error (F-A)
C102: 79 | D102: =INDEX(Demand_History!$B:$B,$D$6+C102-1) -> 46020 | E102: =INDEX(Demand_History!$D:$D,$D$6+C102-1) -> 182 | F102: =INDEX(Forecast_Walkforward!$D:$D,$D$6+C102-1) -> 150 | G102: =INDEX(Forecast_Walkforward!$E:$E,$D$6+C102-1) -> 157.75 | H102: =INDEX(Forecast_Walkforward!$F:$F,$D$6+C102-1) -> 158.375 | I102: =INDEX(Forecast_Walkforward!$G:$G,$D$6+C102-1) -> 157.4873 | J102: =INDEX(F102:I102,$D$7) -> 157.75 | K102: =J102-E102 -> -24.25
C103: 80 | D103: =INDEX(Demand_History!$B:$B,$D$6+C103-1) -> 46027 | E103: =INDEX(Demand_History!$D:$D,$D$6+C103-1) -> 137 | F103: =INDEX(Forecast_Walkforward!$D:$D,$D$6+C103-1) -> 182 | G103: =INDEX(Forecast_Walkforward!$E:$E,$D$6+C103-1) -> 164.5 | H103: =INDEX(Forecast_Walkforward!$F:$F,$D$6+C103-1) -> 162.5 | I103: =INDEX(Forecast_Walkforward!$G:$G,$D$6+C103-1) -> 164.84111 | J103: =INDEX(F103:I103,$D$7) -> 164.5 | K103: =J103-E103 -> 27.5
C104: 81 | D104: =INDEX(Demand_History!$B:$B,$D$6+C104-1) -> 46034 | E104: =INDEX(Demand_History!$D:$D,$D$6+C104-1) -> 160 | F104: =INDEX(Forecast_Walkforward!$D:$D,$D$6+C104-1) -> 137 | G104: =INDEX(Forecast_Walkforward!$E:$E,$D$6+C104-1) -> 160 | H104: =INDEX(Forecast_Walkforward!$F:$F,$D$6+C104-1) -> 156.75 | I104: =INDEX(Forecast_Walkforward!$G:$G,$D$6+C104-1) -> 156.48878 | J104: =INDEX(F104:I104,$D$7) -> 160 | K104: =J104-E104 -> 0
C105: 82 | D105: =INDEX(Demand_History!$B:$B,$D$6+C105-1) -> 46041 | E105: =INDEX(Demand_History!$D:$D,$D$6+C105-1) -> 135 | F105: =INDEX(Forecast_Walkforward!$D:$D,$D$6+C105-1) -> 160 | G105: =INDEX(Forecast_Walkforward!$E:$E,$D$6+C105-1) -> 157.25 | H105: =INDEX(Forecast_Walkforward!$F:$F,$D$6+C105-1) -> 157.375 | I105: =INDEX(Forecast_Walkforward!$G:$G,$D$6+C105-1) -> 157.54214 | J105: =INDEX(F105:I105,$D$7) -> 157.25 | K105: =J105-E105 -> 22.25
C106: 83 | D106: =INDEX(Demand_History!$B:$B,$D$6+C106-1) -> 46048 | E106: =INDEX(Demand_History!$D:$D,$D$6+C106-1) -> 177 | F106: =INDEX(Forecast_Walkforward!$D:$D,$D$6+C106-1) -> 135 | G106: =INDEX(Forecast_Walkforward!$E:$E,$D$6+C106-1) -> 153.5 | H106: =INDEX(Forecast_Walkforward!$F:$F,$D$6+C106-1) -> 155.625 | I106: =INDEX(Forecast_Walkforward!$G:$G,$D$6+C106-1) -> 150.7795 | J106: =INDEX(F106:I106,$D$7) -> 153.5 | K106: =J106-E106 -> -23.5
C107: 84 | D107: =INDEX(Demand_History!$B:$B,$D$6+C107-1) -> 46055 | E107: =INDEX(Demand_History!$D:$D,$D$6+C107-1) -> 145 | F107: =INDEX(Forecast_Walkforward!$D:$D,$D$6+C107-1) -> 177 | G107: =INDEX(Forecast_Walkforward!$E:$E,$D$6+C107-1) -> 152.25 | H107: =INDEX(Forecast_Walkforward!$F:$F,$D$6+C107-1) -> 158.375 | I107: =INDEX(Forecast_Walkforward!$G:$G,$D$6+C107-1) -> 158.64565 | J107: =INDEX(F107:I107,$D$7) -> 152.25 | K107: =J107-E107 -> 7.25
C108: 85 | D108: =INDEX(Demand_History!$B:$B,$D$6+C108-1) -> 46062 | E108: =INDEX(Demand_History!$D:$D,$D$6+C108-1) -> 149 | F108: =INDEX(Forecast_Walkforward!$D:$D,$D$6+C108-1) -> 145 | G108: =INDEX(Forecast_Walkforward!$E:$E,$D$6+C108-1) -> 154.25 | H108: =INDEX(Forecast_Walkforward!$F:$F,$D$6+C108-1) -> 157.125 | I108: =INDEX(Forecast_Walkforward!$G:$G,$D$6+C108-1) -> 154.55195 | J108: =INDEX(F108:I108,$D$7) -> 154.25 | K108: =J108-E108 -> 5.25
C109: 86 | D109: =INDEX(Demand_History!$B:$B,$D$6+C109-1) -> 46069 | E109: =INDEX(Demand_History!$D:$D,$D$6+C109-1) -> 164 | F109: =INDEX(Forecast_Walkforward!$D:$D,$D$6+C109-1) -> 149 | G109: =INDEX(Forecast_Walkforward!$E:$E,$D$6+C109-1) -> 151.5 | H109: =INDEX(Forecast_Walkforward!$F:$F,$D$6+C109-1) -> 154.375 | I109: =INDEX(Forecast_Walkforward!$G:$G,$D$6+C109-1) -> 152.88637 | J109: =INDEX(F109:I109,$D$7) -> 151.5 | K109: =J109-E109 -> -12.5
C110: 87 | D110: =INDEX(Demand_History!$B:$B,$D$6+C110-1) -> 46076 | E110: =INDEX(Demand_History!$D:$D,$D$6+C110-1) -> 169 | F110: =INDEX(Forecast_Walkforward!$D:$D,$D$6+C110-1) -> 164 | G110: =INDEX(Forecast_Walkforward!$E:$E,$D$6+C110-1) -> 158.75 | H110: =INDEX(Forecast_Walkforward!$F:$F,$D$6+C110-1) -> 156.125 | I110: =INDEX(Forecast_Walkforward!$G:$G,$D$6+C110-1) -> 156.22046 | J110: =INDEX(F110:I110,$D$7) -> 158.75 | K110: =J110-E110 -> -10.25
C111: 88 | D111: =INDEX(Demand_History!$B:$B,$D$6+C111-1) -> 46083 | E111: =INDEX(Demand_History!$D:$D,$D$6+C111-1) -> 133 | F111: =INDEX(Forecast_Walkforward!$D:$D,$D$6+C111-1) -> 169 | G111: =INDEX(Forecast_Walkforward!$E:$E,$D$6+C111-1) -> 156.75 | H111: =INDEX(Forecast_Walkforward!$F:$F,$D$6+C111-1) -> 154.5 | I111: =INDEX(Forecast_Walkforward!$G:$G,$D$6+C111-1) -> 160.05432 | J111: =INDEX(F111:I111,$D$7) -> 156.75 | K111: =J111-E111 -> 23.75
C112: 89 | D112: =INDEX(Demand_History!$B:$B,$D$6+C112-1) -> 46090 | E112: =INDEX(Demand_History!$D:$D,$D$6+C112-1) -> 145 | F112: =INDEX(Forecast_Walkforward!$D:$D,$D$6+C112-1) -> 133 | G112: =INDEX(Forecast_Walkforward!$E:$E,$D$6+C112-1) -> 153.75 | H112: =INDEX(Forecast_Walkforward!$F:$F,$D$6+C112-1) -> 154 | I112: =INDEX(Forecast_Walkforward!$G:$G,$D$6+C112-1) -> 151.93802 | J112: =INDEX(F112:I112,$D$7) -> 153.75 | K112: =J112-E112 -> 8.75
C113: 90 | D113: =INDEX(Demand_History!$B:$B,$D$6+C113-1) -> 46097 | E113: =INDEX(Demand_History!$D:$D,$D$6+C113-1) -> 129 | F113: =INDEX(Forecast_Walkforward!$D:$D,$D$6+C113-1) -> 145 | G113: =INDEX(Forecast_Walkforward!$E:$E,$D$6+C113-1) -> 152.75 | H113: =INDEX(Forecast_Walkforward!$F:$F,$D$6+C113-1) -> 152.125 | I113: =INDEX(Forecast_Walkforward!$G:$G,$D$6+C113-1) -> 149.85662 | J113: =INDEX(F113:I113,$D$7) -> 152.75 | K113: =J113-E113 -> 23.75
... C127: 104 | D127: =INDEX(Demand_History!$B:$B,$D$6+C127-1) -> 46195 | E127: =INDEX(Demand_History!$D:$D,$D$6+C127-1) -> 148 | F127: =INDEX(Forecast_Walkforward!$D:$D,$D$6+C127-1) -> 136 | G127: =INDEX(Forecast_Walkforward!$E:$E,$D$6+C127-1) -> 146.25 | H127: =INDEX(Forecast_Walkforward!$F:$F,$D$6+C127-1) -> 147 | I127: =INDEX(Forecast_Walkforward!$G:$G,$D$6+C127-1) -> 144.93083 | J127: =INDEX(F127:I127,$D$7) -> 146.25 | K127: =J127-E127 -> -1.75
B129: G. CHART DATA (feeds the chart in section E)
C130: Model week | D130: Projected inventory | E130: Safety stock | F130: Reorder point | G130: Forward forecast
C131: 104 | D131: =F60 -> 75 | E131: =G40 -> 40.06648 | F131: =G42 -> 478.81648 | G131: =G33 -> 146.25 | H131: Week 104 row = opening net inventory at the snapshot
C132: 105 | D132: =J60 -> 308.75 | E132: =G40 -> 40.06648 | F132: =G42 -> 478.81648 | G132: =G33 -> 146.25
C133: 106 | D133: =J61 -> 162.5 | E133: =G40 -> 40.06648 | F133: =G42 -> 478.81648 | G133: =G33 -> 146.25
C134: 107 | D134: =J62 -> 16.25 | E134: =G40 -> 40.06648 | F134: =G42 -> 478.81648 | G134: =G33 -> 146.25
C135: 108 | D135: =J63 -> 630 | E135: =G40 -> 40.06648 | F135: =G42 -> 478.81648 | G135: =G33 -> 146.25
C136: 109 | D136: =J64 -> 483.75 | E136: =G40 -> 40.06648 | F136: =G42 -> 478.81648 | G136: =G33 -> 146.25
C137: 110 | D137: =J65 -> 337.5 | E137: =G40 -> 40.06648 | F137: =G42 -> 478.81648 | G137: =G33 -> 146.25
C138: 111 | D138: =J66 -> 191.25 | E138: =G40 -> 40.06648 | F138: =G42 -> 478.81648 | G138: =G33 -> 146.25
C139: 112 | D139: =J67 -> 45 | E139: =G40 -> 40.06648 | F139: =G42 -> 478.81648 | G139: =G33 -> 146.25
C140: 113 | D140: =J68 -> -101.25 | E140: =G40 -> 40.06648 | F140: =G42 -> 478.81648 | G140: =G33 -> 146.25
C141: 114 | D141: =J69 -> -247.5 | E141: =G40 -> 40.06648 | F141: =G42 -> 478.81648 | G141: =G33 -> 146.25
C142: 115 | D142: =J70 -> -393.75 | E142: =G40 -> 40.06648 | F142: =G42 -> 478.81648 | G142: =G33 -> 146.25
C143: 116 | D143: =J71 -> -540 | E143: =G40 -> 40.06648 | F143: =G42 -> 478.81648 | G143: =G33 -> 146.25
C146: Receipt point | D146: Model week received | E146: Quantity
C147: Existing PO | D147: =IF(G44>0,Weeks_History+INDEX(Inputs!$L$40:$L$87,$D$5),Weeks_History) -> 105 | E147: =G44 -> 380
C148: New recommended order | D148: =Weeks_History+G39+1 -> 108 | E148: =G53 -> 760
...

Sheet Planner_Overview
A1: Planner Overview
A2: ="Snapshot week 105 | Target service level "&FIXED(TSL*100,1)&"% | Excess threshold "&Excess_WoC&" weeks of cover | Holding rate "&FIXED(Holding_Rate*100,0)&"%" -> Snapshot week 105 | Target service level 95.0% | Excess threshold 12 weeks of cover | Holding rate 20%
A4: Total SKUs | B4: Stockout Risk SKUs | C4: Reorder Required SKUs | D4: Excess Stock SKUs | E4: Healthy SKUs | F4: Total Inventory Value (on hand at cost) | G4: Portfolio WAPE
A5: =COUNTA(Replenishment_Plan!A7:A54) -> 48 | B5: =COUNTIF(Replenishment_Plan!$AG$7:$AG$54,"STOCKOUT RISK") -> 6 | C5: =COUNTIF(Replenishment_Plan!$AG$7:$AG$54,"REORDER REQUIRED") -> 11 | D5: =COUNTIF(Replenishment_Plan!$AG$7:$AG$54,"EXCESS STOCK") -> 8 | E5: =COUNTIF(Replenishment_Plan!$AG$7:$AG$54,"HEALTHY") -> 23 | F5: =SUM(Replenishment_Plan!AI7:AI54) -> 226230 | G5: =Portfolio_WAPE -> 0.14220804
A7: STATUS SUMMARY
A8: Status | B8: SKUs | C8: On-hand value (€) | D8: Recommended order units | E8: Recommended order value (€)
A9: STOCKOUT RISK | B9: =COUNTIF(Replenishment_Plan!$AG$7:$AG$54,A9) -> 6 | C9: =SUMIFS(Replenishment_Plan!$AI$7:$AI$54,Replenishment_Plan!$AG$7:$AG$54,A9) -> 3425 | D9: =SUMIFS(Replenishment_Plan!$AD$7:$AD$54,Replenishment_Plan!$AG$7:$AG$54,A9) -> 1925 | E9: =SUMPRODUCT((Replenishment_Plan!$AG$7:$AG$54=A9)*Replenishment_Plan!$AD$7:$AD$54*Replenishment_Plan!$V$7:$V$54) -> 25896 | G9: Non-healthy SKUs: | H9: =A5-E5 -> 25
A10: REORDER REQUIRED | B10: =COUNTIF(Replenishment_Plan!$AG$7:$AG$54,A10) -> 11 | C10: =SUMIFS(Replenishment_Plan!$AI$7:$AI$54,Replenishment_Plan!$AG$7:$AG$54,A10) -> 19713 | D10: =SUMIFS(Replenishment_Plan!$AD$7:$AD$54,Replenishment_Plan!$AG$7:$AG$54,A10) -> 3291 | E10: =SUMPRODUCT((Replenishment_Plan!$AG$7:$AG$54=A10)*Replenishment_Plan!$AD$7:$AD$54*Replenishment_Plan!$V$7:$V$54) -> 50703
A11: EXCESS STOCK | B11: =COUNTIF(Replenishment_Plan!$AG$7:$AG$54,A11) -> 8 | C11: =SUMIFS(Replenishment_Plan!$AI$7:$AI$54,Replenishment_Plan!$AG$7:$AG$54,A11) -> 96196 | D11: =SUMIFS(Replenishment_Plan!$AD$7:$AD$54,Replenishment_Plan!$AG$7:$AG$54,A11) -> 0 | E11: =SUMPRODUCT((Replenishment_Plan!$AG$7:$AG$54=A11)*Replenishment_Plan!$AD$7:$AD$54*Replenishment_Plan!$V$7:$V$54) -> 0
A12: HEALTHY | B12: =COUNTIF(Replenishment_Plan!$AG$7:$AG$54,A12) -> 23 | C12: =SUMIFS(Replenishment_Plan!$AI$7:$AI$54,Replenishment_Plan!$AG$7:$AG$54,A12) -> 106896 | D12: =SUMIFS(Replenishment_Plan!$AD$7:$AD$54,Replenishment_Plan!$AG$7:$AG$54,A12) -> 0 | E12: =SUMPRODUCT((Replenishment_Plan!$AG$7:$AG$54=A12)*Replenishment_Plan!$AD$7:$AD$54*Replenishment_Plan!$V$7:$V$54) -> 0
A13: Total | B13: =SUM(B9:B12) -> 48 | C13: =SUM(C9:C12) -> 226230 | D13: =SUM(D9:D12) -> 5216 | E13: =SUM(E9:E12) -> 76599
A32: PRODUCTS REQUIRING ATTENTION (ranked: stockout risk, then reorder, then excess; healthy SKUs are not listed)
A33: Rank | B33: SKU | C33: Product | D33: Status | E33: Weeks of Cover | F33: Inventory Position | G33: Reorder Point | H33: EOQ | I33: Recommended Order | J33: Reason
A34: 1 | B34: =IF($A34>$H$9,"",INDEX(Replenishment_Plan!$A$7:$A$54,MATCH($A34,Replenishment_Plan!$AK$7:$AK$54,0))) -> CLN-003 | C34: =IF($A34>$H$9,"",INDEX(Replenishment_Plan!$B$7:$B$54,MATCH($A34,Replenishment_Plan!$AK$7:$AK$54,0))) -> Eco Laundry Detergent 2L | D34: =IF($A34>$H$9,"",INDEX(Replenishment_Plan!$AG$7:$AG$54,MATCH($A34,Replenishment_Plan!$AK$7:$AK$54,0))) -> STOCKOUT RISK | E34: =IF($A34>$H$9,"",INDEX(Replenishment_Plan!$S$7:$S$54,MATCH($A34,Replenishment_Plan!$AK$7:$AK$54,0))) -> -0.52311757 | F34: =IF($A34>$H$9,"",INDEX(Replenishment_Plan!$R$7:$R$54,MATCH($A34,Replenishment_Plan!$AK$7:$AK$54,0))) -> -99 | G34: =IF($A34>$H$9,"",INDEX(Replenishment_Plan!$N$7:$N$54,MATCH($A34,Replenishment_Plan!$AK$7:$AK$54,0))) -> 236.55487 | H34: =IF($A34>$H$9,"",INDEX(Replenishment_Plan!$Z$7:$Z$54,MATCH($A34,Replenishment_Plan!$AK$7:$AK$54,0))) -> 618.632 | I34: =IF($A34>$H$9,"",INDEX(Replenishment_Plan!$AD$7:$AD$54,MATCH($A34,Replenishment_Plan!$AK$7:$AK$54,0))) -> 624 | J34: =IF($A34>$H$9,"",INDEX(Replenishment_Plan!$AH$7:$AH$54,MATCH($A34,Replenishment_Plan!$AK$7:$AK$54,0))) -> Projected inventory reaches zero in week 1, before a new order placed now could arrive (week 2). Inventory position of -99 units is at or below the reorder point of 237, so an order of 624 units is recommended (EOQ 619, case pack 6), but it cannot arrive in time: expedite supply or manage the shortfall.
A35: 2 | B35: =IF($A35>$H$9,"",INDEX(Replenishment_Plan!$A$7:$A$54,MATCH($A35,Replenishment_Plan!$AK$7:$AK$54,0))) -> BED-004 | C35: =IF($A35>$H$9,"",INDEX(Replenishment_Plan!$B$7:$B$54,MATCH($A35,Replenishment_Plan!$AK$7:$AK$54,0))) -> Fitted Sheet 180x200 | D35: =IF($A35>$H$9,"",INDEX(Replenishment_Plan!$AG$7:$AG$54,MATCH($A35,Replenishment_Plan!$AK$7:$AK$54,0))) -> STOCKOUT RISK | E35: =IF($A35>$H$9,"",INDEX(Replenishment_Plan!$S$7:$S$54,MATCH($A35,Replenishment_Plan!$AK$7:$AK$54,0))) -> -0.43076923 | F35: =IF($A35>$H$9,"",INDEX(Replenishment_Plan!$R$7:$R$54,MATCH($A35,Replenishment_Plan!$AK$7:$AK$54,0))) -> -35 | G35: =IF($A35>$H$9,"",INDEX(Replenishment_Plan!$N$7:$N$54,MATCH($A35,Replenishment_Plan!$AK$7:$AK$54,0))) -> 359.80143 | H35: =IF($A35>$H$9,"",INDEX(Replenishment_Plan!$Z$7:$Z$54,MATCH($A35,Replenishment_Plan!$AK$7:$AK$54,0))) -> 349.71793 | I35: =IF($A35>$H$9,"",INDEX(Replenishment_Plan!$AD$7:$AD$54,MATCH($A35,Replenishment_Plan!$AK$7:$AK$54,0))) -> 350 | J35: =IF($A35>$H$9,"",INDEX(Replenishment_Plan!$AH$7:$AH$54,MATCH($A35,Replenishment_Plan!$AK$7:$AK$54,0))) -> Projected inventory reaches zero in week 1, before a new order placed now could arrive (week 5). Inventory position of -35 units is at or below the reorder point of 360, so an order of 350 units is recommended (EOQ 350, case pack 10), but it cannot arrive in time: expedite supply or manage the shortfall.
A36: 3 | B36: =IF($A36>$H$9,"",INDEX(Replenishment_Plan!$A$7:$A$54,MATCH($A36,Replenishment_Plan!$AK$7:$AK$54,0))) -> KIT-003 | C36: =IF($A36>$H$9,"",INDEX(Replenishment_Plan!$B$7:$B$54,MATCH($A36,Replenishment_Plan!$AK$7:$AK$54,0))) -> Glass Food Storage Set 5pc | D36: =IF($A36>$H$9,"",INDEX(Replenishment_Plan!$AG$7:$AG$54,MATCH($A36,Replenishment_Plan!$AK$7:$AK$54,0))) -> STOCKOUT RISK | E36: =IF($A36>$H$9,"",INDEX(Replenishment_Plan!$S$7:$S$54,MATCH($A36,Replenishment_Plan!$AK$7:$AK$54,0))) -> -0.37844941 | F36: =IF($A36>$H$9,"",INDEX(Replenishment_Plan!$R$7:$R$54,MATCH($A36,Replenishment_Plan!$AK$7:$AK$54,0))) -> -36 | G36: =IF($A36>$H$9,"",INDEX(Replenishment_Plan!$N$7:$N$54,MATCH($A36,Replenishment_Plan!$AK$7:$AK$54,0))) -> 216.66261 | H36: =IF($A36>$H$9,"",INDEX(Replenishment_Plan!$Z$7:$Z$54,MATCH($A36,Replenishment_Plan!$AK$7:$AK$54,0))) -> 363.18957 | I36: =IF($A36>$H$9,"",INDEX(Replenishment_Plan!$AD$7:$AD$54,MATCH($A36,Replenishment_Plan!$AK$7:$AK$54,0))) -> 366 | J36: =IF($A36>$H$9,"",INDEX(Replenishment_Plan!$AH$7:$AH$54,MATCH($A36,Replenishment_Plan!$AK$7:$AK$54,0))) -> Projected inventory reaches zero in week 1, before a new order placed now could arrive (week 3). Inventory position of -36 units is at or below the reorder point of 217, so an order of 366 units is recommended (EOQ 363, case pack 6), but it cannot arrive in time: expedite supply or manage the shortfall.
A37: 4 | B37: =IF($A37>$H$9,"",INDEX(Replenishment_Plan!$A$7:$A$54,MATCH($A37,Replenishment_Plan!$AK$7:$AK$54,0))) -> BTH-005 | C37: =IF($A37>$H$9,"",INDEX(Replenishment_Plan!$B$7:$B$54,MATCH($A37,Replenishment_Plan!$AK$7:$AK$54,0))) -> Waffle Bathrobe M | D37: =IF($A37>$H$9,"",INDEX(Replenishment_Plan!$AG$7:$AG$54,MATCH($A37,Replenishment_Plan!$AK$7:$AK$54,0))) -> STOCKOUT RISK | E37: =IF($A37>$H$9,"",INDEX(Replenishment_Plan!$S$7:$S$54,MATCH($A37,Replenishment_Plan!$AK$7:$AK$54,0))) -> 2.2278481 | F37: =IF($A37>$H$9,"",INDEX(Replenishment_Plan!$R$7:$R$54,MATCH($A37,Replenishment_Plan!$AK$7:$AK$54,0))) -> 44 | G37: =IF($A37>$H$9,"",INDEX(Replenishment_Plan!$N$7:$N$54,MATCH($A37,Replenishment_Plan!$AK$7:$AK$54,0))) -> 79.104432 | H37: =IF($A37>$H$9,"",INDEX(Replenishment_Plan!$Z$7:$Z$54,MATCH($A37,Replenishment_Plan!$AK$7:$AK$54,0))) -> 120.17565 | I37: =IF($A37>$H$9,"",INDEX(Replenishment_Plan!$AD$7:$AD$54,MATCH($A37,Replenishment_Plan!$AK$7:$AK$54,0))) -> 125 | J37: =IF($A37>$H$9,"",INDEX(Replenishment_Plan!$AH$7:$AH$54,MATCH($A37,Replenishment_Plan!$AK$7:$AK$54,0))) -> Projected inventory reaches zero in week 1, before a new order placed now could arrive (week 4). Inventory position of 44 units is at or below the reorder point of 79, so an order of 125 units is recommended (EOQ 120, case pack 5), but it cannot arrive in time: expedite supply or manage the shortfall.
A38: 5 | B38: =IF($A38>$H$9,"",INDEX(Replenishment_Plan!$A$7:$A$54,MATCH($A38,Replenishment_Plan!$AK$7:$AK$54,0))) -> BTH-010 | C38: =IF($A38>$H$9,"",INDEX(Replenishment_Plan!$B$7:$B$54,MATCH($A38,Replenishment_Plan!$AK$7:$AK$54,0))) -> Microfibre Hair Towel | D38: =IF($A38>$H$9,"",INDEX(Replenishment_Plan!$AG$7:$AG$54,MATCH($A38,Replenishment_Plan!$AK$7:$AK$54,0))) -> STOCKOUT RISK | E38: =IF($A38>$H$9,"",INDEX(Replenishment_Plan!$S$7:$S$54,MATCH($A38,Replenishment_Plan!$AK$7:$AK$54,0))) -> 2.3354839 | F38: =IF($A38>$H$9,"",INDEX(Replenishment_Plan!$R$7:$R$54,MATCH($A38,Replenishment_Plan!$AK$7:$AK$54,0))) -> 181 | G38: =IF($A38>$H$9,"",INDEX(Replenishment_Plan!$N$7:$N$54,MATCH($A38,Replenishment_Plan!$AK$7:$AK$54,0))) -> 261.20322 | H38: =IF($A38>$H$9,"",INDEX(Replenishment_Plan!$Z$7:$Z$54,MATCH($A38,Replenishment_Plan!$AK$7:$AK$54,0))) -> 448.88751 | I38: =IF($A38>$H$9,"",INDEX(Replenishment_Plan!$AD$7:$AD$54,MATCH($A38,Replenishment_Plan!$AK$7:$AK$54,0))) -> 460 | J38: =IF($A38>$H$9,"",INDEX(Replenishment_Plan!$AH$7:$AH$54,MATCH($A38,Replenishment_Plan!$AK$7:$AK$54,0))) -> Projected inventory reaches zero in week 2, before a new order placed now could arrive (week 4). Inventory position of 181 units is at or below the reorder point of 261, so an order of 460 units is recommended (EOQ 449, case pack 20), but it cannot arrive in time: expedite supply or manage the shortfall.
